Workbook

Sheet Instrucciones
A1: BlackScale — Sistema de Scoring de Prospectos
A2: De 2.000 contactos a 500 mejores | Plataforma principal: LinkedIn Ads
A4: CÓMO FUNCIONA ESTA HOJA
A6: 1. Pega tus 2.000 contactos de Apollo en la hoja 'Contactos' (columnas B–J, azul claro)
A7: 2. El VA (o tú) llena las columnas K–R verificando señales en LinkedIn, Meta y Google (amarillo)
A8: 3. El Score y el Tier se calculan AUTOMÁTICAMENTE (verde claro)
A9: 4. La hoja 'Top 500' filtra automáticamente los mejores
A10: 5. La hoja 'Configuración' permite ajustar los pesos del scoring si quieres recalibrar
A12: CÓDIGO DE COLORES EN HOJA 'CONTACTOS'
A14: AZUL CLARO (col B–J) | B14: Datos que vienen de Apollo. Pegas y listo.
A15: AMARILLO (col K–R) | B15: Datos que llena el VA verificando señales en LinkedIn, Meta y Google.
A16: VERDE CLARO (col S–W) | B16: Score Tamaño, Score Industria, Score Cargo, Score Total y Tier — calculados AUTOMÁTICAMENTE. NO TOCAR.
A18: DEFINICIÓN DE TIERS
A20: Tier A — Score ≥ 12 | B20: Test manual esta semana. 30 mejores van directo.
A21: Tier B — Score 8 a 11 | B21: Cold email cuando tengas Smartlead. Cadencia 5 touches.
A22: Tier C — Score 6 a 7 | B22: Cold email volumen medio. Mensaje más genérico por industria.
A23: Descarte — Score < 6 | B23: Fuera de esta ronda. Considerar para nurturing pasivo.
A25: FLUJO RECOMENDADO
A27: Día 1 | B27: Pegar los 2.000 contactos en hoja 'Contactos'.
A28: Día 2-7 | B28: VA enriquece columnas K–R (5-7 días, ~$200 USD).
A29: Día 8 | B29: Aplicar filtro automático en hoja 'Top 500'. Validar tier A.
A30: Día 9 | B30: Arrancar test manual con 30 contactos top tier A.
A32: INSTRUCCIONES PARA EL VA
A34: Ver hoja 'Instrucciones VA' → | B34: Copia y pega esa hoja completa al VA.

Sheet Configuración
A1: Pesos del Scoring
A2: Edita los valores en columna B para recalibrar. El scoring se actualiza solo.
A4: Criterio | B4: Puntos | C4: Notas
A5: Pauta activa en LinkedIn Ads | B5: 12 | C5: Señal más fuerte. Ya invierte en plataforma. SUPER importante.
A6: Posts empresa: Semanal | B6: 12 | C6: Cuando 'Frecuencia posts' = 'Semanal'
A7: Posts empresa: Mensual | B7: 4 | C7: Cuando 'Frecuencia posts' = 'Mensual'
A8: Decision maker activo en LinkedIn (30 días) | B8: 12 | C8: Si publicó o comentó algo último mes
A9: Pauta activa en Meta Ads | B9: 4 | C9: Verificable en facebook.com/ads/library
A10: Pauta activa en Google Ads | B10: 8 | C10: Verificable en adstransparency.google.com
A11: Marketing Manager sin Head/Director | B11: 8 | C11: Equipo sub-estructurado, listo para tercerizar
A12: Vacante abierta en Marketing | B12: 8 | C12: Ya está intentando solucionar el dolor
A15: Score máximo posible | B15: =SUM(B5:B12)+B23+B27+B31-B7 -> 100 | C15: Asume Semanal + Cargo CEO/CMO + Tamaño 1-10 + Industria Tech
A18: Umbrales de Tier
A19: Tier A (mínimo) | B19: 60
A20: Tier B (mínimo) | B20: 40
A21: Tier C (mínimo) | B21: 24
A23: Tamaño empresa: 1-10 empleados | B23: 12 | C23: Startup / micro empresa — alta probabilidad de tercerizar marketing
A24: Tamaño empresa: 11-50 empleados | B24: 4 | C24: Empresa pequeña — buen fit para BlackScale
A25: Tamaño empresa: 51-200 empleados | B25: 0 | C25: Mediana empresa — ciclo de venta más largo
A27: Industria: Tech / SaaS / IT / Fintech (prioridad alta) | B27: 12 | C27: Mayor presupuesto para marketing digital
A28: Industria: Otras industrias | B28: 4 | C28: Prioridad estándar — menor probabilidad de fit inmediato
A30: Cargo del decisor | B30: Puntos | C30: Criterio de relevancia para contratar agencia
A31: Cargo: CEO / Founder / Owner / Director General / Presidente | B31: 12 | C31: Decisor final en empresas medianas/pequeñas — máxima autoridad
A32: Cargo: CMO / VP Marketing / Director de Marketing / Head of Marketing | B32: 12 | C32: Comprador directo del servicio — es su área
A33: Cargo: Marketing Manager / Gerente de Marketing / Growth / Demand Gen | B33: 8 | C33: Influenciador clave — puede recomendar o liderar la decisión
A34: Cargo: COO / CFO / CTO / Gerente General / General Manager | B34: 4 | C34: Involucrado en aprobación de presupuesto pero no es su área directa
A35: Cargo: Otro (Ventas, Ops, Técnico, etc.) | B35: 0 | C35: Bajo poder de decisión sobre marketing

Sheet Contactos
A1: h | B1: Nombre | C1: Cargo | D1: Empresa | E1: Email | F1: LinkedIn URL persona | G1: LinkedIn URL empresa | H1: Web empresa | I1: Industria | J1: Tamaño empresa | K1: Pauta LinkedIn | L1: Frecuencia posts empresa | M1: Decision maker activo LI | N1: Pauta Meta | O1: Pauta Google | P1: Marketing Manager sin Head | Q1: Vacante Marketing | R1: Notas | S1: Score Tamaño | T1: Score Industria | U1: Score Cargo | V1: Score | W1: Tier
A2: Auto | K2: VA llena | L2: VA llena | M2: VA llena | N2: VA llena | O2: VA llena | P2: VA llena | Q2: VA llena | R2: VA llena | S2: Auto | T2: Auto | U2: Auto | V2: Auto | W2: Auto
A3: =IF(B3="","",ROW()-2) -> 1 | B3: Mario | C3: Co-Founder & COO | D3: Plataform | E3: mario@plataform.com | F3: http://www.linkedin.com/in/mario-jose-marquez-olier | G3: http://www.linkedin.com/company/plataform | H3: https://plataform.com | I3: financial services | J3: 44 | K3: Sí | L3: Semanal | M3: Sí | N3: Sí | O3: Sí | P3: No | Q3: No | S3: =IF(B3="","",IF(ISNUMBER(J3),IF(J3<=10,'Configuración'!$B$23,IF(J3<=50,'Configuración'!$B$24,IF(J3<=200,'Configuración'!$B$25,0))),0)) -> 4 | T3: =IF(B3="","",IF(ISNUMBER(SEARCH("information technology",I3))+ISNUMBER(SEARCH("software",I3))+ISNUMBER(SEARCH("internet",I3))+ISNUMBER(SEARCH("computer",I3))+ISNUMBER(SEARCH("saas",I3))+ISNUMBER(SEARCH("fintech",I3))+ISNUMBER(SEARCH("information services",I3))+ISNUMBER(SEARCH("telecommunications",I3))>0,'Configuración'!$B$27,'Configuración'!$B$28)) -> 4 | U3: =IF(B3="","",IF(ISNUMBER(SEARCH("CEO",C3))+ISNUMBER(SEARCH("Founder",C3))+ISNUMBER(SEARCH("Owner",C3))+ISNUMBER(SEARCH("Dueño",C3))+ISNUMBER(SEARCH("Director General",C3))+ISNUMBER(SEARCH("Presidente",C3))+ISNUMBER(SEARCH("President",C3))>0,'Configuración'!$B$31,IF(ISNUMBER(SEARCH("CMO",C3))+ISNUMBER(SEARCH("Chief Marketing",C3))+ISNUMBER(SEARCH("VP Marketing",C3))+ISNUMBER(SEARCH("Director de Marketing",C3))+ISNUMBER(SEARCH("Director Marketing",C3))+ISNUMBER(SEARCH("Head of Marketing",C3))+ISNUMBER(SEARCH("Head Marketing",C3))>0,'Configuración'!$B$32,IF(ISNUMBER(SEARCH("Marketing Manager",C3))+ISNUMBER(SEARCH("Gerente de Marketing",C3))+ISNUMBER(SEARCH("Growth Manager",C3))+ISNUMBER(SEARCH("Demand Gen",C3))+ISNUMBER(SEARCH("Marketing Lead",C3))>0,'Configuración'!$B$33,IF(ISNUMBER(SEARCH("COO",C3))+ISNUMBER(SEARCH("CFO",C3))+ISNUMBER(SEARCH("CTO",C3))+ISNUMBER(SEARCH("Chief Operating",C3))+ISNUMBER(SEARCH("Chief Financial",C3))+ISNUMBER(SEARCH("Gerente General",C3))+ISNUMBER(SEARCH("General Manager",C3))>0,'Configuración'!$B$34,'Configuración'!$B$35))))) -> 12 | V3: =IF(B3="","",IF(K3="Sí",'Configuración'!$B$5,0)+IF(L3="Semanal",'Configuración'!$B$6,IF(L3="Mensual",'Configuración'!$B$7,0))+IF(M3="Sí",'Configuración'!$B$8,0)+IF(N3="Sí",'Configuración'!$B$9,0)+IF(O3="Sí",'Configuración'!$B$10,0)+IF(P3="Sí",'Configuración'!$B$11,0)+IF(Q3="Sí",'Configuración'!$B$12,0)+S3+T3+U3) -> 68 | W3: =IF(B3="","",IF(V3>='Configuración'!$B$19,"A",IF(V3>='Configuración'!$B$20,"B",IF(V3>='Configuración'!$B$21,"C","Descarte")))) -> A
A4: =IF(B4="","",ROW()-2) -> 2 | B4: Daniel | C4: CEO & Founder | D4: Talk Eva | E4: dani@talkeva.com | F4: http://www.linkedin.com/in/daniel-gonz%c3%a1lez-rico-65366ab1 | G4: http://www.linkedin.com/company/talk-eva | H4: https://talkeva.com | I4: information technology & services | J4: 2 | K4: No | L4: Inactivo | M4: Sí | N4: No | O4: No | P4: No | Q4: No | R4: Posible Tier 1 por ser Startup y el CEO es experto en marketing digital | S4: =IF(B4="","",IF(ISNUMBER(J4),IF(J4<=10,'Configuración'!$B$23,IF(J4<=50,'Configuración'!$B$24,IF(J4<=200,'Configuración'!$B$25,0))),0)) -> 12 | T4: =IF(B4="","",IF(ISNUMBER(SEARCH("information technology",I4))+ISNUMBER(SEARCH("software",I4))+ISNUMBER(SEARCH("internet",I4))+ISNUMBER(SEARCH("computer",I4))+ISNUMBER(SEARCH("saas",I4))+ISNUMBER(SEARCH("fintech",I4))+ISNUMBER(SEARCH("information services",I4))+ISNUMBER(SEARCH("telecommunications",I4))>0,'Configuración'!$B$27,'Configuración'!$B$28)) -> 12 | U4: =IF(B4="","",IF(ISNUMBER(SEARCH("CEO",C4))+ISNUMBER(SEARCH("Founder",C4))+ISNUMBER(SEARCH("Owner",C4))+ISNUMBER(SEARCH("Dueño",C4))+ISNUMBER(SEARCH("Director General",C4))+ISNUMBER(SEARCH("Presidente",C4))+ISNUMBER(SEARCH("President",C4))>0,'Configuración'!$B$31,IF(ISNUMBER(SEARCH("CMO",C4))+ISNUMBER(SEARCH("Chief Marketing",C4))+ISNUMBER(SEARCH("VP Marketing",C4))+ISNUMBER(SEARCH("Director de Marketing",C4))+ISNUMBER(SEARCH("Director Marketing",C4))+ISNUMBER(SEARCH("Head of Marketing",C4))+ISNUMBER(SEARCH("Head Marketing",C4))>0,'Configuración'!$B$32,IF(ISNUMBER(SEARCH("Marketing Manager",C4))+ISNUMBER(SEARCH("Gerente de Marketing",C4))+ISNUMBER(SEARCH("Growth Manager",C4))+ISNUMBER(SEARCH("Demand Gen",C4))+ISNUMBER(SEARCH("Marketing Lead",C4))>0,'Configuración'!$B$33,IF(ISNUMBER(SEARCH("COO",C4))+ISNUMBER(SEARCH("CFO",C4))+ISNUMBER(SEARCH("CTO",C4))+ISNUMBER(SEARCH("Chief Operating",C4))+ISNUMBER(SEARCH("Chief Financial",C4))+ISNUMBER(SEARCH("Gerente General",C4))+ISNUMBER(SEARCH("General Manager",C4))>0,'Configuración'!$B$34,'Configuración'!$B$35))))) -> 12 | V4: =IF(B4="","",IF(K4="Sí",'Configuración'!$B$5,0)+IF(L4="Semanal",'Configuración'!$B$6,IF(L4="Mensual",'Configuración'!$B$7,0))+IF(M4="Sí",'Configuración'!$B$8,0)+IF(N4="Sí",'Configuración'!$B$9,0)+IF(O4="Sí",'Configuración'!$B$10,0)+IF(P4="Sí",'Configuración'!$B$11,0)+IF(Q4="Sí",'Configuración'!$B$12,0)+S4+T4+U4) -> 48 | W4: =IF(B4="","",IF(V4>='Configuración'!$B$19,"A",IF(V4>='Configuración'!$B$20,"B",IF(V4>='Configuración'!$B$21,"C","Descarte")))) -> B
A5: =IF(B5="","",ROW()-2) -> 3 | B5: Viviana | C5: CEO | D5: OfficeFacil | E5: vbecerra@officefacil.com | F5: http://www.linkedin.com/in/viviana-becerra-239364322 | G5: http://www.linkedin.com/company/officefacil-com | H5: https://officefacil.com | I5: professional training & coaching | J5: 2 | K5: Sí | L5: Inactivo | M5: Sí | N5: No | O5: No | P5: Sí | Q5: No | S5: =IF(B5="","",IF(ISNUMBER(J5),IF(J5<=10,'Configuración'!$B$23,IF(J5<=50,'Configuración'!$B$24,IF(J5<=200,'Configuración'!$B$25,0))),0)) -> 12 | T5: =IF(B5="","",IF(ISNUMBER(SEARCH("information technology",I5))+ISNUMBER(SEARCH("software",I5))+ISNUMBER(SEARCH("internet",I5))+ISNUMBER(SEARCH("computer",I5))+ISNUMBER(SEARCH("saas",I5))+ISNUMBER(SEARCH("fintech",I5))+ISNUMBER(SEARCH("information services",I5))+ISNUMBER(SEARCH("telecommunications",I5))>0,'Configuración'!$B$27,'Configuración'!$B$28)) -> 4 | U5: =IF(B5="","",IF(ISNUMBER(SEARCH("CEO",C5))+ISNUMBER(SEARCH("Founder",C5))+ISNUMBER(SEARCH("Owner",C5))+ISNUMBER(SEARCH("Dueño",C5))+ISNUMBER(SEARCH("Director General",C5))+ISNUMBER(SEARCH("Presidente",C5))+ISNUMBER(SEARCH("President",C5))>0,'Configuración'!$B$31,IF(ISNUMBER(SEARCH("CMO",C5))+ISNUMBER(SEARCH("Chief Marketing",C5))+ISNUMBER(SEARCH("VP Marketing",C5))+ISNUMBER(SEARCH("Director de Marketing",C5))+ISNUMBER(SEARCH("Director Marketing",C5))+ISNUMBER(SEARCH("Head of Marketing",C5))+ISNUMBER(SEARCH("Head Marketing",C5))>0,'Configuración'!$B$32,IF(ISNUMBER(SEARCH("Marketing Manager",C5))+ISNUMBER(SEARCH("Gerente de Marketing",C5))+ISNUMBER(SEARCH("Growth Manager",C5))+ISNUMBER(SEARCH("Demand Gen",C5))+ISNUMBER(SEARCH("Marketing Lead",C5))>0,'Configuración'!$B$33,IF(ISNUMBER(SEARCH("COO",C5))+ISNUMBER(SEARCH("CFO",C5))+ISNUMBER(SEARCH("CTO",C5))+ISNUMBER(SEARCH("Chief Operating",C5))+ISNUMBER(SEARCH("Chief Financial",C5))+ISNUMBER(SEARCH("Gerente General",C5))+ISNUMBER(SEARCH("General Manager",C5))>0,'Configuración'!$B$34,'Configuración'!$B$35))))) -> 12 | V5: =IF(B5="","",IF(K5="Sí",'Configuración'!$B$5,0)+IF(L5="Semanal",'Configuración'!$B$6,IF(L5="Mensual",'Configuración'!$B$7,0))+IF(M5="Sí",'Configuración'!$B$8,0)+IF(N5="Sí",'Configuración'!$B$9,0)+IF(O5="Sí",'Configuración'!$B$10,0)+IF(P5="Sí",'Configuración'!$B$11,0)+IF(Q5="Sí",'Configuración'!$B$12,0)+S5+T5+U5) -> 60 | W5: =IF(B5="","",IF(V5>='Configuración'!$B$19,"A",IF(V5>='Configuración'!$B$20,"B",IF(V5>='Configuración'!$B$21,"C","Descarte")))) -> A
A6: =IF(B6="","",ROW()-2) -> 4 | B6: Carlos | C6: CEO - Cofundador | D6: Faroo Legal | E6: carlosfarias@faroolegal.com | F6: http://www.linkedin.com/in/carlos-felipe-arias-avila-6675b98a | G6: http://www.linkedin.com/company/faroolegal | H6: https://faroolegal.com | I6: legal services | J6: 11 | K6: No | L6: Semanal | M6: Sí | N6: No | O6: No | P6: Sí | Q6: No | S6: =IF(B6="","",IF(ISNUMBER(J6),IF(J6<=10,'Configuración'!$B$23,IF(J6<=50,'Configuración'!$B$24,IF(J6<=200,'Configuración'!$B$25,0))),0)) -> 4 | T6: =IF(B6="","",IF(ISNUMBER(SEARCH("information technology",I6))+ISNUMBER(SEARCH("software",I6))+ISNUMBER(SEARCH("internet",I6))+ISNUMBER(SEARCH("computer",I6))+ISNUMBER(SEARCH("saas",I6))+ISNUMBER(SEARCH("fintech",I6))+ISNUMBER(SEARCH("information services",I6))+ISNUMBER(SEARCH("telecommunications",I6))>0,'Configuración'!$B$27,'Configuración'!$B$28)) -> 4 | U6: =IF(B6="","",IF(ISNUMBER(SEARCH("CEO",C6))+ISNUMBER(SEARCH("Founder",C6))+ISNUMBER(SEARCH("Owner",C6))+ISNUMBER(SEARCH("Dueño",C6))+ISNUMBER(SEARCH("Director General",C6))+ISNUMBER(SEARCH("Presidente",C6))+ISNUMBER(SEARCH("President",C6))>0,'Configuración'!$B$31,IF(ISNUMBER(SEARCH("CMO",C6))+ISNUMBER(SEARCH("Chief Marketing",C6))+ISNUMBER(SEARCH("VP Marketing",C6))+ISNUMBER(SEARCH("Director de Marketing",C6))+ISNUMBER(SEARCH("Director Marketing",C6))+ISNUMBER(SEARCH("Head of Marketing",C6))+ISNUMBER(SEARCH("Head Marketing",C6))>0,'Configuración'!$B$32,IF(ISNUMBER(SEARCH("Marketing Manager",C6))+ISNUMBER(SEARCH("Gerente de Marketing",C6))+ISNUMBER(SEARCH("Growth Manager",C6))+ISNUMBER(SEARCH("Demand Gen",C6))+ISNUMBER(SEARCH("Marketing Lead",C6))>0,'Configuración'!$B$33,IF(ISNUMBER(SEARCH("COO",C6))+ISNUMBER(SEARCH("CFO",C6))+ISNUMBER(SEARCH("CTO",C6))+ISNUMBER(SEARCH("Chief Operating",C6))+ISNUMBER(SEARCH("Chief Financial",C6))+ISNUMBER(SEARCH("Gerente General",C6))+ISNUMBER(SEARCH("General Manager",C6))>0,'Configuración'!$B$34,'Configuración'!$B$35))))) -> 12 | V6: =IF(B6="","",IF(K6="Sí",'Configuración'!$B$5,0)+IF(L6="Semanal",'Configuración'!$B$6,IF(L6="Mensual",'Configuración'!$B$7,0))+IF(M6="Sí",'Configuración'!$B$8,0)+IF(N6="Sí",'Configuración'!$B$9,0)+IF(O6="Sí",'Configuración'!$B$10,0)+IF(P6="Sí",'Configuración'!$B$11,0)+IF(Q6="Sí",'Configuración'!$B$12,0)+S6+T6+U6) -> 52 | W6: =IF(B6="","",IF(V6>='Configuración'!$B$19,"A",IF(V6>='Configuración'!$B$20,"B",IF(V6>='Configuración'!$B$21,"C","Descarte")))) -> B
A7: =IF(B7="","",ROW()-2) -> 5 | B7: Daniel | C7: Chief Executive Officer | D7: CAXDAC | E7: danino@caxdac.com | F7: http://www.linkedin.com/in/daniel-ni%c3%b1o-tarazona-89980082 | G7: http://www.linkedin.com/company/caxdac-caja-de-auxilios-y-de-prestaciones-de-acdac | H7: https://caxdac.com | I7: financial services | J7: 35 | K7: No | L7: Inactivo | M7: No | N7: No | O7: No | P7: No | Q7: No | S7: =IF(B7="","",IF(ISNUMBER(J7),IF(J7<=10,'Configuración'!$B$23,IF(J7<=50,'Configuración'!$B$24,IF(J7<=200,'Configuración'!$B$25,0))),0)) -> 4 | T7: =IF(B7="","",IF(ISNUMBER(SEARCH("information technology",I7))+ISNUMBER(SEARCH("software",I7))+ISNUMBER(SEARCH("internet",I7))+ISNUMBER(SEARCH("computer",I7))+ISNUMBER(SEARCH("saas",I7))+ISNUMBER(SEARCH("fintech",I7))+ISNUMBER(SEARCH("information services",I7))+ISNUMBER(SEARCH("telecommunications",I7))>0,'Configuración'!$B$27,'Configuración'!$B$28)) -> 4 | U7: =IF(B7="","",IF(ISNUMBER(SEARCH("CEO",C7))+ISNUMBER(SEARCH("Founder",C7))+ISNUMBER(SEARCH("Owner",C7))+ISNUMBER(SEARCH("Dueño",C7))+ISNUMBER(SEARCH("Director General",C7))+ISNUMBER(SEARCH("Presidente",C7))+ISNUMBER(SEARCH("President",C7))>0,'Configuración'!$B$31,IF(ISNUMBER(SEARCH("CMO",C7))+ISNUMBER(SEARCH("Chief Marketing",C7))+ISNUMBER(SEARCH("VP Marketing",C7))+ISNUMBER(SEARCH("Director de Marketing",C7))+ISNUMBER(SEARCH("Director Marketing",C7))+ISNUMBER(SEARCH("Head of Marketing",C7))+ISNUMBER(SEARCH("Head Marketing",C7))>0,'Configuración'!$B$32,IF(ISNUMBER(SEARCH("Marketing Manager",C7))+ISNUMBER(SEARCH("Gerente de Marketing",C7))+ISNUMBER(SEARCH("Growth Manager",C7))+ISNUMBER(SEARCH("Demand Gen",C7))+ISNUMBER(SEARCH("Marketing Lead",C7))>0,'Configuración'!$B$33,IF(ISNUMBER(SEARCH("COO",C7))+ISNUMBER(SEARCH("CFO",C7))+ISNUMBER(SEARCH("CTO",C7))+ISNUMBER(SEARCH("Chief Operating",C7))+ISNUMBER(SEARCH("Chief Financial",C7))+ISNUMBER(SEARCH("Gerente General",C7))+ISNUMBER(SEARCH("General Manager",C7))>0,'Configuración'!$B$34,'Configuración'!$B$35))))) -> 0 | V7: =IF(B7="","",IF(K7="Sí",'Configuración'!$B$5,0)+IF(L7="Semanal",'Configuración'!$B$6,IF(L7="Mensual",'Configuración'!$B$7,0))+IF(M7="Sí",'Configuración'!$B$8,0)+IF(N7="Sí",'Configuración'!$B$9,0)+IF(O7="Sí",'Configuración'!$B$10,0)+IF(P7="Sí",'Configuración'!$B$11,0)+IF(Q7="Sí",'Configuración'!$B$12,0)+S7+T7+U7) -> 8 | W7: =IF(B7="","",IF(V7>='Configuración'!$B$19,"A",IF(V7>='Configuración'!$B$20,"B",IF(V7>='Configuración'!$B$21,"C","Descarte")))) -> Descarte
A8: =IF(B8="","",ROW()-2) -> 6 | B8: Daniel | C8: Co - Founder | D8: Inkoms | E8: daniel@inkoms.com | F8: http://www.linkedin.com/in/danielgomezvelez | G8: http://www.linkedin.com/company/inkoms | H8: https://inkoms.com | I8: investment management | J8: 4 | K8: No | L8: Inactivo | M8: No | N8: No | O8: No | Q8: No | S8: =IF(B8="","",IF(ISNUMBER(J8),IF(J8<=10,'Configuración'!$B$23,IF(J8<=50,'Configuración'!$B$24,IF(J8<=200,'Configuración'!$B$25,0))),0)) -> 12 | T8: =IF(B8="","",IF(ISNUMBER(SEARCH("information technology",I8))+ISNUMBER(SEARCH("software",I8))+ISNUMBER(SEARCH("internet",I8))+ISNUMBER(SEARCH("computer",I8))+ISNUMBER(SEARCH("saas",I8))+ISNUMBER(SEARCH("fintech",I8))+ISNUMBER(SEARCH("information services",I8))+ISNUMBER(SEARCH("telecommunications",I8))>0,'Configuración'!$B$27,'Configuración'!$B$28)) -> 4 | U8: =IF(B8="","",IF(ISNUMBER(SEARCH("CEO",C8))+ISNUMBER(SEARCH("Founder",C8))+ISNUMBER(SEARCH("Owner",C8))+ISNUMBER(SEARCH("Dueño",C8))+ISNUMBER(SEARCH("Director General",C8))+ISNUMBER(SEARCH("Presidente",C8))+ISNUMBER(SEARCH("President",C8))>0,'Configuración'!$B$31,IF(ISNUMBER(SEARCH("CMO",C8))+ISNUMBER(SEARCH("Chief Marketing",C8))+ISNUMBER(SEARCH("VP Marketing",C8))+ISNUMBER(SEARCH("Director de Marketing",C8))+ISNUMBER(SEARCH("Director Marketing",C8))+ISNUMBER(SEARCH("Head of Marketing",C8))+ISNUMBER(SEARCH("Head Marketing",C8))>0,'Configuración'!$B$32,IF(ISNUMBER(SEARCH("Marketing Manager",C8))+ISNUMBER(SEARCH("Gerente de Marketing",C8))+ISNUMBER(SEARCH("Growth Manager",C8))+ISNUMBER(SEARCH("Demand Gen",C8))+ISNUMBER(SEARCH("Marketing Lead",C8))>0,'Configuración'!$B$33,IF(ISNUMBER(SEARCH("COO",C8))+ISNUMBER(SEARCH("CFO",C8))+ISNUMBER(SEARCH("CTO",C8))+ISNUMBER(SEARCH("Chief Operating",C8))+ISNUMBER(SEARCH("Chief Financial",C8))+ISNUMBER(SEARCH("Gerente General",C8))+ISNUMBER(SEARCH("General Manager",C8))>0,'Configuración'!$B$34,'Configuración'!$B$35))))) -> 12 | V8: =IF(B8="","",IF(K8="Sí",'Configuración'!$B$5,0)+IF(L8="Semanal",'Configuración'!$B$6,IF(L8="Mensual",'Configuración'!$B$7,0))+IF(M8="Sí",'Configuración'!$B$8,0)+IF(N8="Sí",'Configuración'!$B$9,0)+IF(O8="Sí",'Configuración'!$B$10,0)+IF(P8="Sí",'Configuración'!$B$11,0)+IF(Q8="Sí",'Configuración'!$B$12,0)+S8+T8+U8) -> 28 | W8: =IF(B8="","",IF(V8>='Configuración'!$B$19,"A",IF(V8>='Configuración'!$B$20,"B",IF(V8>='Configuración'!$B$21,"C","Descarte")))) -> C
A9: =IF(B9="","",ROW()-2) -> 7 | B9: Sebastian | C9: Head of Sales Colombia | D9: Finnecto | E9: sebastian.gasca@finnecto.com | F9: http://www.linkedin.com/in/sebastian-gasca | G9: http://www.linkedin.com/company/finnecto | H9: https://finnecto.com | I9: information technology & services | J9: 18 | K9: No | L9: Semanal | M9: Sí | N9: No | O9: No | Q9: No | S9: =IF(B9="","",IF(ISNUMBER(J9),IF(J9<=10,'Configuración'!$B$23,IF(J9<=50,'Configuración'!$B$24,IF(J9<=200,'Configuración'!$B$25,0))),0)) -> 4 | T9: =IF(B9="","",IF(ISNUMBER(SEARCH("information technology",I9))+ISNUMBER(SEARCH("software",I9))+ISNUMBER(SEARCH("internet",I9))+ISNUMBER(SEARCH("computer",I9))+ISNUMBER(SEARCH("saas",I9))+ISNUMBER(SEARCH("fintech",I9))+ISNUMBER(SEARCH("information services",I9))+ISNUMBER(SEARCH("telecommunications",I9))>0,'Configuración'!$B$27,'Configuración'!$B$28)) -> 12 | U9: =IF(B9="","",IF(ISNUMBER(SEARCH("CEO",C9))+ISNUMBER(SEARCH("Founder",C9))+ISNUMBER(SEARCH("Owner",C9))+ISNUMBER(SEARCH("Dueño",C9))+ISNUMBER(SEARCH("Director General",C9))+ISNUMBER(SEARCH("Presidente",C9))+ISNUMBER(SEARCH("President",C9))>0,'Configuración'!$B$31,IF(ISNUMBER(SEARCH("CMO",C9))+ISNUMBER(SEARCH("Chief Marketing",C9))+ISNUMBER(SEARCH("VP Marketing",C9))+ISNUMBER(SEARCH("Director de Marketing",C9))+ISNUMBER(SEARCH("Director Marketing",C9))+ISNUMBER(SEARCH("Head of Marketing",C9))+ISNUMBER(SEARCH("Head Marketing",C9))>0,'Configuración'!$B$32,IF(ISNUMBER(SEARCH("Marketing Manager",C9))+ISNUMBER(SEARCH("Gerente de Marketing",C9))+ISNUMBER(SEARCH("Growth Manager",C9))+ISNUMBER(SEARCH("Demand Gen",C9))+ISNUMBER(SEARCH("Marketing Lead",C9))>0,'Configuración'!$B$33,IF(ISNUMBER(SEARCH("COO",C9))+ISNUMBER(SEARCH("CFO",C9))+ISNUMBER(SEARCH("CTO",C9))+ISNUMBER(SEARCH("Chief Operating",C9))+ISNUMBER(SEARCH("Chief Financial",C9))+ISNUMBER(SEARCH("Gerente General",C9))+ISNUMBER(SEARCH("General Manager",C9))>0,'Configuración'!$B$34,'Configuración'!$B$35))))) -> 0 | V9: =IF(B9="","",IF(K9="Sí",'Configuración'!$B$5,0)+IF(L9="Semanal",'Configuración'!$B$6,IF(L9="Mensual",'Configuración'!$B$7,0))+IF(M9="Sí",'Configuración'!$B$8,0)+IF(N9="Sí",'Configuración'!$B$9,0)+IF(O9="Sí",'Configuración'!$B$10,0)+IF(P9="Sí",'Configuración'!$B$11,0)+IF(Q9="Sí",'Configuración'!$B$12,0)+S9+T9+U9) -> 40 | W9: =IF(B9="","",IF(V9>='Configuración'!$B$19,"A",IF(V9>='Configuración'!$B$20,"B",IF(V9>='Configuración'!$B$21,"C","Descarte")))) -> B
A10: =IF(B10="","",ROW()-2) -> 8 | B10: Jorge | C10: CEO | D10: ELSA | E10: juribe@elsa360.com | F10: http://www.linkedin.com/in/jorge-uribe-cardozo-16466740 | G10: http://www.linkedin.com/company/elsa360 | H10: https://elsa360.com | I10: sports | J10: 7 | K10: No | L10: Mensual | M10: Sí | N10: No | O10: No | Q10: No | S10: =IF(B10="","",IF(ISNUMBER(J10),IF(J10<=10,'Configuración'!$B$23,IF(J10<=50,'Configuración'!$B$24,IF(J10<=200,'Configuración'!$B$25,0))),0)) -> 12 | T10: =IF(B10="","",IF(ISNUMBER(SEARCH("information technology",I10))+ISNUMBER(SEARCH("software",I10))+ISNUMBER(SEARCH("internet",I10))+ISNUMBER(SEARCH("computer",I10))+ISNUMBER(SEARCH("saas",I10))+ISNUMBER(SEARCH("fintech",I10))+ISNUMBER(SEARCH("information services",I10))+ISNUMBER(SEARCH("telecommunications",I10))>0,'Configuración'!$B$27,'Configuración'!$B$28)) -> 4 | U10: =IF(B10="","",IF(ISNUMBER(SEARCH("CEO",C10))+ISNUMBER(SEARCH("Founder",C10))+ISNUMBER(SEARCH("Owner",C10))+ISNUMBER(SEARCH("Dueño",C10))+ISNUMBER(SEARCH("Director General",C10))+ISNUMBER(SEARCH("Presidente",C10))+ISNUMBER(SEARCH("President",C10))>0,'Configuración'!$B$31,IF(ISNUMBER(SEARCH("CMO",C10))+ISNUMBER(SEARCH("Chief Marketing",C10))+ISNUMBER(SEARCH("VP Marketing",C10))+ISNUMBER(SEARCH("Director de Marketing",C10))+ISNUMBER(SEARCH("Director Marketing",C10))+ISNUMBER(SEARCH("Head of Marketing",C10))+ISNUMBER(SEARCH("Head Marketing",C10))>0,'Configuración'!$B$32,IF(ISNUMBER(SEARCH("Marketing Manager",C10))+ISNUMBER(SEARCH("Gerente de Marketing",C10))+ISNUMBER(SEARCH("Growth Manager",C10))+ISNUMBER(SEARCH("Demand Gen",C10))+ISNUMBER(SEARCH("Marketing Lead",C10))>0,'Configuración'!$B$33,IF(ISNUMBER(SEARCH("COO",C10))+ISNUMBER(SEARCH("CFO",C10))+ISNUMBER(SEARCH("CTO",C10))+ISNUMBER(SEARCH("Chief Operating",C10))+ISNUMBER(SEARCH("Chief Financial",C10))+ISNUMBER(SEARCH("Gerente General",C10))+ISNUMBER(SEARCH("General Manager",C10))>0,'Configuración'!$B$34,'Configuración'!$B$35))))) -> 12 | V10: =IF(B10="","",IF(K10="Sí",'Configuración'!$B$5,0)+IF(L10="Semanal",'Configuración'!$B$6,IF(L10="Mensual",'Configuración'!$B$7,0))+IF(M10="Sí",'Configuración'!$B$8,0)+IF(N10="Sí",'Configuración'!$B$9,0)+IF(O10="Sí",'Configuración'!$B$10,0)+IF(P10="Sí",'Configuración'!$B$11,0)+IF(Q10="Sí",'Configuración'!$B$12,0)+S10+T10+U10) -> 44 | W10: =IF(B10="","",IF(V10>='Configuración'!$B$19,"A",IF(V10>='Configuración'!$B$20,"B",IF(V10>='Configuración'!$B$21,"C","Descarte")))) -> B
A11: =IF(B11="","",ROW()-2) -> 9 | B11: Juan | C11: Founder | D11: Complemento 360 Colombia | E11: jacobo.paramo@complemento360.com | F11: http://www.linkedin.com/in/juan-jacobo-p%c3%a1ramo-b47a1322 | G11: http://www.linkedin.com/company/complemento360colombia | H11: https://complemento360.com | I11: information technology & services | J11: 30 | K11: No | L11: Semanal | M11: Sí | N11: No | O11: No | Q11: No | S11: =IF(B11="","",IF(ISNUMBER(J11),IF(J11<=10,'Configuración'!$B$23,IF(J11<=50,'Configuración'!$B$24,IF(J11<=200,'Configuración'!$B$25,0))),0)) -> 4 | T11: =IF(B11="","",IF(ISNUMBER(SEARCH("information technology",I11))+ISNUMBER(SEARCH("software",I11))+ISNUMBER(SEARCH("internet",I11))+ISNUMBER(SEARCH("computer",I11))+ISNUMBER(SEARCH("saas",I11))+ISNUMBER(SEARCH("fintech",I11))+ISNUMBER(SEARCH("information services",I11))+ISNUMBER(SEARCH("telecommunications",I11))>0,'Configuración'!$B$27,'Configuración'!$B$28)) -> 12 | U11: =IF(B11="","",IF(ISNUMBER(SEARCH("CEO",C11))+ISNUMBER(SEARCH("Founder",C11))+ISNUMBER(SEARCH("Owner",C11))+ISNUMBER(SEARCH("Dueño",C11))+ISNUMBER(SEARCH("Director General",C11))+ISNUMBER(SEARCH("Presidente",C11))+ISNUMBER(SEARCH("President",C11))>0,'Configuración'!$B$31,IF(ISNUMBER(SEARCH("CMO",C11))+ISNUMBER(SEARCH("Chief Marketing",C11))+ISNUMBER(SEARCH("VP Marketing",C11))+ISNUMBER(SEARCH("Director de Marketing",C11))+ISNUMBER(SEARCH("Director Marketing",C11))+ISNUMBER(SEARCH("Head of Marketing",C11))+ISNUMBER(SEARCH("Head Marketing",C11))>0,'Configuración'!$B$32,IF(ISNUMBER(SEARCH("Marketing Manager",C11))+ISNUMBER(SEARCH("Gerente de Marketing",C11))+ISNUMBER(SEARCH("Growth Manager",C11))+ISNUMBER(SEARCH("Demand Gen",C11))+ISNUMBER(SEARCH("Marketing Lead",C11))>0,'Configuración'!$B$33,IF(ISNUMBER(SEARCH("COO",C11))+ISNUMBER(SEARCH("CFO",C11))+ISNUMBER(SEARCH("CTO",C11))+ISNUMBER(SEARCH("Chief Operating",C11))+ISNUMBER(SEARCH("Chief Financial",C11))+ISNUMBER(SEARCH("Gerente General",C11))+ISNUMBER(SEARCH("General Manager",C11))>0,'Configuración'!$B$34,'Configuración'!$B$35))))) -> 12 | V11: =IF(B11="","",IF(K11="Sí",'Configuración'!$B$5,0)+IF(L11="Semanal",'Configuración'!$B$6,IF(L11="Mensual",'Configuración'!$B$7,0))+IF(M11="Sí",'Configuración'!$B$8,0)+IF(N11="Sí",'Configuración'!$B$9,0)+IF(O11="Sí",'Configuración'!$B$10,0)+IF(P11="Sí",'Configuración'!$B$11,0)+IF(Q11="Sí",'Configuración'!$B$12,0)+S11+T11+U11) -> 52 | W11: =IF(B11="","",IF(V11>='Configuración'!$B$19,"A",IF(V11>='Configuración'!$B$20,"B",IF(V11>='Configuración'!$B$21,"C","Descarte")))) -> B
A12: =IF(B12="","",ROW()-2) -> 10 | B12: Andres | C12: Co-founder & Chief Corporate Officer | D12: Pantera Makers | E12: andres@panteramakers.com | F12: http://www.linkedin.com/in/andres-mejia-99337215 | G12: http://www.linkedin.com/company/panteramakers | H12: https://panteramakers.com | I12: management consulting | J12: 39 | K12: Sí | L12: Semanal | M12: Sí | N12: No | O12: No | Q12: No | S12: =IF(B12="","",IF(ISNUMBER(J12),IF(J12<=10,'Configuración'!$B$23,IF(J12<=50,'Configuración'!$B$24,IF(J12<=200,'Configuración'!$B$25,0))),0)) -> 4 | T12: =IF(B12="","",IF(ISNUMBER(SEARCH("information technology",I12))+ISNUMBER(SEARCH("software",I12))+ISNUMBER(SEARCH("internet",I12))+ISNUMBER(SEARCH("computer",I12))+ISNUMBER(SEARCH("saas",I12))+ISNUMBER(SEARCH("fintech",I12))+ISNUMBER(SEARCH("information services",I12))+ISNUMBER(SEARCH("telecommunications",I12))>0,'Configuración'!$B$27,'Configuración'!$B$28)) -> 4 | U12: =IF(B12="","",IF(ISNUMBER(SEARCH("CEO",C12))+ISNUMBER(SEARCH("Founder",C12))+ISNUMBER(SEARCH("Owner",C12))+ISNUMBER(SEARCH("Dueño",C12))+ISNUMBER(SEARCH("Director General",C12))+ISNUMBER(SEARCH("Presidente",C12))+ISNUMBER(SEARCH("President",C12))>0,'Configuración'!$B$31,IF(ISNUMBER(SEARCH("CMO",C12))+ISNUMBER(SEARCH("Chief Marketing",C12))+ISNUMBER(SEARCH("VP Marketing",C12))+ISNUMBER(SEARCH("Director de Marketing",C12))+ISNUMBER(SEARCH("Director Marketing",C12))+ISNUMBER(SEARCH("Head of Marketing",C12))+ISNUMBER(SEARCH("Head Marketing",C12))>0,'Configuración'!$B$32,IF(ISNUMBER(SEARCH("Marketing Manager",C12))+ISNUMBER(SEARCH("Gerente de Marketing",C12))+ISNUMBER(SEARCH("Growth Manager",C12))+ISNUMBER(SEARCH("Demand Gen",C12))+ISNUMBER(SEARCH("Marketing Lead",C12))>0,'Configuración'!$B$33,IF(ISNUMBER(SEARCH("COO",C12))+ISNUMBER(SEARCH("CFO",C12))+ISNUMBER(SEARCH("CTO",C12))+ISNUMBER(SEARCH("Chief Operating",C12))+ISNUMBER(SEARCH("Chief Financial",C12))+ISNUMBER(SEARCH("Gerente General",C12))+ISNUMBER(SEARCH("General Manager",C12))>0,'Configuración'!$B$34,'Configuración'!$B$35))))) -> 12 | V12: =IF(B12="","",IF(K12="Sí",'Configuración'!$B$5,0)+IF(L12="Semanal",'Configuración'!$B$6,IF(L12="Mensual",'Configuración'!$B$7,0))+IF(M12="Sí",'Configuración'!$B$8,0)+IF(N12="Sí",'Configuración'!$B$9,0)+IF(O12="Sí",'Configuración'!$B$10,0)+IF(P12="Sí",'Configuración'!$B$11,0)+IF(Q12="Sí",'Configuración'!$B$12,0)+S12+T12+U12) -> 56 | W12: =IF(B12="","",IF(V12>='Configuración'!$B$19,"A",IF(V12>='Configuración'!$B$20,"B",IF(V12>='Configuración'!$B$21,"C","Descarte")))) -> B
A13: =IF(B13="","",ROW()-2) -> 11 | B13: Andres | C13: CEO | D13: The Talent Tree S.A.S | E13: andres.morales@thetalenttree.com.co | F13: http://www.linkedin.com/in/andres-mauricio-morales | G13: http://www.linkedin.com/school/thetalenttreebyikenga-finanzaspersonales | H13: https://thetalenttree.com.co | I13: professional training & coaching | J13: 9 | K13: No | L13: Inactivo | M13: Sí | N13: Sí | O13: No | Q13: No | S13: =IF(B13="","",IF(ISNUMBER(J13),IF(J13<=10,'Configuración'!$B$23,IF(J13<=50,'Configuración'!$B$24,IF(J13<=200,'Configuración'!$B$25,0))),0)) -> 12 | T13: =IF(B13="","",IF(ISNUMBER(SEARCH("information technology",I13))+ISNUMBER(SEARCH("software",I13))+ISNUMBER(SEARCH("internet",I13))+ISNUMBER(SEARCH("computer",I13))+ISNUMBER(SEARCH("saas",I13))+ISNUMBER(SEARCH("fintech",I13))+ISNUMBER(SEARCH("information services",I13))+ISNUMBER(SEARCH("telecommunications",I13))>0,'Configuración'!$B$27,'Configuración'!$B$28)) -> 4 | U13: =IF(B13="","",IF(ISNUMBER(SEARCH("CEO",C13))+ISNUMBER(SEARCH("Founder",C13))+ISNUMBER(SEARCH("Owner",C13))+ISNUMBER(SEARCH("Dueño",C13))+ISNUMBER(SEARCH("Director General",C13))+ISNUMBER(SEARCH("Presidente",C13))+ISNUMBER(SEARCH("President",C13))>0,'Configuración'!$B$31,IF(ISNUMBER(SEARCH("CMO",C13))+ISNUMBER(SEARCH("Chief Marketing",C13))+ISNUMBER(SEARCH("VP Marketing",C13))+ISNUMBER(SEARCH("Director de Marketing",C13))+ISNUMBER(SEARCH("Director Marketing",C13))+ISNUMBER(SEARCH("Head of Marketing",C13))+ISNUMBER(SEARCH("Head Marketing",C13))>0,'Configuración'!$B$32,IF(ISNUMBER(SEARCH("Marketing Manager",C13))+ISNUMBER(SEARCH("Gerente de Marketing",C13))+ISNUMBER(SEARCH("Growth Manager",C13))+ISNUMBER(SEARCH("Demand Gen",C13))+ISNUMBER(SEARCH("Marketing Lead",C13))>0,'Configuración'!$B$33,IF(ISNUMBER(SEARCH("COO",C13))+ISNUMBER(SEARCH("CFO",C13))+ISNUMBER(SEARCH("CTO",C13))+ISNUMBER(SEARCH("Chief Operating",C13))+ISNUMBER(SEARCH("Chief Financial",C13))+ISNUMBER(SEARCH("Gerente General",C13))+ISNUMBER(SEARCH("General Manager",C13))>0,'Configuración'!$B$34,'Configuración'!$B$35))))) -> 12 | V13: =IF(B13="","",IF(K13="Sí",'Configuración'!$B$5,0)+IF(L13="Semanal",'Configuración'!$B$6,IF(L13="Mensual",'Configuración'!$B$7,0))+IF(M13="Sí",'Configuración'!$B$8,0)+IF(N13="Sí",'Configuración'!$B$9,0)+IF(O13="Sí",'Configuración'!$B$10,0)+IF(P13="Sí",'Configuración'!$B$11,0)+IF(Q13="Sí",'Configuración'!$B$12,0)+S13+T13+U13) -> 44 | W13: =IF(B13="","",IF(V13>='Configuración'!$B$19,"A",IF(V13>='Configuración'!$B$20,"B",IF(V13>='Configuración'!$B$21,"C","Descarte")))) -> B
A14: =IF(B14="","",ROW()-2) -> 12 | B14: Dora | C14: CEO | D14: PlugIT Solutions | E14: dora.mejia@plugitsolutions.com.co | F14: http://www.linkedin.com/in/dora-mejia-1231302a | G14: http://www.linkedin.com/company/plugit-solutions | H14: https://plugitsolutions.com.co | I14: information technology & services | J14: 3 | M14: Sí | R14: No se encuentra el perfil en Linkedin ni la página de la empresa | S14: =IF(B14="","",IF(ISNUMBER(J14),IF(J14<=10,'Configuración'!$B$23,IF(J14<=50,'Configuración'!$B$24,IF(J14<=200,'Configuración'!$B$25,0))),0)) -> 12 | T14: =IF(B14="","",IF(ISNUMBER(SEARCH("information technology",I14))+ISNUMBER(SEARCH("software",I14))+ISNUMBER(SEARCH("internet",I14))+ISNUMBER(SEARCH("computer",I14))+ISNUMBER(SEARCH("saas",I14))+ISNUMBER(SEARCH("fintech",I14))+ISNUMBER(SEARCH("information services",I14))+ISNUMBER(SEARCH("telecommunications",I14))>0,'Configuración'!$B$27,'Configuración'!$B$28)) -> 12 | U14: =IF(B14="","",IF(ISNUMBER(SEARCH("CEO",C14))+ISNUMBER(SEARCH("Founder",C14))+ISNUMBER(SEARCH("Owner",C14))+ISNUMBER(SEARCH("Dueño",C14))+ISNUMBER(SEARCH("Director General",C14))+ISNUMBER(SEARCH("Presidente",C14))+ISNUMBER(SEARCH("President",C14))>0,'Configuración'!$B$31,IF(ISNUMBER(SEARCH("CMO",C14))+ISNUMBER(SEARCH("Chief Marketing",C14))+ISNUMBER(SEARCH("VP Marketing",C14))+ISNUMBER(SEARCH("Director de Marketing",C14))+ISNUMBER(SEARCH("Director Marketing",C14))+ISNUMBER(SEARCH("Head of Marketing",C14))+ISNUMBER(SEARCH("Head Marketing",C14))>0,'Configuración'!$B$32,IF(ISNUMBER(SEARCH("Marketing Manager",C14))+ISNUMBER(SEARCH("Gerente de Marketing",C14))+ISNUMBER(SEARCH("Growth Manager",C14))+ISNUMBER(SEARCH("Demand Gen",C14))+ISNUMBER(SEARCH("Marketing Lead",C14))>0,'Configuración'!$B$33,IF(ISNUMBER(SEARCH("COO",C14))+ISNUMBER(SEARCH("CFO",C14))+ISNUMBER(SEARCH("CTO",C14))+ISNUMBER(SEARCH("Chief Operating",C14))+ISNUMBER(SEARCH("Chief Financial",C14))+ISNUMBER(SEARCH("Gerente General",C14))+ISNUMBER(SEARCH("General Manager",C14))>0,'Configuración'!$B$34,'Configuración'!$B$35))))) -> 12 | V14: =IF(B14="","",IF(K14="Sí",'Configuración'!$B$5,0)+IF(L14="Semanal",'Configuración'!$B$6,IF(L14="Mensual",'Configuración'!$B$7,0))+IF(M14="Sí",'Configuración'!$B$8,0)+IF(N14="Sí",'Configuración'!$B$9,0)+IF(O14="Sí",'Configuración'!$B$10,0)+IF(P14="Sí",'Configuración'!$B$11,0)+IF(Q14="Sí",'Configuración'!$B$12,0)+S14+T14+U14) -> 48 | W14: =IF(B14="","",IF(V14>='Configuración'!$B$19,"A",IF(V14>='Configuración'!$B$20,"B",IF(V14>='Configuración'!$B$21,"C","Descarte")))) -> B
A15: =IF(B15="","",ROW()-2) -> 13 | B15: Julian | C15: Co-Founder | D15: Legal E-Solutions | E15: julian-robayo@legalesolutions.com | F15: http://www.linkedin.com/in/juli%c3%a1n-robayo-19ab2073 | G15: http://www.linkedin.com/company/legal-e-solutions | H15: https://legalesolutions.com | I15: legal services | J15: 3 | K15: No | L15: Inactivo | M15: Sí | N15: No | O15: No | Q15: No | R15: CO-FOUNDER Ya no trabaja ahí | S15: =IF(B15="","",IF(ISNUMBER(J15),IF(J15<=10,'Configuración'!$B$23,IF(J15<=50,'Configuración'!$B$24,IF(J15<=200,'Configuración'!$B$25,0))),0)) -> 12 | T15: =IF(B15="","",IF(ISNUMBER(SEARCH("information technology",I15))+ISNUMBER(SEARCH("software",I15))+ISNUMBER(SEARCH("internet",I15))+ISNUMBER(SEARCH("computer",I15))+ISNUMBER(SEARCH("saas",I15))+ISNUMBER(SEARCH("fintech",I15))+ISNUMBER(SEARCH("information services",I15))+ISNUMBER(SEARCH("telecommunications",I15))>0,'Configuración'!$B$27,'Configuración'!$B$28)) -> 4 | U15: =IF(B15="","",IF(ISNUMBER(SEARCH("CEO",C15))+ISNUMBER(SEARCH("Founder",C15))+ISNUMBER(SEARCH("Owner",C15))+ISNUMBER(SEARCH("Dueño",C15))+ISNUMBER(SEARCH("Director General",C15))+ISNUMBER(SEARCH("Presidente",C15))+ISNUMBER(SEARCH("President",C15))>0,'Configuración'!$B$31,IF(ISNUMBER(SEARCH("CMO",C15))+ISNUMBER(SEARCH("Chief Marketing",C15))+ISNUMBER(SEARCH("VP Marketing",C15))+ISNUMBER(SEARCH("Director de Marketing",C15))+ISNUMBER(SEARCH("Director Marketing",C15))+ISNUMBER(SEARCH("Head of Marketing",C15))+ISNUMBER(SEARCH("Head Marketing",C15))>0,'Configuración'!$B$32,IF(ISNUMBER(SEARCH("Marketing Manager",C15))+ISNUMBER(SEARCH("Gerente de Marketing",C15))+ISNUMBER(SEARCH("Growth Manager",C15))+ISNUMBER(SEARCH("Demand Gen",C15))+ISNUMBER(SEARCH("Marketing Lead",C15))>0,'Configuración'!$B$33,IF(ISNUMBER(SEARCH("COO",C15))+ISNUMBER(SEARCH("CFO",C15))+ISNUMBER(SEARCH("CTO",C15))+ISNUMBER(SEARCH("Chief Operating",C15))+ISNUMBER(SEARCH("Chief Financial",C15))+ISNUMBER(SEARCH("Gerente General",C15))+ISNUMBER(SEARCH("General Manager",C15))>0,'Configuración'!$B$34,'Configuración'!$B$35))))) -> 12 | V15: =IF(B15="","",IF(K15="Sí",'Configuración'!$B$5,0)+IF(L15="Semanal",'Configuración'!$B$6,IF(L15="Mensual",'Configuración'!$B$7,0))+IF(M15="Sí",'Configuración'!$B$8,0)+IF(N15="Sí",'Configuración'!$B$9,0)+IF(O15="Sí",'Configuración'!$B$10,0)+IF(P15="Sí",'Configuración'!$B$11,0)+IF(Q15="Sí",'Configuración'!$B$12,0)+S15+T15+U15) -> 40 | W15: =IF(B15="","",IF(V15>='Configuración'!$B$19,"A",IF(V15>='Configuración'!$B$20,"B",IF(V15>='Configuración'!$B$21,"C","Descarte")))) -> B
A16: =IF(B16="","",ROW()-2) -> 14 | B16: Adriana | C16: CoFunder/CEO | D16: Cres-ko | E16: adriana@cres-ko.com | F16: http://www.linkedin.com/in/adriana-garcia-serrano | G16: http://www.linkedin.com/company/cres-ko | H16: https://cres-ko.com | I16: professional training & coaching | J16: 2 | K16: No | L16: Inactivo | M16: Sí | N16: No | O16: Sí | Q16: No | S16: =IF(B16="","",IF(ISNUMBER(J16),IF(J16<=10,'Configuración'!$B$23,IF(J16<=50,'Configuración'!$B$24,IF(J16<=200,'Configuración'!$B$25,0))),0)) -> 12 | T16: =IF(B16="","",IF(ISNUMBER(SEARCH("information technology",I16))+ISNUMBER(SEARCH("software",I16))+ISNUMBER(SEARCH("internet",I16))+ISNUMBER(SEARCH("computer",I16))+ISNUMBER(SEARCH("saas",I16))+ISNUMBER(SEARCH("fintech",I16))+ISNUMBER(SEARCH("information services",I16))+ISNUMBER(SEARCH("telecommunications",I16))>0,'Configuración'!$B$27,'Configuración'!$B$28)) -> 4 | U16: =IF(B16="","",IF(ISNUMBER(SEARCH("CEO",C16))+ISNUMBER(SEARCH("Founder",C16))+ISNUMBER(SEARCH("Owner",C16))+ISNUMBER(SEARCH("Dueño",C16))+ISNUMBER(SEARCH("Director General",C16))+ISNUMBER(SEARCH("Presidente",C16))+ISNUMBER(SEARCH("President",C16))>0,'Configuración'!$B$31,IF(ISNUMBER(SEARCH("CMO",C16))+ISNUMBER(SEARCH("Chief Marketing",C16))+ISNUMBER(SEARCH("VP Marketing",C16))+ISNUMBER(SEARCH("Director de Marketing",C16))+ISNUMBER(SEARCH("Director Marketing",C16))+ISNUMBER(SEARCH("Head of Marketing",C16))+ISNUMBER(SEARCH("Head Marketing",C16))>0,'Configuración'!$B$32,IF(ISNUMBER(SEARCH("Marketing Manager",C16))+ISNUMBER(SEARCH("Gerente de Marketing",C16))+ISNUMBER(SEARCH("Growth Manager",C16))+ISNUMBER(SEARCH("Demand Gen",C16))+ISNUMBER(SEARCH("Marketing Lead",C16))>0,'Configuración'!$B$33,IF(ISNUMBER(SEARCH("COO",C16))+ISNUMBER(SEARCH("CFO",C16))+ISNUMBER(SEARCH("CTO",C16))+ISNUMBER(SEARCH("Chief Operating",C16))+ISNUMBER(SEARCH("Chief Financial",C16))+ISNUMBER(SEARCH("Gerente General",C16))+ISNUMBER(SEARCH("General Manager",C16))>0,'Configuración'!$B$34,'Configuración'!$B$35))))) -> 12 | V16: =IF(B16="","",IF(K16="Sí",'Configuración'!$B$5,0)+IF(L16="Semanal",'Configuración'!$B$6,IF(L16="Mensual",'Configuración'!$B$7,0))+IF(M16="Sí",'Configuración'!$B$8,0)+IF(N16="Sí",'Configuración'!$B$9,0)+IF(O16="Sí",'Configuración'!$B$10,0)+IF(P16="Sí",'Configuración'!$B$11,0)+IF(Q16="Sí",'Configuración'!$B$12,0)+S16+T16+U16) -> 48 | W16: =IF(B16="","",IF(V16>='Configuración'!$B$19,"A",IF(V16>='Configuración'!$B$20,"B",IF(V16>='Configuración'!$B$21,"C","Descarte")))) -> B
A17: =IF(B17="","",ROW()-2) -> 15 | B17: Juan | C17: CEO Talenta Learning | D17: Talenta Learning | E17: jmcardona@talentalearning.com | F17: http://www.linkedin.com/in/juanmcardona | G17: http://www.linkedin.com/company/talenta-learning | H17: https://talentalearning.com | I17: e-learning | J17: 3 | K17: No | L17: Semanal | M17: No | N17: No | O17: No | Q17: No | S17: =IF(B17="","",IF(ISNUMBER(J17),IF(J17<=10,'Configuración'!$B$23,IF(J17<=50,'Configuración'!$B$24,IF(J17<=200,'Configuración'!$B$25,0))),0)) -> 12 | T17: =IF(B17="","",IF(ISNUMBER(SEARCH("information technology",I17))+ISNUMBER(SEARCH("software",I17))+ISNUMBER(SEARCH("internet",I17))+ISNUMBER(SEARCH("computer",I17))+ISNUMBER(SEARCH("saas",I17))+ISNUMBER(SEARCH("fintech",I17))+ISNUMBER(SEARCH("information services",I17))+ISNUMBER(SEARCH("telecommunications",I17))>0,'Configuración'!$B$27,'Configuración'!$B$28)) -> 4 | U17: =IF(B17="","",IF(ISNUMBER(SEARCH("CEO",C17))+ISNUMBER(SEARCH("Founder",C17))+ISNUMBER(SEARCH("Owner",C17))+ISNUMBER(SEARCH("Dueño",C17))+ISNUMBER(SEARCH("Director General",C17))+ISNUMBER(SEARCH("Presidente",C17))+ISNUMBER(SEARCH("President",C17))>0,'Configuración'!$B$31,IF(ISNUMBER(SEARCH("CMO",C17))+ISNUMBER(SEARCH("Chief Marketing",C17))+ISNUMBER(SEARCH("VP Marketing",C17))+ISNUMBER(SEARCH("Director de Marketing",C17))+ISNUMBER(SEARCH("Director Marketing",C17))+ISNUMBER(SEARCH("Head of Marketing",C17))+ISNUMBER(SEARCH("Head Marketing",C17))>0,'Configuración'!$B$32,IF(ISNUMBER(SEARCH("Marketing Manager",C17))+ISNUMBER(SEARCH("Gerente de Marketing",C17))+ISNUMBER(SEARCH("Growth Manager",C17))+ISNUMBER(SEARCH("Demand Gen",C17))+ISNUMBER(SEARCH("Marketing Lead",C17))>0,'Configuración'!$B$33,IF(ISNUMBER(SEARCH("COO",C17))+ISNUMBER(SEARCH("CFO",C17))+ISNUMBER(SEARCH("CTO",C17))+ISNUMBER(SEARCH("Chief Operating",C17))+ISNUMBER(SEARCH("Chief Financial",C17))+ISNUMBER(SEARCH("Gerente General",C17))+ISNUMBER(SEARCH("General Manager",C17))>0,'Configuración'!$B$34,'Configuración'!$B$35))))) -> 12 | V17: =IF(B17="","",IF(K17="Sí",'Configuración'!$B$5,0)+IF(L17="Semanal",'Configuración'!$B$6,IF(L17="Mensual",'Configuración'!$B$7,0))+IF(M17="Sí",'Configuración'!$B$8,0)+IF(N17="Sí",'Configuración'!$B$9,0)+IF(O17="Sí",'Configuración'!$B$10,0)+IF(P17="Sí",'Configuración'!$B$11,0)+IF(Q17="Sí",'Configuración'!$B$12,0)+S17+T17+U17) -> 40 | W17: =IF(B17="","",IF(V17>='Configuración'!$B$19,"A",IF(V17>='Configuración'!$B$20,"B",IF(V17>='Configuración'!$B$21,"C","Descarte")))) -> B
A18: =IF(B18="","",ROW()-2) -> 16 | B18: Camilo | C18: Co-founder | D18: Rentmies | E18: camilo@rentmies.com | F18: http://www.linkedin.com/in/camilo-gonzalez-alvarez-1514a615b | G18: http://www.linkedin.com/company/rentmies | H18: https://rentmies.com | I18: information technology & services | J18: 5 | K18: No | L18: Inactivo | M18: Sí | N18: Sí | O18: Sí | Q18: No | R18: Posible Tier 1 | S18: =IF(B18="","",IF(ISNUMBER(J18),IF(J18<=10,'Configuración'!$B$23,IF(J18<=50,'Configuración'!$B$24,IF(J18<=200,'Configuración'!$B$25,0))),0)) -> 12 | T18: =IF(B18="","",IF(ISNUMBER(SEARCH("information technology",I18))+ISNUMBER(SEARCH("software",I18))+ISNUMBER(SEARCH("internet",I18))+ISNUMBER(SEARCH("computer",I18))+ISNUMBER(SEARCH("saas",I18))+ISNUMBER(SEARCH("fintech",I18))+ISNUMBER(SEARCH("information services",I18))+ISNUMBER(SEARCH("telecommunications",I18))>0,'Configuración'!$B$27,'Configuración'!$B$28)) -> 12 | U18: =IF(B18="","",IF(ISNUMBER(SEARCH("CEO",C18))+ISNUMBER(SEARCH("Founder",C18))+ISNUMBER(SEARCH("Owner",C18))+ISNUMBER(SEARCH("Dueño",C18))+ISNUMBER(SEARCH("Director General",C18))+ISNUMBER(SEARCH("Presidente",C18))+ISNUMBER(SEARCH("President",C18))>0,'Configuración'!$B$31,IF(ISNUMBER(SEARCH("CMO",C18))+ISNUMBER(SEARCH("Chief Marketing",C18))+ISNUMBER(SEARCH("VP Marketing",C18))+ISNUMBER(SEARCH("Director de Marketing",C18))+ISNUMBER(SEARCH("Director Marketing",C18))+ISNUMBER(SEARCH("Head of Marketing",C18))+ISNUMBER(SEARCH("Head Marketing",C18))>0,'Configuración'!$B$32,IF(ISNUMBER(SEARCH("Marketing Manager",C18))+ISNUMBER(SEARCH("Gerente de Marketing",C18))+ISNUMBER(SEARCH("Growth Manager",C18))+ISNUMBER(SEARCH("Demand Gen",C18))+ISNUMBER(SEARCH("Marketing Lead",C18))>0,'Configuración'!$B$33,IF(ISNUMBER(SEARCH("COO",C18))+ISNUMBER(SEARCH("CFO",C18))+ISNUMBER(SEARCH("CTO",C18))+ISNUMBER(SEARCH("Chief Operating",C18))+ISNUMBER(SEARCH("Chief Financial",C18))+ISNUMBER(SEARCH("Gerente General",C18))+ISNUMBER(SEARCH("General Manager",C18))>0,'Configuración'!$B$34,'Configuración'!$B$35))))) -> 12 | V18: =IF(B18="","",IF(K18="Sí",'Configuración'!$B$5,0)+IF(L18="Semanal",'Configuración'!$B$6,IF(L18="Mensual",'Configuración'!$B$7,0))+IF(M18="Sí",'Configuración'!$B$8,0)+IF(N18="Sí",'Configuración'!$B$9,0)+IF(O18="Sí",'Configuración'!$B$10,0)+IF(P18="Sí",'Configuración'!$B$11,0)+IF(Q18="Sí",'Configuración'!$B$12,0)+S18+T18+U18) -> 60 | W18: =IF(B18="","",IF(V18>='Configuración'!$B$19,"A",IF(V18>='Configuración'!$B$20,"B",IF(V18>='Configuración'!$B$21,"C","Descarte")))) -> A
A19: =IF(B19="","",ROW()-2) -> 17 | B19: Andres | C19: Co-Founder | D19: Dantai Labs | E19: andres@dantailabs.com | F19: http://www.linkedin.com/in/andressarmiento | G19: http://www.linkedin.com/company/dantai-labs | H19: https://dantailabs.com | I19: information technology & services | J19: 3 | K19: No | L19: Inactivo | M19: Sí | N19: No | O19: No | Q19: No | R19: Posible Tier 1 | S19: =IF(B19="","",IF(ISNUMBER(J19),IF(J19<=10,'Configuración'!$B$23,IF(J19<=50,'Configuración'!$B$24,IF(J19<=200,'Configuración'!$B$25,0))),0)) -> 12 | T19: =IF(B19="","",IF(ISNUMBER(SEARCH("information technology",I19))+ISNUMBER(SEARCH("software",I19))+ISNUMBER(SEARCH("internet",I19))+ISNUMBER(SEARCH("computer",I19))+ISNUMBER(SEARCH("saas",I19))+ISNUMBER(SEARCH("fintech",I19))+ISNUMBER(SEARCH("information services",I19))+ISNUMBER(SEARCH("telecommunications",I19))>0,'Configuración'!$B$27,'Configuración'!$B$28)) -> 12 | U19: =IF(B19="","",IF(ISNUMBER(SEARCH("CEO",C19))+ISNUMBER(SEARCH("Founder",C19))+ISNUMBER(SEARCH("Owner",C19))+ISNUMBER(SEARCH("Dueño",C19))+ISNUMBER(SEARCH("Director General",C19))+ISNUMBER(SEARCH("Presidente",C19))+ISNUMBER(SEARCH("President",C19))>0,'Configuración'!$B$31,IF(ISNUMBER(SEARCH("CMO",C19))+ISNUMBER(SEARCH("Chief Marketing",C19))+ISNUMBER(SEARCH("VP Marketing",C19))+ISNUMBER(SEARCH("Director de Marketing",C19))+ISNUMBER(SEARCH("Director Marketing",C19))+ISNUMBER(SEARCH("Head of Marketing",C19))+ISNUMBER(SEARCH("Head Marketing",C19))>0,'Configuración'!$B$32,IF(ISNUMBER(SEARCH("Marketing Manager",C19))+ISNUMBER(SEARCH("Gerente de Marketing",C19))+ISNUMBER(SEARCH("Growth Manager",C19))+ISNUMBER(SEARCH("Demand Gen",C19))+ISNUMBER(SEARCH("Marketing Lead",C19))>0,'Configuración'!$B$33,IF(ISNUMBER(SEARCH("COO",C19))+ISNUMBER(SEARCH("CFO",C19))+ISNUMBER(SEARCH("CTO",C19))+ISNUMBER(SEARCH("Chief Operating",C19))+ISNUMBER(SEARCH("Chief Financial",C19))+ISNUMBER(SEARCH("Gerente General",C19))+ISNUMBER(SEARCH("General Manager",C19))>0,'Configuración'!$B$34,'Configuración'!$B$35))))) -> 12 | V19: =IF(B19="","",IF(K19="Sí",'Configuración'!$B$5,0)+IF(L19="Semanal",'Configuración'!$B$6,IF(L19="Mensual",'Configuración'!$B$7,0))+IF(M19="Sí",'Configuración'!$B$8,0)+IF(N19="Sí",'Configuración'!$B$9,0)+IF(O19="Sí",'Configuración'!$B$10,0)+IF(P19="Sí",'Configuración'!$B$11,0)+IF(Q19="Sí",'Configuración'!$B$12,0)+S19+T19+U19) -> 48 | W19: =IF(B19="","",IF(V19>='Configuración'!$B$19,"A",IF(V19>='Configuración'!$B$20,"B",IF(V19>='Configuración'!$B$21,"C","Descarte")))) -> B
A20: =IF(B20="","",ROW()-2) -> 18 | B20: Santiago | C20: Co-Founder | D20: Falcon | E20: santiago@falconapp.ai | F20: http://www.linkedin.com/in/aboutsantiago | G20: http://www.linkedin.com/company/falconapp | H20: https://falconapp.ai | I20: information technology & services | J20: 1 | K20: No | L20: Inactivo | M20: No | N20: No | O20: No | Q20: No | S20: =IF(B20="","",IF(ISNUMBER(J20),IF(J20<=10,'Configuración'!$B$23,IF(J20<=50,'Configuración'!$B$24,IF(J20<=200,'Configuración'!$B$25,0))),0)) -> 12 | T20: =IF(B20="","",IF(ISNUMBER(SEARCH("information technology",I20))+ISNUMBER(SEARCH("software",I20))+ISNUMBER(SEARCH("internet",I20))+ISNUMBER(SEARCH("computer",I20))+ISNUMBER(SEARCH("saas",I20))+ISNUMBER(SEARCH("fintech",I20))+ISNUMBER(SEARCH("information services",I20))+ISNUMBER(SEARCH("telecommunications",I20))>0,'Configuración'!$B$27,'Configuración'!$B$28)) -> 12 | U20: =IF(B20="","",IF(ISNUMBER(SEARCH("CEO",C20))+ISNUMBER(SEARCH("Founder",C20))+ISNUMBER(SEARCH("Owner",C20))+ISNUMBER(SEARCH("Dueño",C20))+ISNUMBER(SEARCH("Director General",C20))+ISNUMBER(SEARCH("Presidente",C20))+ISNUMBER(SEARCH("President",C20))>0,'Configuración'!$B$31,IF(ISNUMBER(SEARCH("CMO",C20))+ISNUMBER(SEARCH("Chief Marketing",C20))+ISNUMBER(SEARCH("VP Marketing",C20))+ISNUMBER(SEARCH("Director de Marketing",C20))+ISNUMBER(SEARCH("Director Marketing",C20))+ISNUMBER(SEARCH("Head of Marketing",C20))+ISNUMBER(SEARCH("Head Marketing",C20))>0,'Configuración'!$B$32,IF(ISNUMBER(SEARCH("Marketing Manager",C20))+ISNUMBER(SEARCH("Gerente de Marketing",C20))+ISNUMBER(SEARCH("Growth Manager",C20))+ISNUMBER(SEARCH("Demand Gen",C20))+ISNUMBER(SEARCH("Marketing Lead",C20))>0,'Configuración'!$B$33,IF(ISNUMBER(SEARCH("COO",C20))+ISNUMBER(SEARCH("CFO",C20))+ISNUMBER(SEARCH("CTO",C20))+ISNUMBER(SEARCH("Chief Operating",C20))+ISNUMBER(SEARCH("Chief Financial",C20))+ISNUMBER(SEARCH("Gerente General",C20))+ISNUMBER(SEARCH("General Manager",C20))>0,'Configuración'!$B$34,'Configuración'!$B$35))))) -> 12 | V20: =IF(B20="","",IF(K20="Sí",'Configuración'!$B$5,0)+IF(L20="Semanal",'Configuración'!$B$6,IF(L20="Mensual",'Configuración'!$B$7,0))+IF(M20="Sí",'Configuración'!$B$8,0)+IF(N20="Sí",'Configuración'!$B$9,0)+IF(O20="Sí",'Configuración'!$B$10,0)+IF(P20="Sí",'Configuración'!$B$11,0)+IF(Q20="Sí",'Configuración'!$B$12,0)+S20+T20+U20) -> 36 | W20: =IF(B20="","",IF(V20>='Configuración'!$B$19,"A",IF(V20>='Configuración'!$B$20,"B",IF(V20>='Configuración'!$B$21,"C","Descarte")))) -> C
A21: =IF(B21="","",ROW()-2) -> 19 | B21: Mariana | C21: Founder and Director | D21: Poderosas Colombia | E21: msanzdesantamaria@poderosascolombia.org | F21: http://www.linkedin.com/in/mariana-sanz-de-santamar%c3%ada-franco-72849b19a | G21: http://www.linkedin.com/company/poderosascolombia | H21: https://poderosascolombia.org | I21: civic & social organization | J21: 18 | K21: Sí | L21: Semanal | M21: Sí | N21: No | O21: No | Q21: No | S21: =IF(B21="","",IF(ISNUMBER(J21),IF(J21<=10,'Configuración'!$B$23,IF(J21<=50,'Configuración'!$B$24,IF(J21<=200,'Configuración'!$B$25,0))),0)) -> 4 | T21: =IF(B21="","",IF(ISNUMBER(SEARCH("information technology",I21))+ISNUMBER(SEARCH("software",I21))+ISNUMBER(SEARCH("internet",I21))+ISNUMBER(SEARCH("computer",I21))+ISNUMBER(SEARCH("saas",I21))+ISNUMBER(SEARCH("fintech",I21))+ISNUMBER(SEARCH("information services",I21))+ISNUMBER(SEARCH("telecommunications",I21))>0,'Configuración'!$B$27,'Configuración'!$B$28)) -> 4 | U21: =IF(B21="","",IF(ISNUMBER(SEARCH("CEO",C21))+ISNUMBER(SEARCH("Founder",C21))+ISNUMBER(SEARCH("Owner",C21))+ISNUMBER(SEARCH("Dueño",C21))+ISNUMBER(SEARCH("Director General",C21))+ISNUMBER(SEARCH("Presidente",C21))+ISNUMBER(SEARCH("President",C21))>0,'Configuración'!$B$31,IF(ISNUMBER(SEARCH("CMO",C21))+ISNUMBER(SEARCH("Chief Marketing",C21))+ISNUMBER(SEARCH("VP Marketing",C21))+ISNUMBER(SEARCH("Director de Marketing",C21))+ISNUMBER(SEARCH("Director Marketing",C21))+ISNUMBER(SEARCH("Head of Marketing",C21))+ISNUMBER(SEARCH("Head Marketing",C21))>0,'Configuración'!$B$32,IF(ISNUMBER(SEARCH("Marketing Manager",C21))+ISNUMBER(SEARCH("Gerente de Marketing",C21))+ISNUMBER(SEARCH("Growth Manager",C21))+ISNUMBER(SEARCH("Demand Gen",C21))+ISNUMBER(SEARCH("Marketing Lead",C21))>0,'Configuración'!$B$33,IF(ISNUMBER(SEARCH("COO",C21))+ISNUMBER(SEARCH("CFO",C21))+ISNUMBER(SEARCH("CTO",C21))+ISNUMBER(SEARCH("Chief Operating",C21))+ISNUMBER(SEARCH("Chief Financial",C21))+ISNUMBER(SEARCH("Gerente General",C21))+ISNUMBER(SEARCH("General Manager",C21))>0,'Configuración'!$B$34,'Configuración'!$B$35))))) -> 12 | V21: =IF(B21="","",IF(K21="Sí",'Configuración'!$B$5,0)+IF(L21="Semanal",'Configuración'!$B$6,IF(L21="Mensual",'Configuración'!$B$7,0))+IF(M21="Sí",'Configuración'!$B$8,0)+IF(N21="Sí",'Configuración'!$B$9,0)+IF(O21="Sí",'Configuración'!$B$10,0)+IF(P21="Sí",'Configuración'!$B$11,0)+IF(Q21="Sí",'Configuración'!$B$12,0)+S21+T21+U21) -> 56 | W21: =IF(B21="","",IF(V21>='Configuración'!$B$19,"A",IF(V21>='Configuración'!$B$20,"B",IF(V21>='Configuración'!$B$21,"C","Descarte")))) -> B
A22: =IF(B22="","",ROW()-2) -> 20 | B22: Laura | C22: Fundadora & CEO | D22: Kiper.ai | E22: laura@kiper.ai | F22: http://www.linkedin.com/in/lauranavarro91 | G22: http://www.linkedin.com/company/kiper-ai | H22: https://kipertienda.com | I22: information technology & services | J22: 5 | K22: No | L22: Inactivo | M22: Sí | N22: Sí | O22: No | Q22: No | R22: Posible Tier 1 | S22: =IF(B22="","",IF(ISNUMBER(J22),IF(J22<=10,'Configuración'!$B$23,IF(J22<=50,'Configuración'!$B$24,IF(J22<=200,'Configuración'!$B$25,0))),0)) -> 12 | T22: =IF(B22="","",IF(ISNUMBER(SEARCH("information technology",I22))+ISNUMBER(SEARCH("software",I22))+ISNUMBER(SEARCH("internet",I22))+ISNUMBER(SEARCH("computer",I22))+ISNUMBER(SEARCH("saas",I22))+ISNUMBER(SEARCH("fintech",I22))+ISNUMBER(SEARCH("information services",I22))+ISNUMBER(SEARCH("telecommunications",I22))>0,'Configuración'!$B$27,'Configuración'!$B$28)) -> 12 | U22: =IF(B22="","",IF(ISNUMBER(SEARCH("CEO",C22))+ISNUMBER(SEARCH("Founder",C22))+ISNUMBER(SEARCH("Owner",C22))+ISNUMBER(SEARCH("Dueño",C22))+ISNUMBER(SEARCH("Director General",C22))+ISNUMBER(SEARCH("Presidente",C22))+ISNUMBER(SEARCH("President",C22))>0,'Configuración'!$B$31,IF(ISNUMBER(SEARCH("CMO",C22))+ISNUMBER(SEARCH("Chief Marketing",C22))+ISNUMBER(SEARCH("VP Marketing",C22))+ISNUMBER(SEARCH("Director de Marketing",C22))+ISNUMBER(SEARCH("Director Marketing",C22))+ISNUMBER(SEARCH("Head of Marketing",C22))+ISNUMBER(SEARCH("Head Marketing",C22))>0,'Configuración'!$B$32,IF(ISNUMBER(SEARCH("Marketing Manager",C22))+ISNUMBER(SEARCH("Gerente de Marketing",C22))+ISNUMBER(SEARCH("Growth Manager",C22))+ISNUMBER(SEARCH("Demand Gen",C22))+ISNUMBER(SEARCH("Marketing Lead",C22))>0,'Configuración'!$B$33,IF(ISNUMBER(SEARCH("COO",C22))+ISNUMBER(SEARCH("CFO",C22))+ISNUMBER(SEARCH("CTO",C22))+ISNUMBER(SEARCH("Chief Operating",C22))+ISNUMBER(SEARCH("Chief Financial",C22))+ISNUMBER(SEARCH("Gerente General",C22))+ISNUMBER(SEARCH("General Manager",C22))>0,'Configuración'!$B$34,'Configuración'!$B$35))))) -> 12 | V22: =IF(B22="","",IF(K22="Sí",'Configuración'!$B$5,0)+IF(L22="Semanal",'Configuración'!$B$6,IF(L22="Mensual",'Configuración'!$B$7,0))+IF(M22="Sí",'Configuración'!$B$8,0)+IF(N22="Sí",'Configuración'!$B$9,0)+IF(O22="Sí",'Configuración'!$B$10,0)+IF(P22="Sí",'Configuración'!$B$11,0)+IF(Q22="Sí",'Configuración'!$B$12,0)+S22+T22+U22) -> 52 | W22: =IF(B22="","",IF(V22>='Configuración'!$B$19,"A",IF(V22>='Configuración'!$B$20,"B",IF(V22>='Configuración'!$B$21,"C","Descarte")))) -> B
A23: =IF(B23="","",ROW()-2) -> 21 | B23: Santiago | C23: CEO | D23: Keep Up | E23: svilladiego@keepup.news | F23: http://www.linkedin.com/in/santiagovilladiegomogollon | G23: http://www.linkedin.com/company/keepupagencia | H23: https://keepup.news | I23: information technology & services | J23: 38 | K23: No | L23: Semanal | M23: Sí | N23: No | O23: No | Q23: No | S23: =IF(B23="","",IF(ISNUMBER(J23),IF(J23<=10,'Configuración'!$B$23,IF(J23<=50,'Configuración'!$B$24,IF(J23<=200,'Configuración'!$B$25,0))),0)) -> 4 | T23: =IF(B23="","",IF(ISNUMBER(SEARCH("information technology",I23))+ISNUMBER(SEARCH("software",I23))+ISNUMBER(SEARCH("internet",I23))+ISNUMBER(SEARCH("computer",I23))+ISNUMBER(SEARCH("saas",I23))+ISNUMBER(SEARCH("fintech",I23))+ISNUMBER(SEARCH("information services",I23))+ISNUMBER(SEARCH("telecommunications",I23))>0,'Configuración'!$B$27,'Configuración'!$B$28)) -> 12 | U23: =IF(B23="","",IF(ISNUMBER(SEARCH("CEO",C23))+ISNUMBER(SEARCH("Founder",C23))+ISNUMBER(SEARCH("Owner",C23))+ISNUMBER(SEARCH("Dueño",C23))+ISNUMBER(SEARCH("Director General",C23))+ISNUMBER(SEARCH("Presidente",C23))+ISNUMBER(SEARCH("President",C23))>0,'Configuración'!$B$31,IF(ISNUMBER(SEARCH("CMO",C23))+ISNUMBER(SEARCH("Chief Marketing",C23))+ISNUMBER(SEARCH("VP Marketing",C23))+ISNUMBER(SEARCH("Director de Marketing",C23))+ISNUMBER(SEARCH("Director Marketing",C23))+ISNUMBER(SEARCH("Head of Marketing",C23))+ISNUMBER(SEARCH("Head Marketing",C23))>0,'Configuración'!$B$32,IF(ISNUMBER(SEARCH("Marketing Manager",C23))+ISNUMBER(SEARCH("Gerente de Marketing",C23))+ISNUMBER(SEARCH("Growth Manager",C23))+ISNUMBER(SEARCH("Demand Gen",C23))+ISNUMBER(SEARCH("Marketing Lead",C23))>0,'Configuración'!$B$33,IF(ISNUMBER(SEARCH("COO",C23))+ISNUMBER(SEARCH("CFO",C23))+ISNUMBER(SEARCH("CTO",C23))+ISNUMBER(SEARCH("Chief Operating",C23))+ISNUMBER(SEARCH("Chief Financial",C23))+ISNUMBER(SEARCH("Gerente General",C23))+ISNUMBER(SEARCH("General Manager",C23))>0,'Configuración'!$B$34,'Configuración'!$B$35))))) -> 12 | V23: =IF(B23="","",IF(K23="Sí",'Configuración'!$B$5,0)+IF(L23="Semanal",'Configuración'!$B$6,IF(L23="Mensual",'Configuración'!$B$7,0))+IF(M23="Sí",'Configuración'!$B$8,0)+IF(N23="Sí",'Configuración'!$B$9,0)+IF(O23="Sí",'Configuración'!$B$10,0)+IF(P23="Sí",'Configuración'!$B$11,0)+IF(Q23="Sí",'Configuración'!$B$12,0)+S23+T23+U23) -> 52 | W23: =IF(B23="","",IF(V23>='Configuración'!$B$19,"A",IF(V23>='Configuración'!$B$20,"B",IF(V23>='Configuración'!$B$21,"C","Descarte")))) -> B
A24: =IF(B24="","",ROW()-2) -> 22 | B24: Felipe | C24: Co-Founder | D24: Seeri | E24: fr@seeri.co | F24: http://www.linkedin.com/in/feliperacines | G24: http://www.linkedin.com/company/seeri | H24: https://seeri.co | I24: information technology & services | J24: 26 | K24: No | L24: Inactivo | M24: No | N24: No | O24: No | Q24: No | S24: =IF(B24="","",IF(ISNUMBER(J24),IF(J24<=10,'Configuración'!$B$23,IF(J24<=50,'Configuración'!$B$24,IF(J24<=200,'Configuración'!$B$25,0))),0)) -> 4 | T24: =IF(B24="","",IF(ISNUMBER(SEARCH("information technology",I24))+ISNUMBER(SEARCH("software",I24))+ISNUMBER(SEARCH("internet",I24))+ISNUMBER(SEARCH("computer",I24))+ISNUMBER(SEARCH("saas",I24))+ISNUMBER(SEARCH("fintech",I24))+ISNUMBER(SEARCH("information services",I24))+ISNUMBER(SEARCH("telecommunications",I24))>0,'Configuración'!$B$27,'Configuración'!$B$28)) -> 12 | U24: =IF(B24="","",IF(ISNUMBER(SEARCH("CEO",C24))+ISNUMBER(SEARCH("Founder",C24))+ISNUMBER(SEARCH("Owner",C24))+ISNUMBER(SEARCH("Dueño",C24))+ISNUMBER(SEARCH("Director General",C24))+ISNUMBER(SEARCH("Presidente",C24))+ISNUMBER(SEARCH("President",C24))>0,'Configuración'!$B$31,IF(ISNUMBER(SEARCH("CMO",C24))+ISNUMBER(SEARCH("Chief Marketing",C24))+ISNUMBER(SEARCH("VP Marketing",C24))+ISNUMBER(SEARCH("Director de Marketing",C24))+ISNUMBER(SEARCH("Director Marketing",C24))+ISNUMBER(SEARCH("Head of Marketing",C24))+ISNUMBER(SEARCH("Head Marketing",C24))>0,'Configuración'!$B$32,IF(ISNUMBER(SEARCH("Marketing Manager",C24))+ISNUMBER(SEARCH("Gerente de Marketing",C24))+ISNUMBER(SEARCH("Growth Manager",C24))+ISNUMBER(SEARCH("Demand Gen",C24))+ISNUMBER(SEARCH("Marketing Lead",C24))>0,'Configuración'!$B$33,IF(ISNUMBER(SEARCH("COO",C24))+ISNUMBER(SEARCH("CFO",C24))+ISNUMBER(SEARCH("CTO",C24))+ISNUMBER(SEARCH("Chief Operating",C24))+ISNUMBER(SEARCH("Chief Financial",C24))+ISNUMBER(SEARCH("Gerente General",C24))+ISNUMBER(SEARCH("General Manager",C24))>0,'Configuración'!$B$34,'Configuración'!$B$35))))) -> 12 | V24: =IF(B24="","",IF(K24="Sí",'Configuración'!$B$5,0)+IF(L24="Semanal",'Configuración'!$B$6,IF(L24="Mensual",'Configuración'!$B$7,0))+IF(M24="Sí",'Configuración'!$B$8,0)+IF(N24="Sí",'Configuración'!$B$9,0)+IF(O24="Sí",'Configuración'!$B$10,0)+IF(P24="Sí",'Configuración'!$B$11,0)+IF(Q24="Sí",'Configuración'!$B$12,0)+S24+T24+U24) -> 28 | W24: =IF(B24="","",IF(V24>='Configuración'!$B$19,"A",IF(V24>='Configuración'!$B$20,"B",IF(V24>='Configuración'!$B$21,"C","Descarte")))) -> C
A25: =IF(B25="","",ROW()-2) -> 23 | B25: Felipe | C25: Co-Founder | D25: Fibek | E25: felipe@fibek.co | F25: http://www.linkedin.com/in/felipesalcedob | G25: http://www.linkedin.com/company/fibekco | H25: https://fibek.co | I25: information technology & services | J25: 3 | K25: No | L25: Inactivo | M25: Sí | N25: No | O25: No | Q25: No | R25: Posible Tier 1 | S25: =IF(B25="","",IF(ISNUMBER(J25),IF(J25<=10,'Configuración'!$B$23,IF(J25<=50,'Configuración'!$B$24,IF(J25<=200,'Configuración'!$B$25,0))),0)) -> 12 | T25: =IF(B25="","",IF(ISNUMBER(SEARCH("information technology",I25))+ISNUMBER(SEARCH("software",I25))+ISNUMBER(SEARCH("internet",I25))+ISNUMBER(SEARCH("computer",I25))+ISNUMBER(SEARCH("saas",I25))+ISNUMBER(SEARCH("fintech",I25))+ISNUMBER(SEARCH("information services",I25))+ISNUMBER(SEARCH("telecommunications",I25))>0,'Configuración'!$B$27,'Configuración'!$B$28)) -> 12 | U25: =IF(B25="","",IF(ISNUMBER(SEARCH("CEO",C25))+ISNUMBER(SEARCH("Founder",C25))+ISNUMBER(SEARCH("Owner",C25))+ISNUMBER(SEARCH("Dueño",C25))+ISNUMBER(SEARCH("Director General",C25))+ISNUMBER(SEARCH("Presidente",C25))+ISNUMBER(SEARCH("President",C25))>0,'Configuración'!$B$31,IF(ISNUMBER(SEARCH("CMO",C25))+ISNUMBER(SEARCH("Chief Marketing",C25))+ISNUMBER(SEARCH("VP Marketing",C25))+ISNUMBER(SEARCH("Director de Marketing",C25))+ISNUMBER(SEARCH("Director Marketing",C25))+ISNUMBER(SEARCH("Head of Marketing",C25))+ISNUMBER(SEARCH("Head Marketing",C25))>0,'Configuración'!$B$32,IF(ISNUMBER(SEARCH("Marketing Manager",C25))+ISNUMBER(SEARCH("Gerente de Marketing",C25))+ISNUMBER(SEARCH("Growth Manager",C25))+ISNUMBER(SEARCH("Demand Gen",C25))+ISNUMBER(SEARCH("Marketing Lead",C25))>0,'Configuración'!$B$33,IF(ISNUMBER(SEARCH("COO",C25))+ISNUMBER(SEARCH("CFO",C25))+ISNUMBER(SEARCH("CTO",C25))+ISNUMBER(SEARCH("Chief Operating",C25))+ISNUMBER(SEARCH("Chief Financial",C25))+ISNUMBER(SEARCH("Gerente General",C25))+ISNUMBER(SEARCH("General Manager",C25))>0,'Configuración'!$B$34,'Configuración'!$B$35))))) -> 12 | V25: =IF(B25="","",IF(K25="Sí",'Configuración'!$B$5,0)+IF(L25="Semanal",'Configuración'!$B$6,IF(L25="Mensual",'Configuración'!$B$7,0))+IF(M25="Sí",'Configuración'!$B$8,0)+IF(N25="Sí",'Configuración'!$B$9,0)+IF(O25="Sí",'Configuración'!$B$10,0)+IF(P25="Sí",'Configuración'!$B$11,0)+IF(Q25="Sí",'Configuración'!$B$12,0)+S25+T25+U25) -> 48 | W25: =IF(B25="","",IF(V25>='Configuración'!$B$19,"A",IF(V25>='Configuración'!$B$20,"B",IF(V25>='Configuración'!$B$21,"C","Descarte")))) -> B
A26: =IF(B26="","",ROW()-2) -> 24 | B26: Eivar | C26: Game Developer, Coffee Barista at Red Minas Coffee and Co-Founder | D26: Efecto Studios | E26: eivar.rojas@efectostudios.com | F26: http://www.linkedin.com/in/eivarrocas | G26: http://www.linkedin.com/company/efecto-studios | H26: https://efectostudios.com | I26: computer games | J26: 34 | K26: No | L26: Inactivo | M26: Sí | N26: No | O26: No | Q26: No | S26: =IF(B26="","",IF(ISNUMBER(J26),IF(J26<=10,'Configuración'!$B$23,IF(J26<=50,'Configuración'!$B$24,IF(J26<=200,'Configuración'!$B$25,0))),0)) -> 4 | T26: =IF(B26="","",IF(ISNUMBER(SEARCH("information technology",I26))+ISNUMBER(SEARCH("software",I26))+ISNUMBER(SEARCH("internet",I26))+ISNUMBER(SEARCH("computer",I26))+ISNUMBER(SEARCH("saas",I26))+ISNUMBER(SEARCH("fintech",I26))+ISNUMBER(SEARCH("information services",I26))+ISNUMBER(SEARCH("telecommunications",I26))>0,'Configuración'!$B$27,'Configuración'!$B$28)) -> 12 | U26: =IF(B26="","",IF(ISNUMBER(SEARCH("CEO",C26))+ISNUMBER(SEARCH("Founder",C26))+ISNUMBER(SEARCH("Owner",C26))+ISNUMBER(SEARCH("Dueño",C26))+ISNUMBER(SEARCH("Director General",C26))+ISNUMBER(SEARCH("Presidente",C26))+ISNUMBER(SEARCH("President",C26))>0,'Configuración'!$B$31,IF(ISNUMBER(SEARCH("CMO",C26))+ISNUMBER(SEARCH("Chief Marketing",C26))+ISNUMBER(SEARCH("VP Marketing",C26))+ISNUMBER(SEARCH("Director de Marketing",C26))+ISNUMBER(SEARCH("Director Marketing",C26))+ISNUMBER(SEARCH("Head of Marketing",C26))+ISNUMBER(SEARCH("Head Marketing",C26))>0,'Configuración'!$B$32,IF(ISNUMBER(SEARCH("Marketing Manager",C26))+ISNUMBER(SEARCH("Gerente de Marketing",C26))+ISNUMBER(SEARCH("Growth Manager",C26))+ISNUMBER(SEARCH("Demand Gen",C26))+ISNUMBER(SEARCH("Marketing Lead",C26))>0,'Configuración'!$B$33,IF(ISNUMBER(SEARCH("COO",C26))+ISNUMBER(SEARCH("CFO",C26))+ISNUMBER(SEARCH("CTO",C26))+ISNUMBER(SEARCH("Chief Operating",C26))+ISNUMBER(SEARCH("Chief Financial",C26))+ISNUMBER(SEARCH("Gerente General",C26))+ISNUMBER(SEARCH("General Manager",C26))>0,'Configuración'!$B$34,'Configuración'!$B$35))))) -> 12 | V26: =IF(B26="","",IF(K26="Sí",'Configuración'!$B$5,0)+IF(L26="Semanal",'Configuración'!$B$6,IF(L26="Mensual",'Configuración'!$B$7,0))+IF(M26="Sí",'Configuración'!$B$8,0)+IF(N26="Sí",'Configuración'!$B$9,0)+IF(O26="Sí",'Configuración'!$B$10,0)+IF(P26="Sí",'Configuración'!$B$11,0)+IF(Q26="Sí",'Configuración'!$B$12,0)+S26+T26+U26) -> 40 | W26: =IF(B26="","",IF(V26>='Configuración'!$B$19,"A",IF(V26>='Configuración'!$B$20,"B",IF(V26>='Configuración'!$B$21,"C","Descarte")))) -> B
A27: =IF(B27="","",ROW()-2) -> 25 | B27: Claudia | C27: Founder | Senior Executive Producer | D27: PROUD CONTENT | E27: claudia@minkafilms.co | F27: http://www.linkedin.com/in/claudiacanoncarrillo | G27: http://www.linkedin.com/company/minka-films | H27: https://minkafilms.co | I27: media production | J27: 1 | K27: No | L27: Inactivo | M27: Sí | N27: No | O27: No | Q27: No | S27: =IF(B27="","",IF(ISNUMBER(J27),IF(J27<=10,'Configuración'!$B$23,IF(J27<=50,'Configuración'!$B$24,IF(J27<=200,'Configuración'!$B$25,0))),0)) -> 12 | T27: =IF(B27="","",IF(ISNUMBER(SEARCH("information technology",I27))+ISNUMBER(SEARCH("software",I27))+ISNUMBER(SEARCH("internet",I27))+ISNUMBER(SEARCH("computer",I27))+ISNUMBER(SEARCH("saas",I27))+ISNUMBER(SEARCH("fintech",I27))+ISNUMBER(SEARCH("information services",I27))+ISNUMBER(SEARCH("telecommunications",I27))>0,'Configuración'!$B$27,'Configuración'!$B$28)) -> 4 | U27: =IF(B27="","",IF(ISNUMBER(SEARCH("CEO",C27))+ISNUMBER(SEARCH("Founder",C27))+ISNUMBER(SEARCH("Owner",C27))+ISNUMBER(SEARCH("Dueño",C27))+ISNUMBER(SEARCH("Director General",C27))+ISNUMBER(SEARCH("Presidente",C27))+ISNUMBER(SEARCH("President",C27))>0,'Configuración'!$B$31,IF(ISNUMBER(SEARCH("CMO",C27))+ISNUMBER(SEARCH("Chief Marketing",C27))+ISNUMBER(SEARCH("VP Marketing",C27))+ISNUMBER(SEARCH("Director de Marketing",C27))+ISNUMBER(SEARCH("Director Marketing",C27))+ISNUMBER(SEARCH("Head of Marketing",C27))+ISNUMBER(SEARCH("Head Marketing",C27))>0,'Configuración'!$B$32,IF(ISNUMBER(SEARCH("Marketing Manager",C27))+ISNUMBER(SEARCH("Gerente de Marketing",C27))+ISNUMBER(SEARCH("Growth Manager",C27))+ISNUMBER(SEARCH("Demand Gen",C27))+ISNUMBER(SEARCH("Marketing Lead",C27))>0,'Configuración'!$B$33,IF(ISNUMBER(SEARCH("COO",C27))+ISNUMBER(SEARCH("CFO",C27))+ISNUMBER(SEARCH("CTO",C27))+ISNUMBER(SEARCH("Chief Operating",C27))+ISNUMBER(SEARCH("Chief Financial",C27))+ISNUMBER(SEARCH("Gerente General",C27))+ISNUMBER(SEARCH("General Manager",C27))>0,'Configuración'!$B$34,'Configuración'!$B$35))))) -> 12 | V27: =IF(B27="","",IF(K27="Sí",'Configuración'!$B$5,0)+IF(L27="Semanal",'Configuración'!$B$6,IF(L27="Mensual",'Configuración'!$B$7,0))+IF(M27="Sí",'Configuración'!$B$8,0)+IF(N27="Sí",'Configuración'!$B$9,0)+IF(O27="Sí",'Configuración'!$B$10,0)+IF(P27="Sí",'Configuración'!$B$11,0)+IF(Q27="Sí",'Configuración'!$B$12,0)+S27+T27+U27) -> 40 | W27: =IF(B27="","",IF(V27>='Configuración'!$B$19,"A",IF(V27>='Configuración'!$B$20,"B",IF(V27>='Configuración'!$B$21,"C","Descarte")))) -> B
A28: =IF(B28="","",ROW()-2) -> 26 | B28: Juan | C28: Executive Vice President Sales Marketing | D28: Las Américas Hotels Group | E28: juan.gomez@lasamericashg.com | F28: http://www.linkedin.com/in/juanfdo77 | G28: http://www.linkedin.com/company/lasamericashotels | H28: https://lasamericashotels.com | I28: hospitality | J28: 29 | K28: No | L28: Semanal | M28: Sí | N28: Sí | O28: No | Q28: No | S28: =IF(B28="","",IF(ISNUMBER(J28),IF(J28<=10,'Configuración'!$B$23,IF(J28<=50,'Configuración'!$B$24,IF(J28<=200,'Configuración'!$B$25,0))),0)) -> 4 | T28: =IF(B28="","",IF(ISNUMBER(SEARCH("information technology",I28))+ISNUMBER(SEARCH("software",I28))+ISNUMBER(SEARCH("internet",I28))+ISNUMBER(SEARCH("computer",I28))+ISNUMBER(SEARCH("saas",I28))+ISNUMBER(SEARCH("fintech",I28))+ISNUMBER(SEARCH("information services",I28))+ISNUMBER(SEARCH("telecommunications",I28))>0,'Configuración'!$B$27,'Configuración'!$B$28)) -> 4 | U28: =IF(B28="","",IF(ISNUMBER(SEARCH("CEO",C28))+ISNUMBER(SEARCH("Founder",C28))+ISNUMBER(SEARCH("Owner",C28))+ISNUMBER(SEARCH("Dueño",C28))+ISNUMBER(SEARCH("Director General",C28))+ISNUMBER(SEARCH("Presidente",C28))+ISNUMBER(SEARCH("President",C28))>0,'Configuración'!$B$31,IF(ISNUMBER(SEARCH("CMO",C28))+ISNUMBER(SEARCH("Chief Marketing",C28))+ISNUMBER(SEARCH("VP Marketing",C28))+ISNUMBER(SEARCH("Director de Marketing",C28))+ISNUMBER(SEARCH("Director Marketing",C28))+ISNUMBER(SEARCH("Head of Marketing",C28))+ISNUMBER(SEARCH("Head Marketing",C28))>0,'Configuración'!$B$32,IF(ISNUMBER(SEARCH("Marketing Manager",C28))+ISNUMBER(SEARCH("Gerente de Marketing",C28))+ISNUMBER(SEARCH("Growth Manager",C28))+ISNUMBER(SEARCH("Demand Gen",C28))+ISNUMBER(SEARCH("Marketing Lead",C28))>0,'Configuración'!$B$33,IF(ISNUMBER(SEARCH("COO",C28))+ISNUMBER(SEARCH("CFO",C28))+ISNUMBER(SEARCH("CTO",C28))+ISNUMBER(SEARCH("Chief Operating",C28))+ISNUMBER(SEARCH("Chief Financial",C28))+ISNUMBER(SEARCH("Gerente General",C28))+ISNUMBER(SEARCH("General Manager",C28))>0,'Configuración'!$B$34,'Configuración'!$B$35))))) -> 12 | V28: =IF(B28="","",IF(K28="Sí",'Configuración'!$B$5,0)+IF(L28="Semanal",'Configuración'!$B$6,IF(L28="Mensual",'Configuración'!$B$7,0))+IF(M28="Sí",'Configuración'!$B$8,0)+IF(N28="Sí",'Configuración'!$B$9,0)+IF(O28="Sí",'Configuración'!$B$10,0)+IF(P28="Sí",'Configuración'!$B$11,0)+IF(Q28="Sí",'Configuración'!$B$12,0)+S28+T28+U28) -> 48 | W28: =IF(B28="","",IF(V28>='Configuración'!$B$19,"A",IF(V28>='Configuración'!$B$20,"B",IF(V28>='Configuración'!$B$21,"C","Descarte")))) -> B
A29: =IF(B29="","",ROW()-2) -> 27 | B29: Diego | C29: Principal Chief Executive Officer | D29: Bits | E29: diego@grupobits.co | F29: http://www.linkedin.com/in/diegoluisherrera | G29: http://www.linkedin.com/company/grupobits | H29: https://grupobits.co | I29: information technology & services | J29: 7 | K29: No | L29: Mensual | M29: No | N29: No | O29: No | Q29: No | R29: Posible Tier 1 | S29: =IF(B29="","",IF(ISNUMBER(J29),IF(J29<=10,'Configuración'!$B$23,IF(J29<=50,'Configuración'!$B$24,IF(J29<=200,'Configuración'!$B$25,0))),0)) -> 12 | T29: =IF(B29="","",IF(ISNUMBER(SEARCH("information technology",I29))+ISNUMBER(SEARCH("software",I29))+ISNUMBER(SEARCH("internet",I29))+ISNUMBER(SEARCH("computer",I29))+ISNUMBER(SEARCH("saas",I29))+ISNUMBER(SEARCH("fintech",I29))+ISNUMBER(SEARCH("information services",I29))+ISNUMBER(SEARCH("telecommunications",I29))>0,'Configuración'!$B$27,'Configuración'!$B$28)) -> 12 | U29: =IF(B29="","",IF(ISNUMBER(SEARCH("CEO",C29))+ISNUMBER(SEARCH("Founder",C29))+ISNUMBER(SEARCH("Owner",C29))+ISNUMBER(SEARCH("Dueño",C29))+ISNUMBER(SEARCH("Director General",C29))+ISNUMBER(SEARCH("Presidente",C29))+ISNUMBER(SEARCH("President",C29))>0,'Configuración'!$B$31,IF(ISNUMBER(SEARCH("CMO",C29))+ISNUMBER(SEARCH("Chief Marketing",C29))+ISNUMBER(SEARCH("VP Marketing",C29))+ISNUMBER(SEARCH("Director de Marketing",C29))+ISNUMBER(SEARCH("Director Marketing",C29))+ISNUMBER(SEARCH("Head of Marketing",C29))+ISNUMBER(SEARCH("Head Marketing",C29))>0,'Configuración'!$B$32,IF(ISNUMBER(SEARCH("Marketing Manager",C29))+ISNUMBER(SEARCH("Gerente de Marketing",C29))+ISNUMBER(SEARCH("Growth Manager",C29))+ISNUMBER(SEARCH("Demand Gen",C29))+ISNUMBER(SEARCH("Marketing Lead",C29))>0,'Configuración'!$B$33,IF(ISNUMBER(SEARCH("COO",C29))+ISNUMBER(SEARCH("CFO",C29))+ISNUMBER(SEARCH("CTO",C29))+ISNUMBER(SEARCH("Chief Operating",C29))+ISNUMBER(SEARCH("Chief Financial",C29))+ISNUMBER(SEARCH("Gerente General",C29))+ISNUMBER(SEARCH("General Manager",C29))>0,'Configuración'!$B$34,'Configuración'!$B$35))))) -> 0 | V29: =IF(B29="","",IF(K29="Sí",'Configuración'!$B$5,0)+IF(L29="Semanal",'Configuración'!$B$6,IF(L29="Mensual",'Configuración'!$B$7,0))+IF(M29="Sí",'Configuración'!$B$8,0)+IF(N29="Sí",'Configuración'!$B$9,0)+IF(O29="Sí",'Configuración'!$B$10,0)+IF(P29="Sí",'Configuración'!$B$11,0)+IF(Q29="Sí",'Configuración'!$B$12,0)+S29+T29+U29) -> 28 | W29: =IF(B29="","",IF(V29>='Configuración'!$B$19,"A",IF(V29>='Configuración'!$B$20,"B",IF(V29>='Configuración'!$B$21,"C","Descarte")))) -> C
A30: =IF(B30="","",ROW()-2) -> 28 | B30: Bertha | C30: Sales Director | D30: Épica Inmobiliaria® | E30: bvillegas@epicainmobiliaria.com.co | F30: http://www.linkedin.com/in/bertha-in%c3%a9s-duque-villegas-2165b0a6 | G30: http://www.linkedin.com/company/epicainmobiliaria | H30: https://epicainmobiliaria.com | I30: real estate | J30: 14 | K30: No | L30: Inactivo | M30: No | N30: No | O30: No | Q30: No | S30: =IF(B30="","",IF(ISNUMBER(J30),IF(J30<=10,'Configuración'!$B$23,IF(J30<=50,'Configuración'!$B$24,IF(J30<=200,'Configuración'!$B$25,0))),0)) -> 4 | T30: =IF(B30="","",IF(ISNUMBER(SEARCH("information technology",I30))+ISNUMBER(SEARCH("software",I30))+ISNUMBER(SEARCH("internet",I30))+ISNUMBER(SEARCH("computer",I30))+ISNUMBER(SEARCH("saas",I30))+ISNUMBER(SEARCH("fintech",I30))+ISNUMBER(SEARCH("information services",I30))+ISNUMBER(SEARCH("telecommunications",I30))>0,'Configuración'!$B$27,'Configuración'!$B$28)) -> 4 | U30: =IF(B30="","",IF(ISNUMBER(SEARCH("CEO",C30))+ISNUMBER(SEARCH("Founder",C30))+ISNUMBER(SEARCH("Owner",C30))+ISNUMBER(SEARCH("Dueño",C30))+ISNUMBER(SEARCH("Director General",C30))+ISNUMBER(SEARCH("Presidente",C30))+ISNUMBER(SEARCH("President",C30))>0,'Configuración'!$B$31,IF(ISNUMBER(SEARCH("CMO",C30))+ISNUMBER(SEARCH("Chief Marketing",C30))+ISNUMBER(SEARCH("VP Marketing",C30))+ISNUMBER(SEARCH("Director de Marketing",C30))+ISNUMBER(SEARCH("Director Marketing",C30))+ISNUMBER(SEARCH("Head of Marketing",C30))+ISNUMBER(SEARCH("Head Marketing",C30))>0,'Configuración'!$B$32,IF(ISNUMBER(SEARCH("Marketing Manager",C30))+ISNUMBER(SEARCH("Gerente de Marketing",C30))+ISNUMBER(SEARCH("Growth Manager",C30))+ISNUMBER(SEARCH("Demand Gen",C30))+ISNUMBER(SEARCH("Marketing Lead",C30))>0,'Configuración'!$B$33,IF(ISNUMBER(SEARCH("COO",C30))+ISNUMBER(SEARCH("CFO",C30))+ISNUMBER(SEARCH("CTO",C30))+ISNUMBER(SEARCH("Chief Operating",C30))+ISNUMBER(SEARCH("Chief Financial",C30))+ISNUMBER(SEARCH("Gerente General",C30))+ISNUMBER(SEARCH("General Manager",C30))>0,'Configuración'!$B$34,'Configuración'!$B$35))))) -> 4 | V30: =IF(B30="","",IF(K30="Sí",'Configuración'!$B$5,0)+IF(L30="Semanal",'Configuración'!$B$6,IF(L30="Mensual",'Configuración'!$B$7,0))+IF(M30="Sí",'Configuración'!$B$8,0)+IF(N30="Sí",'Configuración'!$B$9,0)+IF(O30="Sí",'Configuración'!$B$10,0)+IF(P30="Sí",'Configuración'!$B$11,0)+IF(Q30="Sí",'Configuración'!$B$12,0)+S30+T30+U30) -> 12 | W30: =IF(B30="","",IF(V30>='Configuración'!$B$19,"A",IF(V30>='Configuración'!$B$20,"B",IF(V30>='Configuración'!$B$21,"C","Descarte")))) -> Descarte
A31: =IF(B31="","",ROW()-2) -> 29 | B31: Santiago | C31: CEO & Co-Founder | D31: ClosetUp | E31: sbarrios@closetup.com | F31: http://www.linkedin.com/in/santiago-barrios-9a83a5250 | G31: http://www.linkedin.com/company/closet-up | H31: https://closetup.com | I31: wholesale | J31: 9 | K31: No | L31: Inactivo | M31: No | N31: No | O31: No | Q31: No | S31: =IF(B31="","",IF(ISNUMBER(J31),IF(J31<=10,'Configuración'!$B$23,IF(J31<=50,'Configuración'!$B$24,IF(J31<=200,'Configuración'!$B$25,0))),0)) -> 12 | T31: =IF(B31="","",IF(ISNUMBER(SEARCH("information technology",I31))+ISNUMBER(SEARCH("software",I31))+ISNUMBER(SEARCH("internet",I31))+ISNUMBER(SEARCH("computer",I31))+ISNUMBER(SEARCH("saas",I31))+ISNUMBER(SEARCH("fintech",I31))+ISNUMBER(SEARCH("information services",I31))+ISNUMBER(SEARCH("telecommunications",I31))>0,'Configuración'!$B$27,'Configuración'!$B$28)) -> 4 | U31: =IF(B31="","",IF(ISNUMBER(SEARCH("CEO",C31))+ISNUMBER(SEARCH("Founder",C31))+ISNUMBER(SEARCH("Owner",C31))+ISNUMBER(SEARCH("Dueño",C31))+ISNUMBER(SEARCH("Director General",C31))+ISNUMBER(SEARCH("Presidente",C31))+ISNUMBER(SEARCH("President",C31))>0,'Configuración'!$B$31,IF(ISNUMBER(SEARCH("CMO",C31))+ISNUMBER(SEARCH("Chief Marketing",C31))+ISNUMBER(SEARCH("VP Marketing",C31))+ISNUMBER(SEARCH("Director de Marketing",C31))+ISNUMBER(SEARCH("Director Marketing",C31))+ISNUMBER(SEARCH("Head of Marketing",C31))+ISNUMBER(SEARCH("Head Marketing",C31))>0,'Configuración'!$B$32,IF(ISNUMBER(SEARCH("Marketing Manager",C31))+ISNUMBER(SEARCH("Gerente de Marketing",C31))+ISNUMBER(SEARCH("Growth Manager",C31))+ISNUMBER(SEARCH("Demand Gen",C31))+ISNUMBER(SEARCH("Marketing Lead",C31))>0,'Configuración'!$B$33,IF(ISNUMBER(SEARCH("COO",C31))+ISNUMBER(SEARCH("CFO",C31))+ISNUMBER(SEARCH("CTO",C31))+ISNUMBER(SEARCH("Chief Operating",C31))+ISNUMBER(SEARCH("Chief Financial",C31))+ISNUMBER(SEARCH("Gerente General",C31))+ISNUMBER(SEARCH("General Manager",C31))>0,'Configuración'!$B$34,'Configuración'!$B$35))))) -> 12 | V31: =IF(B31="","",IF(K31="Sí",'Configuración'!$B$5,0)+IF(L31="Semanal",'Configuración'!$B$6,IF(L31="Mensual",'Configuración'!$B$7,0))+IF(M31="Sí",'Configuración'!$B$8,0)+IF(N31="Sí",'Configuración'!$B$9,0)+IF(O31="Sí",'Configuración'!$B$10,0)+IF(P31="Sí",'Configuración'!$B$11,0)+IF(Q31="Sí",'Configuración'!$B$12,0)+S31+T31+U31) -> 28 | W31: =IF(B31="","",IF(V31>='Configuración'!$B$19,"A",IF(V31>='Configuración'!$B$20,"B",IF(V31>='Configuración'!$B$21,"C","Descarte")))) -> C
A32: =IF(B32="","",ROW()-2) -> 30 | B32: Felipe | C32: Chief Operating Officer | D32: Mis Propias Finanzas | E32: fzuluaga@mispropiasfinanzas.com | F32: http://www.linkedin.com/in/felipe-zuluaga-piedrahita | G32: http://www.linkedin.com/company/mis-propias-finanzas | H32: https://mispropiasfinanzas.com | I32: e-learning | J32: 23 | K32: Sí | L32: Semanal | M32: Sí | N32: Sí | O32: Sí | Q32: No | S32: =IF(B32="","",IF(ISNUMBER(J32),IF(J32<=10,'Configuración'!$B$23,IF(J32<=50,'Configuración'!$B$24,IF(J32<=200,'Configuración'!$B$25,0))),0)) -> 4 | T32: =IF(B32="","",IF(ISNUMBER(SEARCH("information technology",I32))+ISNUMBER(SEARCH("software",I32))+ISNUMBER(SEARCH("internet",I32))+ISNUMBER(SEARCH("computer",I32))+ISNUMBER(SEARCH("saas",I32))+ISNUMBER(SEARCH("fintech",I32))+ISNUMBER(SEARCH("information services",I32))+ISNUMBER(SEARCH("telecommunications",I32))>0,'Configuración'!$B$27,'Configuración'!$B$28)) -> 4 | U32: =IF(B32="","",IF(ISNUMBER(SEARCH("CEO",C32))+ISNUMBER(SEARCH("Founder",C32))+ISNUMBER(SEARCH("Owner",C32))+ISNUMBER(SEARCH("Dueño",C32))+ISNUMBER(SEARCH("Director General",C32))+ISNUMBER(SEARCH("Presidente",C32))+ISNUMBER(SEARCH("President",C32))>0,'Configuración'!$B$31,IF(ISNUMBER(SEARCH("CMO",C32))+ISNUMBER(SEARCH("Chief Marketing",C32))+ISNUMBER(SEARCH("VP Marketing",C32))+ISNUMBER(SEARCH("Director de Marketing",C32))+ISNUMBER(SEARCH("Director Marketing",C32))+ISNUMBER(SEARCH("Head of Marketing",C32))+ISNUMBER(SEARCH("Head Marketing",C32))>0,'Configuración'!$B$32,IF(ISNUMBER(SEARCH("Marketing Manager",C32))+ISNUMBER(SEARCH("Gerente de Marketing",C32))+ISNUMBER(SEARCH("Growth Manager",C32))+ISNUMBER(SEARCH("Demand Gen",C32))+ISNUMBER(SEARCH("Marketing Lead",C32))>0,'Configuración'!$B$33,IF(ISNUMBER(SEARCH("COO",C32))+ISNUMBER(SEARCH("CFO",C32))+ISNUMBER(SEARCH("CTO",C32))+ISNUMBER(SEARCH("Chief Operating",C32))+ISNUMBER(SEARCH("Chief Financial",C32))+ISNUMBER(SEARCH("Gerente General",C32))+ISNUMBER(SEARCH("General Manager",C32))>0,'Configuración'!$B$34,'Configuración'!$B$35))))) -> 4 | V32: =IF(B32="","",IF(K32="Sí",'Configuración'!$B$5,0)+IF(L32="Semanal",'Configuración'!$B$6,IF(L32="Mensual",'Configuración'!$B$7,0))+IF(M32="Sí",'Configuración'!$B$8,0)+IF(N32="Sí",'Configuración'!$B$9,0)+IF(O32="Sí",'Configuración'!$B$10,0)+IF(P32="Sí",'Configuración'!$B$11,0)+IF(Q32="Sí",'Configuración'!$B$12,0)+S32+T32+U32) -> 60 | W32: =IF(B32="","",IF(V32>='Configuración'!$B$19,"A",IF(V32>='Configuración'!$B$20,"B",IF(V32>='Configuración'!$B$21,"C","Descarte")))) -> A
A33: =IF(B33="","",ROW()-2) -> 31 | B33: Jose | C33: Founder & Executive Advisor | D33: JoseNanez | E33: jose@josenanez.com | F33: http://www.linkedin.com/in/jfnanezg | G33: http://www.linkedin.com/company/josenanez | H33: https://josenanez.com | I33: management consulting | J33: 1 | K33: No | L33: Inactivo | M33: Sí | N33: No | O33: No | Q33: No | S33: =IF(B33="","",IF(ISNUMBER(J33),IF(J33<=10,'Configuración'!$B$23,IF(J33<=50,'Configuración'!$B$24,IF(J33<=200,'Configuración'!$B$25,0))),0)) -> 12 | T33: =IF(B33="","",IF(ISNUMBER(SEARCH("information technology",I33))+ISNUMBER(SEARCH("software",I33))+ISNUMBER(SEARCH("internet",I33))+ISNUMBER(SEARCH("computer",I33))+ISNUMBER(SEARCH("saas",I33))+ISNUMBER(SEARCH("fintech",I33))+ISNUMBER(SEARCH("information services",I33))+ISNUMBER(SEARCH("telecommunications",I33))>0,'Configuración'!$B$27,'Configuración'!$B$28)) -> 4 | U33: =IF(B33="","",IF(ISNUMBER(SEARCH("CEO",C33))+ISNUMBER(SEARCH("Founder",C33))+ISNUMBER(SEARCH("Owner",C33))+ISNUMBER(SEARCH("Dueño",C33))+ISNUMBER(SEARCH("Director General",C33))+ISNUMBER(SEARCH("Presidente",C33))+ISNUMBER(SEARCH("President",C33))>0,'Configuración'!$B$31,IF(ISNUMBER(SEARCH("CMO",C33))+ISNUMBER(SEARCH("Chief Marketing",C33))+ISNUMBER(SEARCH("VP Marketing",C33))+ISNUMBER(SEARCH("Director de Marketing",C33))+ISNUMBER(SEARCH("Director Marketing",C33))+ISNUMBER(SEARCH("Head of Marketing",C33))+ISNUMBER(SEARCH("Head Marketing",C33))>0,'Configuración'!$B$32,IF(ISNUMBER(SEARCH("Marketing Manager",C33))+ISNUMBER(SEARCH("Gerente de Marketing",C33))+ISNUMBER(SEARCH("Growth Manager",C33))+ISNUMBER(SEARCH("Demand Gen",C33))+ISNUMBER(SEARCH("Marketing Lead",C33))>0,'Configuración'!$B$33,IF(ISNUMBER(SEARCH("COO",C33))+ISNUMBER(SEARCH("CFO",C33))+ISNUMBER(SEARCH("CTO",C33))+ISNUMBER(SEARCH("Chief Operating",C33))+ISNUMBER(SEARCH("Chief Financial",C33))+ISNUMBER(SEARCH("Gerente General",C33))+ISNUMBER(SEARCH("General Manager",C33))>0,'Configuración'!$B$34,'Configuración'!$B$35))))) -> 12 | V33: =IF(B33="","",IF(K33="Sí",'Configuración'!$B$5,0)+IF(L33="Semanal",'Configuración'!$B$6,IF(L33="Mensual",'Configuración'!$B$7,0))+IF(M33="Sí",'Configuración'!$B$8,0)+IF(N33="Sí",'Configuración'!$B$9,0)+IF(O33="Sí",'Configuración'!$B$10,0)+IF(P33="Sí",'Configuración'!$B$11,0)+IF(Q33="Sí",'Configuración'!$B$12,0)+S33+T33+U33) -> 40 | W33: =IF(B33="","",IF(V33>='Configuración'!$B$19,"A",IF(V33>='Configuración'!$B$20,"B",IF(V33>='Configuración'!$B$21,"C","Descarte")))) -> B
A34: =IF(B34="","",ROW()-2) -> 32 | B34: Alberto | C34: Co-Founder | D34: Setenta Veces Siete | E34: aospina@70v7.com | F34: http://www.linkedin.com/in/albertoospina | G34: http://www.linkedin.com/company/setenta-veces-siete | H34: https://70v7.com | I34: health, wellness & fitness | J34: 4 | K34: No | L34: Inactivo | M34: No | N34: Sí | O34: Sí | Q34: No | S34: =IF(B34="","",IF(ISNUMBER(J34),IF(J34<=10,'Configuración'!$B$23,IF(J34<=50,'Configuración'!$B$24,IF(J34<=200,'Configuración'!$B$25,0))),0)) -> 12 | T34: =IF(B34="","",IF(ISNUMBER(SEARCH("information technology",I34))+ISNUMBER(SEARCH("software",I34))+ISNUMBER(SEARCH("internet",I34))+ISNUMBER(SEARCH("computer",I34))+ISNUMBER(SEARCH("saas",I34))+ISNUMBER(SEARCH("fintech",I34))+ISNUMBER(SEARCH("information services",I34))+ISNUMBER(SEARCH("telecommunications",I34))>0,'Configuración'!$B$27,'Configuración'!$B$28)) -> 4 | U34: =IF(B34="","",IF(ISNUMBER(SEARCH("CEO",C34))+ISNUMBER(SEARCH("Founder",C34))+ISNUMBER(SEARCH("Owner",C34))+ISNUMBER(SEARCH("Dueño",C34))+ISNUMBER(SEARCH("Director General",C34))+ISNUMBER(SEARCH("Presidente",C34))+ISNUMBER(SEARCH("President",C34))>0,'Configuración'!$B$31,IF(ISNUMBER(SEARCH("CMO",C34))+ISNUMBER(SEARCH("Chief Marketing",C34))+ISNUMBER(SEARCH("VP Marketing",C34))+ISNUMBER(SEARCH("Director de Marketing",C34))+ISNUMBER(SEARCH("Director Marketing",C34))+ISNUMBER(SEARCH("Head of Marketing",C34))+ISNUMBER(SEARCH("Head Marketing",C34))>0,'Configuración'!$B$32,IF(ISNUMBER(SEARCH("Marketing Manager",C34))+ISNUMBER(SEARCH("Gerente de Marketing",C34))+ISNUMBER(SEARCH("Growth Manager",C34))+ISNUMBER(SEARCH("Demand Gen",C34))+ISNUMBER(SEARCH("Marketing Lead",C34))>0,'Configuración'!$B$33,IF(ISNUMBER(SEARCH("COO",C34))+ISNUMBER(SEARCH("CFO",C34))+ISNUMBER(SEARCH("CTO",C34))+ISNUMBER(SEARCH("Chief Operating",C34))+ISNUMBER(SEARCH("Chief Financial",C34))+ISNUMBER(SEARCH("Gerente General",C34))+ISNUMBER(SEARCH("General Manager",C34))>0,'Configuración'!$B$34,'Configuración'!$B$35))))) -> 12 | V34: =IF(B34="","",IF(K34="Sí",'Configuración'!$B$5,0)+IF(L34="Semanal",'Configuración'!$B$6,IF(L34="Mensual",'Configuración'!$B$7,0))+IF(M34="Sí",'Configuración'!$B$8,0)+IF(N34="Sí",'Configuración'!$B$9,0)+IF(O34="Sí",'Configuración'!$B$10,0)+IF(P34="Sí",'Configuración'!$B$11,0)+IF(Q34="Sí",'Configuración'!$B$12,0)+S34+T34+U34) -> 40 | W34: =IF(B34="","",IF(V34>='Configuración'!$B$19,"A",IF(V34>='Configuración'!$B$20,"B",IF(V34>='Configuración'!$B$21,"C","Descarte")))) -> B
A35: =IF(B35="","",ROW()-2) -> 33 | B35: Daniel | C35: CEO | D35: Cuantico | E35: daniel.medina@cuantico.com | F35: http://www.linkedin.com/in/daniel-medina-b1126727 | G35: http://www.linkedin.com/company/cuanticore | H35: https://cuantico.com | I35: information technology & services | J35: 23 | K35: No | L35: Semanal | M35: Sí | N35: No | O35: No | Q35: No | S35: =IF(B35="","",IF(ISNUMBER(J35),IF(J35<=10,'Configuración'!$B$23,IF(J35<=50,'Configuración'!$B$24,IF(J35<=200,'Configuración'!$B$25,0))),0)) -> 4 | T35: =IF(B35="","",IF(ISNUMBER(SEARCH("information technology",I35))+ISNUMBER(SEARCH("software",I35))+ISNUMBER(SEARCH("internet",I35))+ISNUMBER(SEARCH("computer",I35))+ISNUMBER(SEARCH("saas",I35))+ISNUMBER(SEARCH("fintech",I35))+ISNUMBER(SEARCH("information services",I35))+ISNUMBER(SEARCH("telecommunications",I35))>0,'Configuración'!$B$27,'Configuración'!$B$28)) -> 12 | U35: =IF(B35="","",IF(ISNUMBER(SEARCH("CEO",C35))+ISNUMBER(SEARCH("Founder",C35))+ISNUMBER(SEARCH("Owner",C35))+ISNUMBER(SEARCH("Dueño",C35))+ISNUMBER(SEARCH("Director General",C35))+ISNUMBER(SEARCH("Presidente",C35))+ISNUMBER(SEARCH("President",C35))>0,'Configuración'!$B$31,IF(ISNUMBER(SEARCH("CMO",C35))+ISNUMBER(SEARCH("Chief Marketing",C35))+ISNUMBER(SEARCH("VP Marketing",C35))+ISNUMBER(SEARCH("Director de Marketing",C35))+ISNUMBER(SEARCH("Director Marketing",C35))+ISNUMBER(SEARCH("Head of Marketing",C35))+ISNUMBER(SEARCH("Head Marketing",C35))>0,'Configuración'!$B$32,IF(ISNUMBER(SEARCH("Marketing Manager",C35))+ISNUMBER(SEARCH("Gerente de Marketing",C35))+ISNUMBER(SEARCH("Growth Manager",C35))+ISNUMBER(SEARCH("Demand Gen",C35))+ISNUMBER(SEARCH("Marketing Lead",C35))>0,'Configuración'!$B$33,IF(ISNUMBER(SEARCH("COO",C35))+ISNUMBER(SEARCH("CFO",C35))+ISNUMBER(SEARCH("CTO",C35))+ISNUMBER(SEARCH("Chief Operating",C35))+ISNUMBER(SEARCH("Chief Financial",C35))+ISNUMBER(SEARCH("Gerente General",C35))+ISNUMBER(SEARCH("General Manager",C35))>0,'Configuración'!$B$34,'Configuración'!$B$35))))) -> 12 | V35: =IF(B35="","",IF(K35="Sí",'Configuración'!$B$5,0)+IF(L35="Semanal",'Configuración'!$B$6,IF(L35="Mensual",'Configuración'!$B$7,0))+IF(M35="Sí",'Configuración'!$B$8,0)+IF(N35="Sí",'Configuración'!$B$9,0)+IF(O35="Sí",'Configuración'!$B$10,0)+IF(P35="Sí",'Configuración'!$B$11,0)+IF(Q35="Sí",'Configuración'!$B$12,0)+S35+T35+U35) -> 52 | W35: =IF(B35="","",IF(V35>='Configuración'!$B$19,"A",IF(V35>='Configuración'!$B$20,"B",IF(V35>='Configuración'!$B$21,"C","Descarte")))) -> B
A36: =IF(B36="","",ROW()-2) -> 34 | B36: Rodrigo | C36: Co Founder Business Owner - Business Development | D36: Ingennova SAS | E36: rodrigo.villamil@ingennova.com | F36: http://www.linkedin.com/in/villamilrodrigo | G36: http://www.linkedin.com/company/ingennova-sas | H36: https://ingennova.com | I36: machinery | J36: 26 | K36: No | L36: Inactivo | M36: No | N36: No | O36: No | Q36: No | S36: =IF(B36="","",IF(ISNUMBER(J36),IF(J36<=10,'Configuración'!$B$23,IF(J36<=50,'Configuración'!$B$24,IF(J36<=200,'Configuración'!$B$25,0))),0)) -> 4 | T36: =IF(B36="","",IF(ISNUMBER(SEARCH("information technology",I36))+ISNUMBER(SEARCH("software",I36))+ISNUMBER(SEARCH("internet",I36))+ISNUMBER(SEARCH("computer",I36))+ISNUMBER(SEARCH("saas",I36))+ISNUMBER(SEARCH("fintech",I36))+ISNUMBER(SEARCH("information services",I36))+ISNUMBER(SEARCH("telecommunications",I36))>0,'Configuración'!$B$27,'Configuración'!$B$28)) -> 4 | U36: =IF(B36="","",IF(ISNUMBER(SEARCH("CEO",C36))+ISNUMBER(SEARCH("Founder",C36))+ISNUMBER(SEARCH("Owner",C36))+ISNUMBER(SEARCH("Dueño",C36))+ISNUMBER(SEARCH("Director General",C36))+ISNUMBER(SEARCH("Presidente",C36))+ISNUMBER(SEARCH("President",C36))>0,'Configuración'!$B$31,IF(ISNUMBER(SEARCH("CMO",C36))+ISNUMBER(SEARCH("Chief Marketing",C36))+ISNUMBER(SEARCH("VP Marketing",C36))+ISNUMBER(SEARCH("Director de Marketing",C36))+ISNUMBER(SEARCH("Director Marketing",C36))+ISNUMBER(SEARCH("Head of Marketing",C36))+ISNUMBER(SEARCH("Head Marketing",C36))>0,'Configuración'!$B$32,IF(ISNUMBER(SEARCH("Marketing Manager",C36))+ISNUMBER(SEARCH("Gerente de Marketing",C36))+ISNUMBER(SEARCH("Growth Manager",C36))+ISNUMBER(SEARCH("Demand Gen",C36))+ISNUMBER(SEARCH("Marketing Lead",C36))>0,'Configuración'!$B$33,IF(ISNUMBER(SEARCH("COO",C36))+ISNUMBER(SEARCH("CFO",C36))+ISNUMBER(SEARCH("CTO",C36))+ISNUMBER(SEARCH("Chief Operating",C36))+ISNUMBER(SEARCH("Chief Financial",C36))+ISNUMBER(SEARCH("Gerente General",C36))+ISNUMBER(SEARCH("General Manager",C36))>0,'Configuración'!$B$34,'Configuración'!$B$35))))) -> 12 | V36: =IF(B36="","",IF(K36="Sí",'Configuración'!$B$5,0)+IF(L36="Semanal",'Configuración'!$B$6,IF(L36="Mensual",'Configuración'!$B$7,0))+IF(M36="Sí",'Configuración'!$B$8,0)+IF(N36="Sí",'Configuración'!$B$9,0)+IF(O36="Sí",'Configuración'!$B$10,0)+IF(P36="Sí",'Configuración'!$B$11,0)+IF(Q36="Sí",'Configuración'!$B$12,0)+S36+T36+U36) -> 20 | W36: =IF(B36="","",IF(V36>='Configuración'!$B$19,"A",IF(V36>='Configuración'!$B$20,"B",IF(V36>='Configuración'!$B$21,"C","Descarte")))) -> Descarte
A37: =IF(B37="","",ROW()-2) -> 35 | B37: Mauricio | C37: CEO | Fintech Especializada en Créditos de Libranza | Experto Modelos de Riesgo Crediticios | D37: LiberTec | E37: mauricio@libertec.co | F37: http://www.linkedin.com/in/mauricio-anjel-87590664 | G37: http://www.linkedin.com/company/libertec-co | H37: https://libertec.co | I37: financial services | J37: 10 | K37: No | L37: Inactivo | M37: No | N37: No | O37: No | Q37: No | S37: =IF(B37="","",IF(ISNUMBER(J37),IF(J37<=10,'Configuración'!$B$23,IF(J37<=50,'Configuración'!$B$24,IF(J37<=200,'Configuración'!$B$25,0))),0)) -> 12 | T37: =IF(B37="","",IF(ISNUMBER(SEARCH("information technology",I37))+ISNUMBER(SEARCH("software",I37))+ISNUMBER(SEARCH("internet",I37))+ISNUMBER(SEARCH("computer",I37))+ISNUMBER(SEARCH("saas",I37))+ISNUMBER(SEARCH("fintech",I37))+ISNUMBER(SEARCH("information services",I37))+ISNUMBER(SEARCH("telecommunications",I37))>0,'Configuración'!$B$27,'Configuración'!$B$28)) -> 4 | U37: =IF(B37="","",IF(ISNUMBER(SEARCH("CEO",C37))+ISNUMBER(SEARCH("Founder",C37))+ISNUMBER(SEARCH("Owner",C37))+ISNUMBER(SEARCH("Dueño",C37))+ISNUMBER(SEARCH("Director General",C37))+ISNUMBER(SEARCH("Presidente",C37))+ISNUMBER(SEARCH("President",C37))>0,'Configuración'!$B$31,IF(ISNUMBER(SEARCH("CMO",C37))+ISNUMBER(SEARCH("Chief Marketing",C37))+ISNUMBER(SEARCH("VP Marketing",C37))+ISNUMBER(SEARCH("Director de Marketing",C37))+ISNUMBER(SEARCH("Director Marketing",C37))+ISNUMBER(SEARCH("Head of Marketing",C37))+ISNUMBER(SEARCH("Head Marketing",C37))>0,'Configuración'!$B$32,IF(ISNUMBER(SEARCH("Marketing Manager",C37))+ISNUMBER(SEARCH("Gerente de Marketing",C37))+ISNUMBER(SEARCH("Growth Manager",C37))+ISNUMBER(SEARCH("Demand Gen",C37))+ISNUMBER(SEARCH("Marketing Lead",C37))>0,'Configuración'!$B$33,IF(ISNUMBER(SEARCH("COO",C37))+ISNUMBER(SEARCH("CFO",C37))+ISNUMBER(SEARCH("CTO",C37))+ISNUMBER(SEARCH("Chief Operating",C37))+ISNUMBER(SEARCH("Chief Financial",C37))+ISNUMBER(SEARCH("Gerente General",C37))+ISNUMBER(SEARCH("General Manager",C37))>0,'Configuración'!$B$34,'Configuración'!$B$35))))) -> 12 | V37: =IF(B37="","",IF(K37="Sí",'Configuración'!$B$5,0)+IF(L37="Semanal",'Configuración'!$B$6,IF(L37="Mensual",'Configuración'!$B$7,0))+IF(M37="Sí",'Configuración'!$B$8,0)+IF(N37="Sí",'Configuración'!$B$9,0)+IF(O37="Sí",'Configuración'!$B$10,0)+IF(P37="Sí",'Configuración'!$B$11,0)+IF(Q37="Sí",'Configuración'!$B$12,0)+S37+T37+U37) -> 28 | W37: =IF(B37="","",IF(V37>='Configuración'!$B$19,"A",IF(V37>='Configuración'!$B$20,"B",IF(V37>='Configuración'!$B$21,"C","Descarte")))) -> C
A38: =IF(B38="","",ROW()-2) -> 36 | B38: Juan | C38: Co-founder | D38: Keep Up | E38: jgarzon@keepup.news | F38: http://www.linkedin.com/in/juan-sebastian-garzon-cano-729618b3 | G38: http://www.linkedin.com/company/keepupagencia | H38: https://keepup.news | I38: information technology & services | J38: 38 | R38: Empresa repetida | S38: =IF(B38="","",IF(ISNUMBER(J38),IF(J38<=10,'Configuración'!$B$23,IF(J38<=50,'Configuración'!$B$24,IF(J38<=200,'Configuración'!$B$25,0))),0)) -> 4 | T38: =IF(B38="","",IF(ISNUMBER(SEARCH("information technology",I38))+ISNUMBER(SEARCH("software",I38))+ISNUMBER(SEARCH("internet",I38))+ISNUMBER(SEARCH("computer",I38))+ISNUMBER(SEARCH("saas",I38))+ISNUMBER(SEARCH("fintech",I38))+ISNUMBER(SEARCH("information services",I38))+ISNUMBER(SEARCH("telecommunications",I38))>0,'Configuración'!$B$27,'Configuración'!$B$28)) -> 12 | U38: =IF(B38="","",IF(ISNUMBER(SEARCH("CEO",C38))+ISNUMBER(SEARCH("Founder",C38))+ISNUMBER(SEARCH("Owner",C38))+ISNUMBER(SEARCH("Dueño",C38))+ISNUMBER(SEARCH("Director General",C38))+ISNUMBER(SEARCH("Presidente",C38))+ISNUMBER(SEARCH("President",C38))>0,'Configuración'!$B$31,IF(ISNUMBER(SEARCH("CMO",C38))+ISNUMBER(SEARCH("Chief Marketing",C38))+ISNUMBER(SEARCH("VP Marketing",C38))+ISNUMBER(SEARCH("Director de Marketing",C38))+ISNUMBER(SEARCH("Director Marketing",C38))+ISNUMBER(SEARCH("Head of Marketing",C38))+ISNUMBER(SEARCH("Head Marketing",C38))>0,'Configuración'!$B$32,IF(ISNUMBER(SEARCH("Marketing Manager",C38))+ISNUMBER(SEARCH("Gerente de Marketing",C38))+ISNUMBER(SEARCH("Growth Manager",C38))+ISNUMBER(SEARCH("Demand Gen",C38))+ISNUMBER(SEARCH("Marketing Lead",C38))>0,'Configuración'!$B$33,IF(ISNUMBER(SEARCH("COO",C38))+ISNUMBER(SEARCH("CFO",C38))+ISNUMBER(SEARCH("CTO",C38))+ISNUMBER(SEARCH("Chief Operating",C38))+ISNUMBER(SEARCH("Chief Financial",C38))+ISNUMBER(SEARCH("Gerente General",C38))+ISNUMBER(SEARCH("General Manager",C38))>0,'Configuración'!$B$34,'Configuración'!$B$35))))) -> 12 | V38: =IF(B38="","",IF(K38="Sí",'Configuración'!$B$5,0)+IF(L38="Semanal",'Configuración'!$B$6,IF(L38="Mensual",'Configuración'!$B$7,0))+IF(M38="Sí",'Configuración'!$B$8,0)+IF(N38="Sí",'Configuración'!$B$9,0)+IF(O38="Sí",'Configuración'!$B$10,0)+IF(P38="Sí",'Configuración'!$B$11,0)+IF(Q38="Sí",'Configuración'!$B$12,0)+S38+T38+U38) -> 28 | W38: =IF(B38="","",IF(V38>='Configuración'!$B$19,"A",IF(V38>='Configuración'!$B$20,"B",IF(V38>='Configuración'!$B$21,"C","Descarte")))) -> C
A39: =IF(B39="","",ROW()-2) -> 37 | B39: Andres | C39: Chief Operations Officer | D39: RODDOS®️ | E39: andres@roddos.com | F39: http://www.linkedin.com/in/andres-san-juan-03105643 | G39: http://www.linkedin.com/company/roddos%c2%ae%ef%b8%8f | H39: https://roddos.com | I39: financial services | J39: 5 | K39: No | L39: Inactivo | M39: No | N39: No | O39: No | Q39: No | S39: =IF(B39="","",IF(ISNUMBER(J39),IF(J39<=10,'Configuración'!$B$23,IF(J39<=50,'Configuración'!$B$24,IF(J39<=200,'Configuración'!$B$25,0))),0)) -> 12 | T39: =IF(B39="","",IF(ISNUMBER(SEARCH("information technology",I39))+ISNUMBER(SEARCH("software",I39))+ISNUMBER(SEARCH("internet",I39))+ISNUMBER(SEARCH("computer",I39))+ISNUMBER(SEARCH("saas",I39))+ISNUMBER(SEARCH("fintech",I39))+ISNUMBER(SEARCH("information services",I39))+ISNUMBER(SEARCH("telecommunications",I39))>0,'Configuración'!$B$27,'Configuración'!$B$28)) -> 4 | U39: =IF(B39="","",IF(ISNUMBER(SEARCH("CEO",C39))+ISNUMBER(SEARCH("Founder",C39))+ISNUMBER(SEARCH("Owner",C39))+ISNUMBER(SEARCH("Dueño",C39))+ISNUMBER(SEARCH("Director General",C39))+ISNUMBER(SEARCH("Presidente",C39))+ISNUMBER(SEARCH("President",C39))>0,'Configuración'!$B$31,IF(ISNUMBER(SEARCH("CMO",C39))+ISNUMBER(SEARCH("Chief Marketing",C39))+ISNUMBER(SEARCH("VP Marketing",C39))+ISNUMBER(SEARCH("Director de Marketing",C39))+ISNUMBER(SEARCH("Director Marketing",C39))+ISNUMBER(SEARCH("Head of Marketing",C39))+ISNUMBER(SEARCH("Head Marketing",C39))>0,'Configuración'!$B$32,IF(ISNUMBER(SEARCH("Marketing Manager",C39))+ISNUMBER(SEARCH("Gerente de Marketing",C39))+ISNUMBER(SEARCH("Growth Manager",C39))+ISNUMBER(SEARCH("Demand Gen",C39))+ISNUMBER(SEARCH("Marketing Lead",C39))>0,'Configuración'!$B$33,IF(ISNUMBER(SEARCH("COO",C39))+ISNUMBER(SEARCH("CFO",C39))+ISNUMBER(SEARCH("CTO",C39))+ISNUMBER(SEARCH("Chief Operating",C39))+ISNUMBER(SEARCH("Chief Financial",C39))+ISNUMBER(SEARCH("Gerente General",C39))+ISNUMBER(SEARCH("General Manager",C39))>0,'Configuración'!$B$34,'Configuración'!$B$35))))) -> 0 | V39: =IF(B39="","",IF(K39="Sí",'Configuración'!$B$5,0)+IF(L39="Semanal",'Configuración'!$B$6,IF(L39="Mensual",'Configuración'!$B$7,0))+IF(M39="Sí",'Configuración'!$B$8,0)+IF(N39="Sí",'Configuración'!$B$9,0)+IF(O39="Sí",'Configuración'!$B$10,0)+IF(P39="Sí",'Configuración'!$B$11,0)+IF(Q39="Sí",'Configuración'!$B$12,0)+S39+T39+U39) -> 16 | W39: =IF(B39="","",IF(V39>='Configuración'!$B$19,"A",IF(V39>='Configuración'!$B$20,"B",IF(V39>='Configuración'!$B$21,"C","Descarte")))) -> Descarte
A40: =IF(B40="","",ROW()-2) -> 38 | B40: Henry | C40: CEO - Cofounder | D40: Seika ai | E40: henry@seika.ai | F40: http://www.linkedin.com/in/henry-bravo-b9315583 | G40: http://www.linkedin.com/company/seika-ai | H40: https://seika.ai | I40: information technology & services | J40: 4 | K40: Sí | L40: Semanal | M40: Sí | N40: No | O40: No | Q40: No | R40: Posible Tier 1 | S40: =IF(B40="","",IF(ISNUMBER(J40),IF(J40<=10,'Configuración'!$B$23,IF(J40<=50,'Configuración'!$B$24,IF(J40<=200,'Configuración'!$B$25,0))),0)) -> 12 | T40: =IF(B40="","",IF(ISNUMBER(SEARCH("information technology",I40))+ISNUMBER(SEARCH("software",I40))+ISNUMBER(SEARCH("internet",I40))+ISNUMBER(SEARCH("computer",I40))+ISNUMBER(SEARCH("saas",I40))+ISNUMBER(SEARCH("fintech",I40))+ISNUMBER(SEARCH("information services",I40))+ISNUMBER(SEARCH("telecommunications",I40))>0,'Configuración'!$B$27,'Configuración'!$B$28)) -> 12 | U40: =IF(B40="","",IF(ISNUMBER(SEARCH("CEO",C40))+ISNUMBER(SEARCH("Founder",C40))+ISNUMBER(SEARCH("Owner",C40))+ISNUMBER(SEARCH("Dueño",C40))+ISNUMBER(SEARCH("Director General",C40))+ISNUMBER(SEARCH("Presidente",C40))+ISNUMBER(SEARCH("President",C40))>0,'Configuración'!$B$31,IF(ISNUMBER(SEARCH("CMO",C40))+ISNUMBER(SEARCH("Chief Marketing",C40))+ISNUMBER(SEARCH("VP Marketing",C40))+ISNUMBER(SEARCH("Director de Marketing",C40))+ISNUMBER(SEARCH("Director Marketing",C40))+ISNUMBER(SEARCH("Head of Marketing",C40))+ISNUMBER(SEARCH("Head Marketing",C40))>0,'Configuración'!$B$32,IF(ISNUMBER(SEARCH("Marketing Manager",C40))+ISNUMBER(SEARCH("Gerente de Marketing",C40))+ISNUMBER(SEARCH("Growth Manager",C40))+ISNUMBER(SEARCH("Demand Gen",C40))+ISNUMBER(SEARCH("Marketing Lead",C40))>0,'Configuración'!$B$33,IF(ISNUMBER(SEARCH("COO",C40))+ISNUMBER(SEARCH("CFO",C40))+ISNUMBER(SEARCH("CTO",C40))+ISNUMBER(SEARCH("Chief Operating",C40))+ISNUMBER(SEARCH("Chief Financial",C40))+ISNUMBER(SEARCH("Gerente General",C40))+ISNUMBER(SEARCH("General Manager",C40))>0,'Configuración'!$B$34,'Configuración'!$B$35))))) -> 12 | V40: =IF(B40="","",IF(K40="Sí",'Configuración'!$B$5,0)+IF(L40="Semanal",'Configuración'!$B$6,IF(L40="Mensual",'Configuración'!$B$7,0))+IF(M40="Sí",'Configuración'!$B$8,0)+IF(N40="Sí",'Configuración'!$B$9,0)+IF(O40="Sí",'Configuración'!$B$10,0)+IF(P40="Sí",'Configuración'!$B$11,0)+IF(Q40="Sí",'Configuración'!$B$12,0)+S40+T40+U40) -> 72 | W40: =IF(B40="","",IF(V40>='Configuración'!$B$19,"A",IF(V40>='Configuración'!$B$20,"B",IF(V40>='Configuración'!$B$21,"C","Descarte")))) -> A
A41: =IF(B41="","",ROW()-2) -> 39 | B41: Juan | C41: Co-Founder and CSO | D41: Sporalys | E41: juan@sporalys.com | F41: http://www.linkedin.com/in/juansrubiano | G41: http://www.linkedin.com/company/kojilabco | H41: https://koji.com.co | I41: research | J41: 2 | K41: No | L41: Semanal | M41: No | N41: No | O41: No | Q41: No | S41: =IF(B41="","",IF(ISNUMBER(J41),IF(J41<=10,'Configuración'!$B$23,IF(J41<=50,'Configuración'!$B$24,IF(J41<=200,'Configuración'!$B$25,0))),0)) -> 12 | T41: =IF(B41="","",IF(ISNUMBER(SEARCH("information technology",I41))+ISNUMBER(SEARCH("software",I41))+ISNUMBER(SEARCH("internet",I41))+ISNUMBER(SEARCH("computer",I41))+ISNUMBER(SEARCH("saas",I41))+ISNUMBER(SEARCH("fintech",I41))+ISNUMBER(SEARCH("information services",I41))+ISNUMBER(SEARCH("telecommunications",I41))>0,'Configuración'!$B$27,'Configuración'!$B$28)) -> 4 | U41: =IF(B41="","",IF(ISNUMBER(SEARCH("CEO",C41))+ISNUMBER(SEARCH("Founder",C41))+ISNUMBER(SEARCH("Owner",C41))+ISNUMBER(SEARCH("Dueño",C41))+ISNUMBER(SEARCH("Director General",C41))+ISNUMBER(SEARCH("Presidente",C41))+ISNUMBER(SEARCH("President",C41))>0,'Configuración'!$B$31,IF(ISNUMBER(SEARCH("CMO",C41))+ISNUMBER(SEARCH("Chief Marketing",C41))+ISNUMBER(SEARCH("VP Marketing",C41))+ISNUMBER(SEARCH("Director de Marketing",C41))+ISNUMBER(SEARCH("Director Marketing",C41))+ISNUMBER(SEARCH("Head of Marketing",C41))+ISNUMBER(SEARCH("Head Marketing",C41))>0,'Configuración'!$B$32,IF(ISNUMBER(SEARCH("Marketing Manager",C41))+ISNUMBER(SEARCH("Gerente de Marketing",C41))+ISNUMBER(SEARCH("Growth Manager",C41))+ISNUMBER(SEARCH("Demand Gen",C41))+ISNUMBER(SEARCH("Marketing Lead",C41))>0,'Configuración'!$B$33,IF(ISNUMBER(SEARCH("COO",C41))+ISNUMBER(SEARCH("CFO",C41))+ISNUMBER(SEARCH("CTO",C41))+ISNUMBER(SEARCH("Chief Operating",C41))+ISNUMBER(SEARCH("Chief Financial",C41))+ISNUMBER(SEARCH("Gerente General",C41))+ISNUMBER(SEARCH("General Manager",C41))>0,'Configuración'!$B$34,'Configuración'!$B$35))))) -> 12 | V41: =IF(B41="","",IF(K41="Sí",'Configuración'!$B$5,0)+IF(L41="Semanal",'Configuración'!$B$6,IF(L41="Mensual",'Configuración'!$B$7,0))+IF(M41="Sí",'Configuración'!$B$8,0)+IF(N41="Sí",'Configuración'!$B$9,0)+IF(O41="Sí",'Configuración'!$B$10,0)+IF(P41="Sí",'Configuración'!$B$11,0)+IF(Q41="Sí",'Configuración'!$B$12,0)+S41+T41+U41) -> 40 | W41: =IF(B41="","",IF(V41>='Configuración'!$B$19,"A",IF(V41>='Configuración'!$B$20,"B",IF(V41>='Configuración'!$B$21,"C","Descarte")))) -> B
A42: =IF(B42="","",ROW()-2) -> 40 | B42: Santiago | C42: Chief Revenue Officer | D42: NanoFreeze | E42: santiago@nanofreeze.com.co | F42: http://www.linkedin.com/in/santiagosaenzariza | G42: http://www.linkedin.com/company/nanofreeze | H42: https://nanofreeze.com.co | I42: research | J42: 8 | K42: No | L42: Mensual | M42: No | N42: No | O42: No | Q42: No | S42: =IF(B42="","",IF(ISNUMBER(J42),IF(J42<=10,'Configuración'!$B$23,IF(J42<=50,'Configuración'!$B$24,IF(J42<=200,'Configuración'!$B$25,0))),0)) -> 12 | T42: =IF(B42="","",IF(ISNUMBER(SEARCH("information technology",I42))+ISNUMBER(SEARCH("software",I42))+ISNUMBER(SEARCH("internet",I42))+ISNUMBER(SEARCH("computer",I42))+ISNUMBER(SEARCH("saas",I42))+ISNUMBER(SEARCH("fintech",I42))+ISNUMBER(SEARCH("information services",I42))+ISNUMBER(SEARCH("telecommunications",I42))>0,'Configuración'!$B$27,'Configuración'!$B$28)) -> 4 | U42: =IF(B42="","",IF(ISNUMBER(SEARCH("CEO",C42))+ISNUMBER(SEARCH("Founder",C42))+ISNUMBER(SEARCH("Owner",C42))+ISNUMBER(SEARCH("Dueño",C42))+ISNUMBER(SEARCH("Director General",C42))+ISNUMBER(SEARCH("Presidente",C42))+ISNUMBER(SEARCH("President",C42))>0,'Configuración'!$B$31,IF(ISNUMBER(SEARCH("CMO",C42))+ISNUMBER(SEARCH("Chief Marketing",C42))+ISNUMBER(SEARCH("VP Marketing",C42))+ISNUMBER(SEARCH("Director de Marketing",C42))+ISNUMBER(SEARCH("Director Marketing",C42))+ISNUMBER(SEARCH("Head of Marketing",C42))+ISNUMBER(SEARCH("Head Marketing",C42))>0,'Configuración'!$B$32,IF(ISNUMBER(SEARCH("Marketing Manager",C42))+ISNUMBER(SEARCH("Gerente de Marketing",C42))+ISNUMBER(SEARCH("Growth Manager",C42))+ISNUMBER(SEARCH("Demand Gen",C42))+ISNUMBER(SEARCH("Marketing Lead",C42))>0,'Configuración'!$B$33,IF(ISNUMBER(SEARCH("COO",C42))+ISNUMBER(SEARCH("CFO",C42))+ISNUMBER(SEARCH("CTO",C42))+ISNUMBER(SEARCH("Chief Operating",C42))+ISNUMBER(SEARCH("Chief Financial",C42))+ISNUMBER(SEARCH("Gerente General",C42))+ISNUMBER(SEARCH("General Manager",C42))>0,'Configuración'!$B$34,'Configuración'!$B$35))))) -> 0 | V42: =IF(B42="","",IF(K42="Sí",'Configuración'!$B$5,0)+IF(L42="Semanal",'Configuración'!$B$6,IF(L42="Mensual",'Configuración'!$B$7,0))+IF(M42="Sí",'Configuración'!$B$8,0)+IF(N42="Sí",'Configuración'!$B$9,0)+IF(O42="Sí",'Configuración'!$B$10,0)+IF(P42="Sí",'Configuración'!$B$11,0)+IF(Q42="Sí",'Configuración'!$B$12,0)+S42+T42+U42) -> 20 | W42: =IF(B42="","",IF(V42>='Configuración'!$B$19,"A",IF(V42>='Configuración'!$B$20,"B",IF(V42>='Configuración'!$B$21,"C","Descarte")))) -> Descarte
A43: =IF(B43="","",ROW()-2) -> 41 | B43: Jorge | C43: CEO - Co-Founder | D43: Saggio ESG | E43: juseche@saggioesg.com | F43: http://www.linkedin.com/in/jorge-alfonso-useche-goenaga-00045a86 | G43: http://www.linkedin.com/company/saggio-esg-software | H43: https://saggioesg.com | I43: information technology & services | J43: 7 | K43: No | L43: Inactivo | M43: Sí | N43: No | O43: No | Q43: No | R43: Posible Tier 1 | S43: =IF(B43="","",IF(ISNUMBER(J43),IF(J43<=10,'Configuración'!$B$23,IF(J43<=50,'Configuración'!$B$24,IF(J43<=200,'Configuración'!$B$25,0))),0)) -> 12 | T43: =IF(B43="","",IF(ISNUMBER(SEARCH("information technology",I43))+ISNUMBER(SEARCH("software",I43))+ISNUMBER(SEARCH("internet",I43))+ISNUMBER(SEARCH("computer",I43))+ISNUMBER(SEARCH("saas",I43))+ISNUMBER(SEARCH("fintech",I43))+ISNUMBER(SEARCH("information services",I43))+ISNUMBER(SEARCH("telecommunications",I43))>0,'Configuración'!$B$27,'Configuración'!$B$28)) -> 12 | U43: =IF(B43="","",IF(ISNUMBER(SEARCH("CEO",C43))+ISNUMBER(SEARCH("Founder",C43))+ISNUMBER(SEARCH("Owner",C43))+ISNUMBER(SEARCH("Dueño",C43))+ISNUMBER(SEARCH("Director General",C43))+ISNUMBER(SEARCH("Presidente",C43))+ISNUMBER(SEARCH("President",C43))>0,'Configuración'!$B$31,IF(ISNUMBER(SEARCH("CMO",C43))+ISNUMBER(SEARCH("Chief Marketing",C43))+ISNUMBER(SEARCH("VP Marketing",C43))+ISNUMBER(SEARCH("Director de Marketing",C43))+ISNUMBER(SEARCH("Director Marketing",C43))+ISNUMBER(SEARCH("Head of Marketing",C43))+ISNUMBER(SEARCH("Head Marketing",C43))>0,'Configuración'!$B$32,IF(ISNUMBER(SEARCH("Marketing Manager",C43))+ISNUMBER(SEARCH("Gerente de Marketing",C43))+ISNUMBER(SEARCH("Growth Manager",C43))+ISNUMBER(SEARCH("Demand Gen",C43))+ISNUMBER(SEARCH("Marketing Lead",C43))>0,'Configuración'!$B$33,IF(ISNUMBER(SEARCH("COO",C43))+ISNUMBER(SEARCH("CFO",C43))+ISNUMBER(SEARCH("CTO",C43))+ISNUMBER(SEARCH("Chief Operating",C43))+ISNUMBER(SEARCH("Chief Financial",C43))+ISNUMBER(SEARCH("Gerente General",C43))+ISNUMBER(SEARCH("General Manager",C43))>0,'Configuración'!$B$34,'Configuración'!$B$35))))) -> 12 | V43: =IF(B43="","",IF(K43="Sí",'Configuración'!$B$5,0)+IF(L43="Semanal",'Configuración'!$B$6,IF(L43="Mensual",'Configuración'!$B$7,0))+IF(M43="Sí",'Configuración'!$B$8,0)+IF(N43="Sí",'Configuración'!$B$9,0)+IF(O43="Sí",'Configuración'!$B$10,0)+IF(P43="Sí",'Configuración'!$B$11,0)+IF(Q43="Sí",'Configuración'!$B$12,0)+S43+T43+U43) -> 48 | W43: =IF(B43="","",IF(V43>='Configuración'!$B$19,"A",IF(V43>='Configuración'!$B$20,"B",IF(V43>='Configuración'!$B$21,"C","Descarte")))) -> B
A44: =IF(B44="","",ROW()-2) -> 42 | B44: Julian | C44: Chief Executive Officer | D44: Estrategias Comerciales y de Mercadeo | E44: j.arenas@estrategiascomerciales.co | F44: http://www.linkedin.com/in/julian-camilo-arenas-torres-38147135 | G44: http://www.linkedin.com/company/estrategias-comerciales-y-de-mercadeo | H44: https://estrategiascomerciales.co | I44: real estate | J44: 50 | K44: No | L44: Inactivo | M44: No | N44: No | O44: No | Q44: No | S44: =IF(B44="","",IF(ISNUMBER(J44),IF(J44<=10,'Configuración'!$B$23,IF(J44<=50,'Configuración'!$B$24,IF(J44<=200,'Configuración'!$B$25,0))),0)) -> 4 | T44: =IF(B44="","",IF(ISNUMBER(SEARCH("information technology",I44))+ISNUMBER(SEARCH("software",I44))+ISNUMBER(SEARCH("internet",I44))+ISNUMBER(SEARCH("computer",I44))+ISNUMBER(SEARCH("saas",I44))+ISNUMBER(SEARCH("fintech",I44))+ISNUMBER(SEARCH("information services",I44))+ISNUMBER(SEARCH("telecommunications",I44))>0,'Configuración'!$B$27,'Configuración'!$B$28)) -> 4 | U44: =IF(B44="","",IF(ISNUMBER(SEARCH("CEO",C44))+ISNUMBER(SEARCH("Founder",C44))+ISNUMBER(SEARCH("Owner",C44))+ISNUMBER(SEARCH("Dueño",C44))+ISNUMBER(SEARCH("Director General",C44))+ISNUMBER(SEARCH("Presidente",C44))+ISNUMBER(SEARCH("President",C44))>0,'Configuración'!$B$31,IF(ISNUMBER(SEARCH("CMO",C44))+ISNUMBER(SEARCH("Chief Marketing",C44))+ISNUMBER(SEARCH("VP Marketing",C44))+ISNUMBER(SEARCH("Director de Marketing",C44))+ISNUMBER(SEARCH("Director Marketing",C44))+ISNUMBER(SEARCH("Head of Marketing",C44))+ISNUMBER(SEARCH("Head Marketing",C44))>0,'Configuración'!$B$32,IF(ISNUMBER(SEARCH("Marketing Manager",C44))+ISNUMBER(SEARCH("Gerente de Marketing",C44))+ISNUMBER(SEARCH("Growth Manager",C44))+ISNUMBER(SEARCH("Demand Gen",C44))+ISNUMBER(SEARCH("Marketing Lead",C44))>0,'Configuración'!$B$33,IF(ISNUMBER(SEARCH("COO",C44))+ISNUMBER(SEARCH("CFO",C44))+ISNUMBER(SEARCH("CTO",C44))+ISNUMBER(SEARCH("Chief Operating",C44))+ISNUMBER(SEARCH("Chief Financial",C44))+ISNUMBER(SEARCH("Gerente General",C44))+ISNUMBER(SEARCH("General Manager",C44))>0,'Configuración'!$B$34,'Configuración'!$B$35))))) -> 0 | V44: =IF(B44="","",IF(K44="Sí",'Configuración'!$B$5,0)+IF(L44="Semanal",'Configuración'!$B$6,IF(L44="Mensual",'Configuración'!$B$7,0))+IF(M44="Sí",'Configuración'!$B$8,0)+IF(N44="Sí",'Configuración'!$B$9,0)+IF(O44="Sí",'Configuración'!$B$10,0)+IF(P44="Sí",'Configuración'!$B$11,0)+IF(Q44="Sí",'Configuración'!$B$12,0)+S44+T44+U44) -> 8 | W44: =IF(B44="","",IF(V44>='Configuración'!$B$19,"A",IF(V44>='Configuración'!$B$20,"B",IF(V44>='Configuración'!$B$21,"C","Descarte")))) -> Descarte
A45: =IF(B45="","",ROW()-2) -> 43 | B45: Orlando | C45: Chief Executive Officer | D45: HCX SAS | E45: orlando.garcia@hcx.com.co | F45: http://www.linkedin.com/in/orlando-garcia-monroy-b303a272 | G45: http://www.linkedin.com/company/hcx-sas | H45: https://hcx.com.co | I45: information technology & services | J45: 3 | K45: No | L45: Mensual | M45: No | N45: No | O45: No | Q45: No | R45: Posible Tier 1 | S45: =IF(B45="","",IF(ISNUMBER(J45),IF(J45<=10,'Configuración'!$B$23,IF(J45<=50,'Configuración'!$B$24,IF(J45<=200,'Configuración'!$B$25,0))),0)) -> 12 | T45: =IF(B45="","",IF(ISNUMBER(SEARCH("information technology",I45))+ISNUMBER(SEARCH("software",I45))+ISNUMBER(SEARCH("internet",I45))+ISNUMBER(SEARCH("computer",I45))+ISNUMBER(SEARCH("saas",I45))+ISNUMBER(SEARCH("fintech",I45))+ISNUMBER(SEARCH("information services",I45))+ISNUMBER(SEARCH("telecommunications",I45))>0,'Configuración'!$B$27,'Configuración'!$B$28)) -> 12 | U45: =IF(B45="","",IF(ISNUMBER(SEARCH("CEO",C45))+ISNUMBER(SEARCH("Founder",C45))+ISNUMBER(SEARCH("Owner",C45))+ISNUMBER(SEARCH("Dueño",C45))+ISNUMBER(SEARCH("Director General",C45))+ISNUMBER(SEARCH("Presidente",C45))+ISNUMBER(SEARCH("President",C45))>0,'Configuración'!$B$31,IF(ISNUMBER(SEARCH("CMO",C45))+ISNUMBER(SEARCH("Chief Marketing",C45))+ISNUMBER(SEARCH("VP Marketing",C45))+ISNUMBER(SEARCH("Director de Marketing",C45))+ISNUMBER(SEARCH("Director Marketing",C45))+ISNUMBER(SEARCH("Head of Marketing",C45))+ISNUMBER(SEARCH("Head Marketing",C45))>0,'Configuración'!$B$32,IF(ISNUMBER(SEARCH("Marketing Manager",C45))+ISNUMBER(SEARCH("Gerente de Marketing",C45))+ISNUMBER(SEARCH("Growth Manager",C45))+ISNUMBER(SEARCH("Demand Gen",C45))+ISNUMBER(SEARCH("Marketing Lead",C45))>0,'Configuración'!$B$33,IF(ISNUMBER(SEARCH("COO",C45))+ISNUMBER(SEARCH("CFO",C45))+ISNUMBER(SEARCH("CTO",C45))+ISNUMBER(SEARCH("Chief Operating",C45))+ISNUMBER(SEARCH("Chief Financial",C45))+ISNUMBER(SEARCH("Gerente General",C45))+ISNUMBER(SEARCH("General Manager",C45))>0,'Configuración'!$B$34,'Configuración'!$B$35))))) -> 0 | V45: =IF(B45="","",IF(K45="Sí",'Configuración'!$B$5,0)+IF(L45="Semanal",'Configuración'!$B$6,IF(L45="Mensual",'Configuración'!$B$7,0))+IF(M45="Sí",'Configuración'!$B$8,0)+IF(N45="Sí",'Configuración'!$B$9,0)+IF(O45="Sí",'Configuración'!$B$10,0)+IF(P45="Sí",'Configuración'!$B$11,0)+IF(Q45="Sí",'Configuración'!$B$12,0)+S45+T45+U45) -> 28 | W45: =IF(B45="","",IF(V45>='Configuración'!$B$19,"A",IF(V45>='Configuración'!$B$20,"B",IF(V45>='Configuración'!$B$21,"C","Descarte")))) -> C
A46: =IF(B46="","",ROW()-2) -> 44 | B46: Emerson | C46: Co-founder & Executive Director | D46: Cluster Orinoco TIC | E46: emerson.duran@orinocotic.org | F46: http://www.linkedin.com/in/emerson-duran-rodriguez-49953b28 | G46: http://www.linkedin.com/company/orinocotic | H46: https://orinocotic.org | I46: information technology & services | J46: 5 | K46: No | L46: Inactivo | M46: No | N46: No | O46: No | Q46: No | R46: Posible Tier 1 | S46: =IF(B46="","",IF(ISNUMBER(J46),IF(J46<=10,'Configuración'!$B$23,IF(J46<=50,'Configuración'!$B$24,IF(J46<=200,'Configuración'!$B$25,0))),0)) -> 12 | T46: =IF(B46="","",IF(ISNUMBER(SEARCH("information technology",I46))+ISNUMBER(SEARCH("software",I46))+ISNUMBER(SEARCH("internet",I46))+ISNUMBER(SEARCH("computer",I46))+ISNUMBER(SEARCH("saas",I46))+ISNUMBER(SEARCH("fintech",I46))+ISNUMBER(SEARCH("information services",I46))+ISNUMBER(SEARCH("telecommunications",I46))>0,'Configuración'!$B$27,'Configuración'!$B$28)) -> 12 | U46: =IF(B46="","",IF(ISNUMBER(SEARCH("CEO",C46))+ISNUMBER(SEARCH("Founder",C46))+ISNUMBER(SEARCH("Owner",C46))+ISNUMBER(SEARCH("Dueño",C46))+ISNUMBER(SEARCH("Director General",C46))+ISNUMBER(SEARCH("Presidente",C46))+ISNUMBER(SEARCH("President",C46))>0,'Configuración'!$B$31,IF(ISNUMBER(SEARCH("CMO",C46))+ISNUMBER(SEARCH("Chief Marketing",C46))+ISNUMBER(SEARCH("VP Marketing",C46))+ISNUMBER(SEARCH("Director de Marketing",C46))+ISNUMBER(SEARCH("Director Marketing",C46))+ISNUMBER(SEARCH("Head of Marketing",C46))+ISNUMBER(SEARCH("Head Marketing",C46))>0,'Configuración'!$B$32,IF(ISNUMBER(SEARCH("Marketing Manager",C46))+ISNUMBER(SEARCH("Gerente de Marketing",C46))+ISNUMBER(SEARCH("Growth Manager",C46))+ISNUMBER(SEARCH("Demand Gen",C46))+ISNUMBER(SEARCH("Marketing Lead",C46))>0,'Configuración'!$B$33,IF(ISNUMBER(SEARCH("COO",C46))+ISNUMBER(SEARCH("CFO",C46))+ISNUMBER(SEARCH("CTO",C46))+ISNUMBER(SEARCH("Chief Operating",C46))+ISNUMBER(SEARCH("Chief Financial",C46))+ISNUMBER(SEARCH("Gerente General",C46))+ISNUMBER(SEARCH("General Manager",C46))>0,'Configuración'!$B$34,'Configuración'!$B$35))))) -> 12 | V46: =IF(B46="","",IF(K46="Sí",'Configuración'!$B$5,0)+IF(L46="Semanal",'Configuración'!$B$6,IF(L46="Mensual",'Configuración'!$B$7,0))+IF(M46="Sí",'Configuración'!$B$8,0)+IF(N46="Sí",'Configuración'!$B$9,0)+IF(O46="Sí",'Configuración'!$B$10,0)+IF(P46="Sí",'Configuración'!$B$11,0)+IF(Q46="Sí",'Configuración'!$B$12,0)+S46+T46+U46) -> 36 | W46: =IF(B46="","",IF(V46>='Configuración'!$B$19,"A",IF(V46>='Configuración'!$B$20,"B",IF(V46>='Configuración'!$B$21,"C","Descarte")))) -> C
A47: =IF(B47="","",ROW()-2) -> 45 | B47: Daniel | C47: Chief Executive Officer | D47: Raddar Studios | E47: daniel.forerop@raddarstudios.com | F47: http://www.linkedin.com/in/daniforero | G47: http://www.linkedin.com/company/raddarstudios | H47: https://raddarstudios.com | I47: information technology & services | J47: 17 | K47: No | L47: Inactivo | M47: No | N47: No | O47: No | Q47: No | R47: Posible Tier 1 | S47: =IF(B47="","",IF(ISNUMBER(J47),IF(J47<=10,'Configuración'!$B$23,IF(J47<=50,'Configuración'!$B$24,IF(J47<=200,'Configuración'!$B$25,0))),0)) -> 4 | T47: =IF(B47="","",IF(ISNUMBER(SEARCH("information technology",I47))+ISNUMBER(SEARCH("software",I47))+ISNUMBER(SEARCH("internet",I47))+ISNUMBER(SEARCH("computer",I47))+ISNUMBER(SEARCH("saas",I47))+ISNUMBER(SEARCH("fintech",I47))+ISNUMBER(SEARCH("information services",I47))+ISNUMBER(SEARCH("telecommunications",I47))>0,'Configuración'!$B$27,'Configuración'!$B$28)) -> 12 | U47: =IF(B47="","",IF(ISNUMBER(SEARCH("CEO",C47))+ISNUMBER(SEARCH("Founder",C47))+ISNUMBER(SEARCH("Owner",C47))+ISNUMBER(SEARCH("Dueño",C47))+ISNUMBER(SEARCH("Director General",C47))+ISNUMBER(SEARCH("Presidente",C47))+ISNUMBER(SEARCH("President",C47))>0,'Configuración'!$B$31,IF(ISNUMBER(SEARCH("CMO",C47))+ISNUMBER(SEARCH("Chief Marketing",C47))+ISNUMBER(SEARCH("VP Marketing",C47))+ISNUMBER(SEARCH("Director de Marketing",C47))+ISNUMBER(SEARCH("Director Marketing",C47))+ISNUMBER(SEARCH("Head of Marketing",C47))+ISNUMBER(SEARCH("Head Marketing",C47))>0,'Configuración'!$B$32,IF(ISNUMBER(SEARCH("Marketing Manager",C47))+ISNUMBER(SEARCH("Gerente de Marketing",C47))+ISNUMBER(SEARCH("Growth Manager",C47))+ISNUMBER(SEARCH("Demand Gen",C47))+ISNUMBER(SEARCH("Marketing Lead",C47))>0,'Configuración'!$B$33,IF(ISNUMBER(SEARCH("COO",C47))+ISNUMBER(SEARCH("CFO",C47))+ISNUMBER(SEARCH("CTO",C47))+ISNUMBER(SEARCH("Chief Operating",C47))+ISNUMBER(SEARCH("Chief Financial",C47))+ISNUMBER(SEARCH("Gerente General",C47))+ISNUMBER(SEARCH("General Manager",C47))>0,'Configuración'!$B$34,'Configuración'!$B$35))))) -> 0 | V47: =IF(B47="","",IF(K47="Sí",'Configuración'!$B$5,0)+IF(L47="Semanal",'Configuración'!$B$6,IF(L47="Mensual",'Configuración'!$B$7,0))+IF(M47="Sí",'Configuración'!$B$8,0)+IF(N47="Sí",'Configuración'!$B$9,0)+IF(O47="Sí",'Configuración'!$B$10,0)+IF(P47="Sí",'Configuración'!$B$11,0)+IF(Q47="Sí",'Configuración'!$B$12,0)+S47+T47+U47) -> 16 | W47: =IF(B47="","",IF(V47>='Configuración'!$B$19,"A",IF(V47>='Configuración'!$B$20,"B",IF(V47>='Configuración'!$B$21,"C","Descarte")))) -> Descarte
A48: =IF(B48="","",ROW()-2) -> 46 | B48: Carlos | C48: CTO & Co- Founder | D48: KastorFinance | E48: carlos@kastorfinance.com | F48: http://www.linkedin.com/in/carlos-andr%c3%a9s-serna-carvajal-38b1b7111 | G48: http://www.linkedin.com/company/kastor-fi | H48: https://kastorfinance.com | I48: investment management | J48: 7 | K48: No | L48: Inactivo | M48: No | N48: No | O48: No | Q48: No | S48: =IF(B48="","",IF(ISNUMBER(J48),IF(J48<=10,'Configuración'!$B$23,IF(J48<=50,'Configuración'!$B$24,IF(J48<=200,'Configuración'!$B$25,0))),0)) -> 12 | T48: =IF(B48="","",IF(ISNUMBER(SEARCH("information technology",I48))+ISNUMBER(SEARCH("software",I48))+ISNUMBER(SEARCH("internet",I48))+ISNUMBER(SEARCH("computer",I48))+ISNUMBER(SEARCH("saas",I48))+ISNUMBER(SEARCH("fintech",I48))+ISNUMBER(SEARCH("information services",I48))+ISNUMBER(SEARCH("telecommunications",I48))>0,'Configuración'!$B$27,'Configuración'!$B$28)) -> 4 | U48: =IF(B48="","",IF(ISNUMBER(SEARCH("CEO",C48))+ISNUMBER(SEARCH("Founder",C48))+ISNUMBER(SEARCH("Owner",C48))+ISNUMBER(SEARCH("Dueño",C48))+ISNUMBER(SEARCH("Director General",C48))+ISNUMBER(SEARCH("Presidente",C48))+ISNUMBER(SEARCH("President",C48))>0,'Configuración'!$B$31,IF(ISNUMBER(SEARCH("CMO",C48))+ISNUMBER(SEARCH("Chief Marketing",C48))+ISNUMBER(SEARCH("VP Marketing",C48))+ISNUMBER(SEARCH("Director de Marketing",C48))+ISNUMBER(SEARCH("Director Marketing",C48))+ISNUMBER(SEARCH("Head of Marketing",C48))+ISNUMBER(SEARCH("Head Marketing",C48))>0,'Configuración'!$B$32,IF(ISNUMBER(SEARCH("Marketing Manager",C48))+ISNUMBER(SEARCH("Gerente de Marketing",C48))+ISNUMBER(SEARCH("Growth Manager",C48))+ISNUMBER(SEARCH("Demand Gen",C48))+ISNUMBER(SEARCH("Marketing Lead",C48))>0,'Configuración'!$B$33,IF(ISNUMBER(SEARCH("COO",C48))+ISNUMBER(SEARCH("CFO",C48))+ISNUMBER(SEARCH("CTO",C48))+ISNUMBER(SEARCH("Chief Operating",C48))+ISNUMBER(SEARCH("Chief Financial",C48))+ISNUMBER(SEARCH("Gerente General",C48))+ISNUMBER(SEARCH("General Manager",C48))>0,'Configuración'!$B$34,'Configuración'!$B$35))))) -> 12 | V48: =IF(B48="","",IF(K48="Sí",'Configuración'!$B$5,0)+IF(L48="Semanal",'Configuración'!$B$6,IF(L48="Mensual",'Configuración'!$B$7,0))+IF(M48="Sí",'Configuración'!$B$8,0)+IF(N48="Sí",'Configuración'!$B$9,0)+IF(O48="Sí",'Configuración'!$B$10,0)+IF(P48="Sí",'Configuración'!$B$11,0)+IF(Q48="Sí",'Configuración'!$B$12,0)+S48+T48+U48) -> 28 | W48: =IF(B48="","",IF(V48>='Configuración'!$B$19,"A",IF(V48>='Configuración'!$B$20,"B",IF(V48>='Configuración'!$B$21,"C","Descarte")))) -> C
A49: =IF(B49="","",ROW()-2) -> 47 | B49: Hanna | C49: CEO | D49: Teamco Consulting SAS | E49: hanna.vivas@teamco.com.co | F49: http://www.linkedin.com/in/hannacarolinavivaslopez | G49: http://www.linkedin.com/company/teamcoconsulting | H49: https://teamco.com.co | I49: telecommunications | J49: 31 | K49: No | L49: Mensual | M49: Sí | N49: No | O49: No | Q49: No | S49: =IF(B49="","",IF(ISNUMBER(J49),IF(J49<=10,'Configuración'!$B$23,IF(J49<=50,'Configuración'!$B$24,IF(J49<=200,'Configuración'!$B$25,0))),0)) -> 4 | T49: =IF(B49="","",IF(ISNUMBER(SEARCH("information technology",I49))+ISNUMBER(SEARCH("software",I49))+ISNUMBER(SEARCH("internet",I49))+ISNUMBER(SEARCH("computer",I49))+ISNUMBER(SEARCH("saas",I49))+ISNUMBER(SEARCH("fintech",I49))+ISNUMBER(SEARCH("information services",I49))+ISNUMBER(SEARCH("telecommunications",I49))>0,'Configuración'!$B$27,'Configuración'!$B$28)) -> 12 | U49: =IF(B49="","",IF(ISNUMBER(SEARCH("CEO",C49))+ISNUMBER(SEARCH("Founder",C49))+ISNUMBER(SEARCH("Owner",C49))+ISNUMBER(SEARCH("Dueño",C49))+ISNUMBER(SEARCH("Director General",C49))+ISNUMBER(SEARCH("Presidente",C49))+ISNUMBER(SEARCH("President",C49))>0,'Configuración'!$B$31,IF(ISNUMBER(SEARCH("CMO",C49))+ISNUMBER(SEARCH("Chief Marketing",C49))+ISNUMBER(SEARCH("VP Marketing",C49))+ISNUMBER(SEARCH("Director de Marketing",C49))+ISNUMBER(SEARCH("Director Marketing",C49))+ISNUMBER(SEARCH("Head of Marketing",C49))+ISNUMBER(SEARCH("Head Marketing",C49))>0,'Configuración'!$B$32,IF(ISNUMBER(SEARCH("Marketing Manager",C49))+ISNUMBER(SEARCH("Gerente de Marketing",C49))+ISNUMBER(SEARCH("Growth Manager",C49))+ISNUMBER(SEARCH("Demand Gen",C49))+ISNUMBER(SEARCH("Marketing Lead",C49))>0,'Configuración'!$B$33,IF(ISNUMBER(SEARCH("COO",C49))+ISNUMBER(SEARCH("CFO",C49))+ISNUMBER(SEARCH("CTO",C49))+ISNUMBER(SEARCH("Chief Operating",C49))+ISNUMBER(SEARCH("Chief Financial",C49))+ISNUMBER(SEARCH("Gerente General",C49))+ISNUMBER(SEARCH("General Manager",C49))>0,'Configuración'!$B$34,'Configuración'!$B$35))))) -> 12 | V49: =IF(B49="","",IF(K49="Sí",'Configuración'!$B$5,0)+IF(L49="Semanal",'Configuración'!$B$6,IF(L49="Mensual",'Configuración'!$B$7,0))+IF(M49="Sí",'Configuración'!$B$8,0)+IF(N49="Sí",'Configuración'!$B$9,0)+IF(O49="Sí",'Configuración'!$B$10,0)+IF(P49="Sí",'Configuración'!$B$11,0)+IF(Q49="Sí",'Configuración'!$B$12,0)+S49+T49+U49) -> 44 | W49: =IF(B49="","",IF(V49>='Configuración'!$B$19,"A",IF(V49>='Configuración'!$B$20,"B",IF(V49>='Configuración'!$B$21,"C","Descarte")))) -> B
A50: =IF(B50="","",ROW()-2) -> 48 | B50: Diego | C50: CO-CEO | D50: ORKID | E50: diego@orkid.tech | F50: http://www.linkedin.com/in/diego-pinzon-paz-097a6223 | G50: http://www.linkedin.com/company/orkid-tech | H50: https://orkid.tech | I50: aviation & aerospace | J50: 16 | K50: Sí | L50: Semanal | M50: No | N50: No | O50: No | Q50: No | S50: =IF(B50="","",IF(ISNUMBER(J50),IF(J50<=10,'Configuración'!$B$23,IF(J50<=50,'Configuración'!$B$24,IF(J50<=200,'Configuración'!$B$25,0))),0)) -> 4 | T50: =IF(B50="","",IF(ISNUMBER(SEARCH("information technology",I50))+ISNUMBER(SEARCH("software",I50))+ISNUMBER(SEARCH("internet",I50))+ISNUMBER(SEARCH("computer",I50))+ISNUMBER(SEARCH("saas",I50))+ISNUMBER(SEARCH("fintech",I50))+ISNUMBER(SEARCH("information services",I50))+ISNUMBER(SEARCH("telecommunications",I50))>0,'Configuración'!$B$27,'Configuración'!$B$28)) -> 4 | U50: =IF(B50="","",IF(ISNUMBER(SEARCH("CEO",C50))+ISNUMBER(SEARCH("Founder",C50))+ISNUMBER(SEARCH("Owner",C50))+ISNUMBER(SEARCH("Dueño",C50))+ISNUMBER(SEARCH("Director General",C50))+ISNUMBER(SEARCH("Presidente",C50))+ISNUMBER(SEARCH("President",C50))>0,'Configuración'!$B$31,IF(ISNUMBER(SEARCH("CMO",C50))+ISNUMBER(SEARCH("Chief Marketing",C50))+ISNUMBER(SEARCH("VP Marketing",C50))+ISNUMBER(SEARCH("Director de Marketing",C50))+ISNUMBER(SEARCH("Director Marketing",C50))+ISNUMBER(SEARCH("Head of Marketing",C50))+ISNUMBER(SEARCH("Head Marketing",C50))>0,'Configuración'!$B$32,IF(ISNUMBER(SEARCH("Marketing Manager",C50))+ISNUMBER(SEARCH("Gerente de Marketing",C50))+ISNUMBER(SEARCH("Growth Manager",C50))+ISNUMBER(SEARCH("Demand Gen",C50))+ISNUMBER(SEARCH("Marketing Lead",C50))>0,'Configuración'!$B$33,IF(ISNUMBER(SEARCH("COO",C50))+ISNUMBER(SEARCH("CFO",C50))+ISNUMBER(SEARCH("CTO",C50))+ISNUMBER(SEARCH("Chief Operating",C50))+ISNUMBER(SEARCH("Chief Financial",C50))+ISNUMBER(SEARCH("Gerente General",C50))+ISNUMBER(SEARCH("General Manager",C50))>0,'Configuración'!$B$34,'Configuración'!$B$35))))) -> 12 | V50: =IF(B50="","",IF(K50="Sí",'Configuración'!$B$5,0)+IF(L50="Semanal",'Configuración'!$B$6,IF(L50="Mensual",'Configuración'!$B$7,0))+IF(M50="Sí",'Configuración'!$B$8,0)+IF(N50="Sí",'Configuración'!$B$9,0)+IF(O50="Sí",'Configuración'!$B$10,0)+IF(P50="Sí",'Configuración'!$B$11,0)+IF(Q50="Sí",'Configuración'!$B$12,0)+S50+T50+U50) -> 44 | W50: =IF(B50="","",IF(V50>='Configuración'!$B$19,"A",IF(V50>='Configuración'!$B$20,"B",IF(V50>='Configuración'!$B$21,"C","Descarte")))) -> B
A51: =IF(B51="","",ROW()-2) -> 49 | B51: Ines | C51: Co-Founder and CFO - Ecoguard Energy PTE Ltd | D51: Ecoguard Energy | E51: i.delgado@ecoguardenergy.com | F51: http://www.linkedin.com/in/ines-cecilia-delgado-fl%c3%b3rez-6aa5318 | G51: http://www.linkedin.com/company/ecoguardenergy | H51: https://ecoguardenergy.com | I51: mining & metals | J51: 9 | K51: No | L51: Inactivo | M51: No | N51: No | O51: No | Q51: No | S51: =IF(B51="","",IF(ISNUMBER(J51),IF(J51<=10,'Configuración'!$B$23,IF(J51<=50,'Configuración'!$B$24,IF(J51<=200,'Configuración'!$B$25,0))),0)) -> 12 | T51: =IF(B51="","",IF(ISNUMBER(SEARCH("information technology",I51))+ISNUMBER(SEARCH("software",I51))+ISNUMBER(SEARCH("internet",I51))+ISNUMBER(SEARCH("computer",I51))+ISNUMBER(SEARCH("saas",I51))+ISNUMBER(SEARCH("fintech",I51))+ISNUMBER(SEARCH("information services",I51))+ISNUMBER(SEARCH("telecommunications",I51))>0,'Configuración'!$B$27,'Configuración'!$B$28)) -> 4 | U51: =IF(B51="","",IF(ISNUMBER(SEARCH("CEO",C51))+ISNUMBER(SEARCH("Founder",C51))+ISNUMBER(SEARCH("Owner",C51))+ISNUMBER(SEARCH("Dueño",C51))+ISNUMBER(SEARCH("Director General",C51))+ISNUMBER(SEARCH("Presidente",C51))+ISNUMBER(SEARCH("President",C51))>0,'Configuración'!$B$31,IF(ISNUMBER(SEARCH("CMO",C51))+ISNUMBER(SEARCH("Chief Marketing",C51))+ISNUMBER(SEARCH("VP Marketing",C51))+ISNUMBER(SEARCH("Director de Marketing",C51))+ISNUMBER(SEARCH("Director Marketing",C51))+ISNUMBER(SEARCH("Head of Marketing",C51))+ISNUMBER(SEARCH("Head Marketing",C51))>0,'Configuración'!$B$32,IF(ISNUMBER(SEARCH("Marketing Manager",C51))+ISNUMBER(SEARCH("Gerente de Marketing",C51))+ISNUMBER(SEARCH("Growth Manager",C51))+ISNUMBER(SEARCH("Demand Gen",C51))+ISNUMBER(SEARCH("Marketing Lead",C51))>0,'Configuración'!$B$33,IF(ISNUMBER(SEARCH("COO",C51))+ISNUMBER(SEARCH("CFO",C51))+ISNUMBER(SEARCH("CTO",C51))+ISNUMBER(SEARCH("Chief Operating",C51))+ISNUMBER(SEARCH("Chief Financial",C51))+ISNUMBER(SEARCH("Gerente General",C51))+ISNUMBER(SEARCH("General Manager",C51))>0,'Configuración'!$B$34,'Configuración'!$B$35))))) -> 12 | V51: =IF(B51="","",IF(K51="Sí",'Configuración'!$B$5,0)+IF(L51="Semanal",'Configuración'!$B$6,IF(L51="Mensual",'Configuración'!$B$7,0))+IF(M51="Sí",'Configuración'!$B$8,0)+IF(N51="Sí",'Configuración'!$B$9,0)+IF(O51="Sí",'Configuración'!$B$10,0)+IF(P51="Sí",'Configuración'!$B$11,0)+IF(Q51="Sí",'Configuración'!$B$12,0)+S51+T51+U51) -> 28 | W51: =IF(B51="","",IF(V51>='Configuración'!$B$19,"A",IF(V51>='Configuración'!$B$20,"B",IF(V51>='Configuración'!$B$21,"C","Descarte")))) -> C
A52: =IF(B52="","",ROW()-2) -> 50 | B52: Juan | C52: CEO and Co-founder | D52: datapeers | E52: juan.urrea@datapeers.co | F52: http://www.linkedin.com/in/juandurrea | G52: http://www.linkedin.com/company/datapeers-ai | H52: https://datapeers.co | I52: information services | J52: 7 | K52: No | L52: Inactivo | M52: No | N52: No | O52: No | Q52: No | S52: =IF(B52="","",IF(ISNUMBER(J52),IF(J52<=10,'Configuración'!$B$23,IF(J52<=50,'Configuración'!$B$24,IF(J52<=200,'Configuración'!$B$25,0))),0)) -> 12 | T52: =IF(B52="","",IF(ISNUMBER(SEARCH("information technology",I52))+ISNUMBER(SEARCH("software",I52))+ISNUMBER(SEARCH("internet",I52))+ISNUMBER(SEARCH("computer",I52))+ISNUMBER(SEARCH("saas",I52))+ISNUMBER(SEARCH("fintech",I52))+ISNUMBER(SEARCH("information services",I52))+ISNUMBER(SEARCH("telecommunications",I52))>0,'Configuración'!$B$27,'Configuración'!$B$28)) -> 12 | U52: =IF(B52="","",IF(ISNUMBER(SEARCH("CEO",C52))+ISNUMBER(SEARCH("Founder",C52))+ISNUMBER(SEARCH("Owner",C52))+ISNUMBER(SEARCH("Dueño",C52))+ISNUMBER(SEARCH("Director General",C52))+ISNUMBER(SEARCH("Presidente",C52))+ISNUMBER(SEARCH("President",C52))>0,'Configuración'!$B$31,IF(ISNUMBER(SEARCH("CMO",C52))+ISNUMBER(SEARCH("Chief Marketing",C52))+ISNUMBER(SEARCH("VP Marketing",C52))+ISNUMBER(SEARCH("Director de Marketing",C52))+ISNUMBER(SEARCH("Director Marketing",C52))+ISNUMBER(SEARCH("Head of Marketing",C52))+ISNUMBER(SEARCH("Head Marketing",C52))>0,'Configuración'!$B$32,IF(ISNUMBER(SEARCH("Marketing Manager",C52))+ISNUMBER(SEARCH("Gerente de Marketing",C52))+ISNUMBER(SEARCH("Growth Manager",C52))+ISNUMBER(SEARCH("Demand Gen",C52))+ISNUMBER(SEARCH("Marketing Lead",C52))>0,'Configuración'!$B$33,IF(ISNUMBER(SEARCH("COO",C52))+ISNUMBER(SEARCH("CFO",C52))+ISNUMBER(SEARCH("CTO",C52))+ISNUMBER(SEARCH("Chief Operating",C52))+ISNUMBER(SEARCH("Chief Financial",C52))+ISNUMBER(SEARCH("Gerente General",C52))+ISNUMBER(SEARCH("General Manager",C52))>0,'Configuración'!$B$34,'Configuración'!$B$35))))) -> 12 | V52: =IF(B52="","",IF(K52="Sí",'Configuración'!$B$5,0)+IF(L52="Semanal",'Configuración'!$B$6,IF(L52="Mensual",'Configuración'!$B$7,0))+IF(M52="Sí",'Configuración'!$B$8,0)+IF(N52="Sí",'Configuración'!$B$9,0)+IF(O52="Sí",'Configuración'!$B$10,0)+IF(P52="Sí",'Configuración'!$B$11,0)+IF(Q52="Sí",'Configuración'!$B$12,0)+S52+T52+U52) -> 36 | W52: =IF(B52="","",IF(V52>='Configuración'!$B$19,"A",IF(V52>='Configuración'!$B$20,"B",IF(V52>='Configuración'!$B$21,"C","Descarte")))) -> C
A53: =IF(B53="","",ROW()-2) -> 51 | B53: Herman | C53: Founder & COO, Founder & CEO | D53: HTI Hub | E53: herman.rojas@htihub.com | F53: http://www.linkedin.com/in/herman-rojas-amaya-6154a920 | G53: http://www.linkedin.com/company/hti-hub | H53: https://htihub.com | I53: think tanks | J53: 3 | K53: No | L53: Inactivo | M53: No | N53: No | O53: No | Q53: No | S53: =IF(B53="","",IF(ISNUMBER(J53),IF(J53<=10,'Configuración'!$B$23,IF(J53<=50,'Configuración'!$B$24,IF(J53<=200,'Configuración'!$B$25,0))),0)) -> 12 | T53: =IF(B53="","",IF(ISNUMBER(SEARCH("information technology",I53))+ISNUMBER(SEARCH("software",I53))+ISNUMBER(SEARCH("internet",I53))+ISNUMBER(SEARCH("computer",I53))+ISNUMBER(SEARCH("saas",I53))+ISNUMBER(SEARCH("fintech",I53))+ISNUMBER(SEARCH("information services",I53))+ISNUMBER(SEARCH("telecommunications",I53))>0,'Configuración'!$B$27,'Configuración'!$B$28)) -> 4 | U53: =IF(B53="","",IF(ISNUMBER(SEARCH("CEO",C53))+ISNUMBER(SEARCH("Founder",C53))+ISNUMBER(SEARCH("Owner",C53))+ISNUMBER(SEARCH("Dueño",C53))+ISNUMBER(SEARCH("Director General",C53))+ISNUMBER(SEARCH("Presidente",C53))+ISNUMBER(SEARCH("President",C53))>0,'Configuración'!$B$31,IF(ISNUMBER(SEARCH("CMO",C53))+ISNUMBER(SEARCH("Chief Marketing",C53))+ISNUMBER(SEARCH("VP Marketing",C53))+ISNUMBER(SEARCH("Director de Marketing",C53))+ISNUMBER(SEARCH("Director Marketing",C53))+ISNUMBER(SEARCH("Head of Marketing",C53))+ISNUMBER(SEARCH("Head Marketing",C53))>0,'Configuración'!$B$32,IF(ISNUMBER(SEARCH("Marketing Manager",C53))+ISNUMBER(SEARCH("Gerente de Marketing",C53))+ISNUMBER(SEARCH("Growth Manager",C53))+ISNUMBER(SEARCH("Demand Gen",C53))+ISNUMBER(SEARCH("Marketing Lead",C53))>0,'Configuración'!$B$33,IF(ISNUMBER(SEARCH("COO",C53))+ISNUMBER(SEARCH("CFO",C53))+ISNUMBER(SEARCH("CTO",C53))+ISNUMBER(SEARCH("Chief Operating",C53))+ISNUMBER(SEARCH("Chief Financial",C53))+ISNUMBER(SEARCH("Gerente General",C53))+ISNUMBER(SEARCH("General Manager",C53))>0,'Configuración'!$B$34,'Configuración'!$B$35))))) -> 12 | V53: =IF(B53="","",IF(K53="Sí",'Configuración'!$B$5,0)+IF(L53="Semanal",'Configuración'!$B$6,IF(L53="Mensual",'Configuración'!$B$7,0))+IF(M53="Sí",'Configuración'!$B$8,0)+IF(N53="Sí",'Configuración'!$B$9,0)+IF(O53="Sí",'Configuración'!$B$10,0)+IF(P53="Sí",'Configuración'!$B$11,0)+IF(Q53="Sí",'Configuración'!$B$12,0)+S53+T53+U53) -> 28 | W53: =IF(B53="","",IF(V53>='Configuración'!$B$19,"A",IF(V53>='Configuración'!$B$20,"B",IF(V53>='Configuración'!$B$21,"C","Descarte")))) -> C
A54: =IF(B54="","",ROW()-2) -> 52 | B54: Katie | C54: Founder | D54: Prometryx Accounting | E54: katie@prometryx.com | F54: http://www.linkedin.com/in/katie-ellinger | G54: http://www.linkedin.com/company/prometryx | H54: https://prometryx.com | I54: accounting | J54: 6 | K54: No | L54: Inactivo | M54: No | N54: No | O54: No | Q54: No | S54: =IF(B54="","",IF(ISNUMBER(J54),IF(J54<=10,'Configuración'!$B$23,IF(J54<=50,'Configuración'!$B$24,IF(J54<=200,'Configuración'!$B$25,0))),0)) -> 12 | T54: =IF(B54="","",IF(ISNUMBER(SEARCH("information technology",I54))+ISNUMBER(SEARCH("software",I54))+ISNUMBER(SEARCH("internet",I54))+ISNUMBER(SEARCH("computer",I54))+ISNUMBER(SEARCH("saas",I54))+ISNUMBER(SEARCH("fintech",I54))+ISNUMBER(SEARCH("information services",I54))+ISNUMBER(SEARCH("telecommunications",I54))>0,'Configuración'!$B$27,'Configuración'!$B$28)) -> 4 | U54: =IF(B54="","",IF(ISNUMBER(SEARCH("CEO",C54))+ISNUMBER(SEARCH("Founder",C54))+ISNUMBER(SEARCH("Owner",C54))+ISNUMBER(SEARCH("Dueño",C54))+ISNUMBER(SEARCH("Director General",C54))+ISNUMBER(SEARCH("Presidente",C54))+ISNUMBER(SEARCH("President",C54))>0,'Configuración'!$B$31,IF(ISNUMBER(SEARCH("CMO",C54))+ISNUMBER(SEARCH("Chief Marketing",C54))+ISNUMBER(SEARCH("VP Marketing",C54))+ISNUMBER(SEARCH("Director de Marketing",C54))+ISNUMBER(SEARCH("Director Marketing",C54))+ISNUMBER(SEARCH("Head of Marketing",C54))+ISNUMBER(SEARCH("Head Marketing",C54))>0,'Configuración'!$B$32,IF(ISNUMBER(SEARCH("Marketing Manager",C54))+ISNUMBER(SEARCH("Gerente de Marketing",C54))+ISNUMBER(SEARCH("Growth Manager",C54))+ISNUMBER(SEARCH("Demand Gen",C54))+ISNUMBER(SEARCH("Marketing Lead",C54))>0,'Configuración'!$B$33,IF(ISNUMBER(SEARCH("COO",C54))+ISNUMBER(SEARCH("CFO",C54))+ISNUMBER(SEARCH("CTO",C54))+ISNUMBER(SEARCH("Chief Operating",C54))+ISNUMBER(SEARCH("Chief Financial",C54))+ISNUMBER(SEARCH("Gerente General",C54))+ISNUMBER(SEARCH("General Manager",C54))>0,'Configuración'!$B$34,'Configuración'!$B$35))))) -> 12 | V54: =IF(B54="","",IF(K54="Sí",'Configuración'!$B$5,0)+IF(L54="Semanal",'Configuración'!$B$6,IF(L54="Mensual",'Configuración'!$B$7,0))+IF(M54="Sí",'Configuración'!$B$8,0)+IF(N54="Sí",'Configuración'!$B$9,0)+IF(O54="Sí",'Configuración'!$B$10,0)+IF(P54="Sí",'Configuración'!$B$11,0)+IF(Q54="Sí",'Configuración'!$B$12,0)+S54+T54+U54) -> 28 | W54: =IF(B54="","",IF(V54>='Configuración'!$B$19,"A",IF(V54>='Configuración'!$B$20,"B",IF(V54>='Configuración'!$B$21,"C","Descarte")))) -> C
A55: =IF(B55="","",ROW()-2) -> 53 | B55: Ricardo | C55: Head of Sales | D55: duppla | E55: rarenas@duppla.co | F55: http://www.linkedin.com/in/ricardo-arenas-hurtado-49160b148 | G55: http://www.linkedin.com/company/duppla-com-co | H55: https://duppla.co | I55: financial services | J55: 36 | K55: No | L55: Inactivo | M55: Sí | N55: Sí | O55: Sí | Q55: No | S55: =IF(B55="","",IF(ISNUMBER(J55),IF(J55<=10,'Configuración'!$B$23,IF(J55<=50,'Configuración'!$B$24,IF(J55<=200,'Configuración'!$B$25,0))),0)) -> 4 | T55: =IF(B55="","",IF(ISNUMBER(SEARCH("information technology",I55))+ISNUMBER(SEARCH("software",I55))+ISNUMBER(SEARCH("internet",I55))+ISNUMBER(SEARCH("computer",I55))+ISNUMBER(SEARCH("saas",I55))+ISNUMBER(SEARCH("fintech",I55))+ISNUMBER(SEARCH("information services",I55))+ISNUMBER(SEARCH("telecommunications",I55))>0,'Configuración'!$B$27,'Configuración'!$B$28)) -> 4 | U55: =IF(B55="","",IF(ISNUMBER(SEARCH("CEO",C55))+ISNUMBER(SEARCH("Founder",C55))+ISNUMBER(SEARCH("Owner",C55))+ISNUMBER(SEARCH("Dueño",C55))+ISNUMBER(SEARCH("Director General",C55))+ISNUMBER(SEARCH("Presidente",C55))+ISNUMBER(SEARCH("President",C55))>0,'Configuración'!$B$31,IF(ISNUMBER(SEARCH("CMO",C55))+ISNUMBER(SEARCH("Chief Marketing",C55))+ISNUMBER(SEARCH("VP Marketing",C55))+ISNUMBER(SEARCH("Director de Marketing",C55))+ISNUMBER(SEARCH("Director Marketing",C55))+ISNUMBER(SEARCH("Head of Marketing",C55))+ISNUMBER(SEARCH("Head Marketing",C55))>0,'Configuración'!$B$32,IF(ISNUMBER(SEARCH("Marketing Manager",C55))+ISNUMBER(SEARCH("Gerente de Marketing",C55))+ISNUMBER(SEARCH("Growth Manager",C55))+ISNUMBER(SEARCH("Demand Gen",C55))+ISNUMBER(SEARCH("Marketing Lead",C55))>0,'Configuración'!$B$33,IF(ISNUMBER(SEARCH("COO",C55))+ISNUMBER(SEARCH("CFO",C55))+ISNUMBER(SEARCH("CTO",C55))+ISNUMBER(SEARCH("Chief Operating",C55))+ISNUMBER(SEARCH("Chief Financial",C55))+ISNUMBER(SEARCH("Gerente General",C55))+ISNUMBER(SEARCH("General Manager",C55))>0,'Configuración'!$B$34,'Configuración'!$B$35))))) -> 0 | V55: =IF(B55="","",IF(K55="Sí",'Configuración'!$B$5,0)+IF(L55="Semanal",'Configuración'!$B$6,IF(L55="Mensual",'Configuración'!$B$7,0))+IF(M55="Sí",'Configuración'!$B$8,0)+IF(N55="Sí",'Configuración'!$B$9,0)+IF(O55="Sí",'Configuración'!$B$10,0)+IF(P55="Sí",'Configuración'!$B$11,0)+IF(Q55="Sí",'Configuración'!$B$12,0)+S55+T55+U55) -> 32 | W55: =IF(B55="","",IF(V55>='Configuración'!$B$19,"A",IF(V55>='Configuración'!$B$20,"B",IF(V55>='Configuración'!$B$21,"C","Descarte")))) -> C
A56: =IF(B56="","",ROW()-2) -> 54 | B56: Nicolas | C56: Operations Director & Co Founder - Project Strategist & Consultant | D56: Lil Horse | E56: nicolas@lilhorselab.com | F56: http://www.linkedin.com/in/nicolas-useche-landinez | G56: http://www.linkedin.com/company/lil-horse | H56: https://lilhorselab.com | I56: design | J56: 17 | K56: No | L56: Semanal | M56: Sí | N56: No | O56: No | Q56: No | S56: =IF(B56="","",IF(ISNUMBER(J56),IF(J56<=10,'Configuración'!$B$23,IF(J56<=50,'Configuración'!$B$24,IF(J56<=200,'Configuración'!$B$25,0))),0)) -> 4 | T56: =IF(B56="","",IF(ISNUMBER(SEARCH("information technology",I56))+ISNUMBER(SEARCH("software",I56))+ISNUMBER(SEARCH("internet",I56))+ISNUMBER(SEARCH("computer",I56))+ISNUMBER(SEARCH("saas",I56))+ISNUMBER(SEARCH("fintech",I56))+ISNUMBER(SEARCH("information services",I56))+ISNUMBER(SEARCH("telecommunications",I56))>0,'Configuración'!$B$27,'Configuración'!$B$28)) -> 4 | U56: =IF(B56="","",IF(ISNUMBER(SEARCH("CEO",C56))+ISNUMBER(SEARCH("Founder",C56))+ISNUMBER(SEARCH("Owner",C56))+ISNUMBER(SEARCH("Dueño",C56))+ISNUMBER(SEARCH("Director General",C56))+ISNUMBER(SEARCH("Presidente",C56))+ISNUMBER(SEARCH("President",C56))>0,'Configuración'!$B$31,IF(ISNUMBER(SEARCH("CMO",C56))+ISNUMBER(SEARCH("Chief Marketing",C56))+ISNUMBER(SEARCH("VP Marketing",C56))+ISNUMBER(SEARCH("Director de Marketing",C56))+ISNUMBER(SEARCH("Director Marketing",C56))+ISNUMBER(SEARCH("Head of Marketing",C56))+ISNUMBER(SEARCH("Head Marketing",C56))>0,'Configuración'!$B$32,IF(ISNUMBER(SEARCH("Marketing Manager",C56))+ISNUMBER(SEARCH("Gerente de Marketing",C56))+ISNUMBER(SEARCH("Growth Manager",C56))+ISNUMBER(SEARCH("Demand Gen",C56))+ISNUMBER(SEARCH("Marketing Lead",C56))>0,'Configuración'!$B$33,IF(ISNUMBER(SEARCH("COO",C56))+ISNUMBER(SEARCH("CFO",C56))+ISNUMBER(SEARCH("CTO",C56))+ISNUMBER(SEARCH("Chief Operating",C56))+ISNUMBER(SEARCH("Chief Financial",C56))+ISNUMBER(SEARCH("Gerente General",C56))+ISNUMBER(SEARCH("General Manager",C56))>0,'Configuración'!$B$34,'Configuración'!$B$35))))) -> 12 | V56: =IF(B56="","",IF(K56="Sí",'Configuración'!$B$5,0)+IF(L56="Semanal",'Configuración'!$B$6,IF(L56="Mensual",'Configuración'!$B$7,0))+IF(M56="Sí",'Configuración'!$B$8,0)+IF(N56="Sí",'Configuración'!$B$9,0)+IF(O56="Sí",'Configuración'!$B$10,0)+IF(P56="Sí",'Configuración'!$B$11,0)+IF(Q56="Sí",'Configuración'!$B$12,0)+S56+T56+U56) -> 44 | W56: =IF(B56="","",IF(V56>='Configuración'!$B$19,"A",IF(V56>='Configuración'!$B$20,"B",IF(V56>='Configuración'!$B$21,"C","Descarte")))) -> B
A57: =IF(B57="","",ROW()-2) -> 55 | B57: Rafael | C57: Co-Founder | Managing Partner | D57: EX-View Solar | F57: http://www.linkedin.com/in/rafael-aar%c3%b3n-v%c3%a1squez | G57: http://www.linkedin.com/company/ex-viewsolar | H57: https://ex-view.com | I57: information technology & services | J57: 3 | K57: No | L57: Inactivo | M57: Sí | N57: No | O57: No | Q57: No | R57: Posible Tier 1 | S57: =IF(B57="","",IF(ISNUMBER(J57),IF(J57<=10,'Configuración'!$B$23,IF(J57<=50,'Configuración'!$B$24,IF(J57<=200,'Configuración'!$B$25,0))),0)) -> 12 | T57: =IF(B57="","",IF(ISNUMBER(SEARCH("information technology",I57))+ISNUMBER(SEARCH("software",I57))+ISNUMBER(SEARCH("internet",I57))+ISNUMBER(SEARCH("computer",I57))+ISNUMBER(SEARCH("saas",I57))+ISNUMBER(SEARCH("fintech",I57))+ISNUMBER(SEARCH("information services",I57))+ISNUMBER(SEARCH("telecommunications",I57))>0,'Configuración'!$B$27,'Configuración'!$B$28)) -> 12 | U57: =IF(B57="","",IF(ISNUMBER(SEARCH("CEO",C57))+ISNUMBER(SEARCH("Founder",C57))+ISNUMBER(SEARCH("Owner",C57))+ISNUMBER(SEARCH("Dueño",C57))+ISNUMBER(SEARCH("Director General",C57))+ISNUMBER(SEARCH("Presidente",C57))+ISNUMBER(SEARCH("President",C57))>0,'Configuración'!$B$31,IF(ISNUMBER(SEARCH("CMO",C57))+ISNUMBER(SEARCH("Chief Marketing",C57))+ISNUMBER(SEARCH("VP Marketing",C57))+ISNUMBER(SEARCH("Director de Marketing",C57))+ISNUMBER(SEARCH("Director Marketing",C57))+ISNUMBER(SEARCH("Head of Marketing",C57))+ISNUMBER(SEARCH("Head Marketing",C57))>0,'Configuración'!$B$32,IF(ISNUMBER(SEARCH("Marketing Manager",C57))+ISNUMBER(SEARCH("Gerente de Marketing",C57))+ISNUMBER(SEARCH("Growth Manager",C57))+ISNUMBER(SEARCH("Demand Gen",C57))+ISNUMBER(SEARCH("Marketing Lead",C57))>0,'Configuración'!$B$33,IF(ISNUMBER(SEARCH("COO",C57))+ISNUMBER(SEARCH("CFO",C57))+ISNUMBER(SEARCH("CTO",C57))+ISNUMBER(SEARCH("Chief Operating",C57))+ISNUMBER(SEARCH("Chief Financial",C57))+ISNUMBER(SEARCH("Gerente General",C57))+ISNUMBER(SEARCH("General Manager",C57))>0,'Configuración'!$B$34,'Configuración'!$B$35))))) -> 12 | V57: =IF(B57="","",IF(K57="Sí",'Configuración'!$B$5,0)+IF(L57="Semanal",'Configuración'!$B$6,IF(L57="Mensual",'Configuración'!$B$7,0))+IF(M57="Sí",'Configuración'!$B$8,0)+IF(N57="Sí",'Configuración'!$B$9,0)+IF(O57="Sí",'Configuración'!$B$10,0)+IF(P57="Sí",'Configuración'!$B$11,0)+IF(Q57="Sí",'Configuración'!$B$12,0)+S57+T57+U57) -> 48 | W57: =IF(B57="","",IF(V57>='Configuración'!$B$19,"A",IF(V57>='Configuración'!$B$20,"B",IF(V57>='Configuración'!$B$21,"C","Descarte")))) -> B
A58: =IF(B58="","",ROW()-2) -> 56 | B58: Ricardo | C58: Chief CEO | D58: ISSAC SAS | E58: ricardo.puentes@issac.co | F58: http://www.linkedin.com/in/ricardo-puentes-231212263 | G58: http://www.linkedin.com/company/issac-sas | H58: https://issac.co | I58: information technology & services | J58: 9 | K58: No | L58: Mensual | M58: Sí | N58: No | O58: No | Q58: No | R58: Posible Tier 1 | S58: =IF(B58="","",IF(ISNUMBER(J58),IF(J58<=10,'Configuración'!$B$23,IF(J58<=50,'Configuración'!$B$24,IF(J58<=200,'Configuración'!$B$25,0))),0)) -> 12 | T58: =IF(B58="","",IF(ISNUMBER(SEARCH("information technology",I58))+ISNUMBER(SEARCH("software",I58))+ISNUMBER(SEARCH("internet",I58))+ISNUMBER(SEARCH("computer",I58))+ISNUMBER(SEARCH("saas",I58))+ISNUMBER(SEARCH("fintech",I58))+ISNUMBER(SEARCH("information services",I58))+ISNUMBER(SEARCH("telecommunications",I58))>0,'Configuración'!$B$27,'Configuración'!$B$28)) -> 12 | U58: =IF(B58="","",IF(ISNUMBER(SEARCH("CEO",C58))+ISNUMBER(SEARCH("Founder",C58))+ISNUMBER(SEARCH("Owner",C58))+ISNUMBER(SEARCH("Dueño",C58))+ISNUMBER(SEARCH("Director General",C58))+ISNUMBER(SEARCH("Presidente",C58))+ISNUMBER(SEARCH("President",C58))>0,'Configuración'!$B$31,IF(ISNUMBER(SEARCH("CMO",C58))+ISNUMBER(SEARCH("Chief Marketing",C58))+ISNUMBER(SEARCH("VP Marketing",C58))+ISNUMBER(SEARCH("Director de Marketing",C58))+ISNUMBER(SEARCH("Director Marketing",C58))+ISNUMBER(SEARCH("Head of Marketing",C58))+ISNUMBER(SEARCH("Head Marketing",C58))>0,'Configuración'!$B$32,IF(ISNUMBER(SEARCH("Marketing Manager",C58))+ISNUMBER(SEARCH("Gerente de Marketing",C58))+ISNUMBER(SEARCH("Growth Manager",C58))+ISNUMBER(SEARCH("Demand Gen",C58))+ISNUMBER(SEARCH("Marketing Lead",C58))>0,'Configuración'!$B$33,IF(ISNUMBER(SEARCH("COO",C58))+ISNUMBER(SEARCH("CFO",C58))+ISNUMBER(SEARCH("CTO",C58))+ISNUMBER(SEARCH("Chief Operating",C58))+ISNUMBER(SEARCH("Chief Financial",C58))+ISNUMBER(SEARCH("Gerente General",C58))+ISNUMBER(SEARCH("General Manager",C58))>0,'Configuración'!$B$34,'Configuración'!$B$35))))) -> 12 | V58: =IF(B58="","",IF(K58="Sí",'Configuración'!$B$5,0)+IF(L58="Semanal",'Configuración'!$B$6,IF(L58="Mensual",'Configuración'!$B$7,0))+IF(M58="Sí",'Configuración'!$B$8,0)+IF(N58="Sí",'Configuración'!$B$9,0)+IF(O58="Sí",'Configuración'!$B$10,0)+IF(P58="Sí",'Configuración'!$B$11,0)+IF(Q58="Sí",'Configuración'!$B$12,0)+S58+T58+U58) -> 52 | W58: =IF(B58="","",IF(V58>='Configuración'!$B$19,"A",IF(V58>='Configuración'!$B$20,"B",IF(V58>='Configuración'!$B$21,"C","Descarte")))) -> B
A59: =IF(B59="","",ROW()-2) -> 57 | B59: Marcela | C59: Marketing Director | D59: Primero | E59: msalinas@primero.com.co | F59: http://www.linkedin.com/in/marcela-salinas-r-bb100125 | G59: http://www.linkedin.com/company/somos-primero | H59: https://primero.com.co | I59: individual & family services | J59: 33 | K59: No | L59: Semanal | M59: No | N59: No | O59: No | Q59: No | S59: =IF(B59="","",IF(ISNUMBER(J59),IF(J59<=10,'Configuración'!$B$23,IF(J59<=50,'Configuración'!$B$24,IF(J59<=200,'Configuración'!$B$25,0))),0)) -> 4 | T59: =IF(B59="","",IF(ISNUMBER(SEARCH("information technology",I59))+ISNUMBER(SEARCH("software",I59))+ISNUMBER(SEARCH("internet",I59))+ISNUMBER(SEARCH("computer",I59))+ISNUMBER(SEARCH("saas",I59))+ISNUMBER(SEARCH("fintech",I59))+ISNUMBER(SEARCH("information services",I59))+ISNUMBER(SEARCH("telecommunications",I59))>0,'Configuración'!$B$27,'Configuración'!$B$28)) -> 4 | U59: =IF(B59="","",IF(ISNUMBER(SEARCH("CEO",C59))+ISNUMBER(SEARCH("Founder",C59))+ISNUMBER(SEARCH("Owner",C59))+ISNUMBER(SEARCH("Dueño",C59))+ISNUMBER(SEARCH("Director General",C59))+ISNUMBER(SEARCH("Presidente",C59))+ISNUMBER(SEARCH("President",C59))>0,'Configuración'!$B$31,IF(ISNUMBER(SEARCH("CMO",C59))+ISNUMBER(SEARCH("Chief Marketing",C59))+ISNUMBER(SEARCH("VP Marketing",C59))+ISNUMBER(SEARCH("Director de Marketing",C59))+ISNUMBER(SEARCH("Director Marketing",C59))+ISNUMBER(SEARCH("Head of Marketing",C59))+ISNUMBER(SEARCH("Head Marketing",C59))>0,'Configuración'!$B$32,IF(ISNUMBER(SEARCH("Marketing Manager",C59))+ISNUMBER(SEARCH("Gerente de Marketing",C59))+ISNUMBER(SEARCH("Growth Manager",C59))+ISNUMBER(SEARCH("Demand Gen",C59))+ISNUMBER(SEARCH("Marketing Lead",C59))>0,'Configuración'!$B$33,IF(ISNUMBER(SEARCH("COO",C59))+ISNUMBER(SEARCH("CFO",C59))+ISNUMBER(SEARCH("CTO",C59))+ISNUMBER(SEARCH("Chief Operating",C59))+ISNUMBER(SEARCH("Chief Financial",C59))+ISNUMBER(SEARCH("Gerente General",C59))+ISNUMBER(SEARCH("General Manager",C59))>0,'Configuración'!$B$34,'Configuración'!$B$35))))) -> 4 | V59: =IF(B59="","",IF(K59="Sí",'Configuración'!$B$5,0)+IF(L59="Semanal",'Configuración'!$B$6,IF(L59="Mensual",'Configuración'!$B$7,0))+IF(M59="Sí",'Configuración'!$B$8,0)+IF(N59="Sí",'Configuración'!$B$9,0)+IF(O59="Sí",'Configuración'!$B$10,0)+IF(P59="Sí",'Configuración'!$B$11,0)+IF(Q59="Sí",'Configuración'!$B$12,0)+S59+T59+U59) -> 24 | W59: =IF(B59="","",IF(V59>='Configuración'!$B$19,"A",IF(V59>='Configuración'!$B$20,"B",IF(V59>='Configuración'!$B$21,"C","Descarte")))) -> C
A60: =IF(B60="","",ROW()-2) -> 58 | B60: Luis | C60: C.E.O | D60: ATLANTIC LATAM CORREDORES DE SEGUROS | E60: alejandro.fuentes@atlanticrebrokers.com | F60: http://www.linkedin.com/in/luis-alejandro-fuentes-vargas-46302069 | G60: http://www.linkedin.com/company/atlantic-latam-corredores-de-seguros | H60: https://atlanticrebrokers.com | I60: insurance | J60: 22 | K60: No | L60: Inactivo | M60: No | N60: No | O60: No | Q60: No | S60: =IF(B60="","",IF(ISNUMBER(J60),IF(J60<=10,'Configuración'!$B$23,IF(J60<=50,'Configuración'!$B$24,IF(J60<=200,'Configuración'!$B$25,0))),0)) -> 4 | T60: =IF(B60="","",IF(ISNUMBER(SEARCH("information technology",I60))+ISNUMBER(SEARCH("software",I60))+ISNUMBER(SEARCH("internet",I60))+ISNUMBER(SEARCH("computer",I60))+ISNUMBER(SEARCH("saas",I60))+ISNUMBER(SEARCH("fintech",I60))+ISNUMBER(SEARCH("information services",I60))+ISNUMBER(SEARCH("telecommunications",I60))>0,'Configuración'!$B$27,'Configuración'!$B$28)) -> 4 | U60: =IF(B60="","",IF(ISNUMBER(SEARCH("CEO",C60))+ISNUMBER(SEARCH("Founder",C60))+ISNUMBER(SEARCH("Owner",C60))+ISNUMBER(SEARCH("Dueño",C60))+ISNUMBER(SEARCH("Director General",C60))+ISNUMBER(SEARCH("Presidente",C60))+ISNUMBER(SEARCH("President",C60))>0,'Configuración'!$B$31,IF(ISNUMBER(SEARCH("CMO",C60))+ISNUMBER(SEARCH("Chief Marketing",C60))+ISNUMBER(SEARCH("VP Marketing",C60))+ISNUMBER(SEARCH("Director de Marketing",C60))+ISNUMBER(SEARCH("Director Marketing",C60))+ISNUMBER(SEARCH("Head of Marketing",C60))+ISNUMBER(SEARCH("Head Marketing",C60))>0,'Configuración'!$B$32,IF(ISNUMBER(SEARCH("Marketing Manager",C60))+ISNUMBER(SEARCH("Gerente de Marketing",C60))+ISNUMBER(SEARCH("Growth Manager",C60))+ISNUMBER(SEARCH("Demand Gen",C60))+ISNUMBER(SEARCH("Marketing Lead",C60))>0,'Configuración'!$B$33,IF(ISNUMBER(SEARCH("COO",C60))+ISNUMBER(SEARCH("CFO",C60))+ISNUMBER(SEARCH("CTO",C60))+ISNUMBER(SEARCH("Chief Operating",C60))+ISNUMBER(SEARCH("Chief Financial",C60))+ISNUMBER(SEARCH("Gerente General",C60))+ISNUMBER(SEARCH("General Manager",C60))>0,'Configuración'!$B$34,'Configuración'!$B$35))))) -> 0 | V60: =IF(B60="","",IF(K60="Sí",'Configuración'!$B$5,0)+IF(L60="Semanal",'Configuración'!$B$6,IF(L60="Mensual",'Configuración'!$B$7,0))+IF(M60="Sí",'Configuración'!$B$8,0)+IF(N60="Sí",'Configuración'!$B$9,0)+IF(O60="Sí",'Configuración'!$B$10,0)+IF(P60="Sí",'Configuración'!$B$11,0)+IF(Q60="Sí",'Configuración'!$B$12,0)+S60+T60+U60) -> 8 | W60: =IF(B60="","",IF(V60>='Configuración'!$B$19,"A",IF(V60>='Configuración'!$B$20,"B",IF(V60>='Configuración'!$B$21,"C","Descarte")))) -> Descarte
A61: =IF(B61="","",ROW()-2) -> 59 | B61: Aurora | C61: Marketing, Corporate Communications & Research Director | D61: Newmark Colombia | E61: aurora.turriago@nmrk.com | F61: http://www.linkedin.com/in/aurora-turriago-72b41772 | G61: http://www.linkedin.com/company/newmarkco | H61: https://newmark.com.co | I61: real estate | J61: 17 | K61: Sí | L61: Semanal | M61: Sí | N61: No | O61: No | Q61: No | S61: =IF(B61="","",IF(ISNUMBER(J61),IF(J61<=10,'Configuración'!$B$23,IF(J61<=50,'Configuración'!$B$24,IF(J61<=200,'Configuración'!$B$25,0))),0)) -> 4 | T61: =IF(B61="","",IF(ISNUMBER(SEARCH("information technology",I61))+ISNUMBER(SEARCH("software",I61))+ISNUMBER(SEARCH("internet",I61))+ISNUMBER(SEARCH("computer",I61))+ISNUMBER(SEARCH("saas",I61))+ISNUMBER(SEARCH("fintech",I61))+ISNUMBER(SEARCH("information services",I61))+ISNUMBER(SEARCH("telecommunications",I61))>0,'Configuración'!$B$27,'Configuración'!$B$28)) -> 4 | U61: =IF(B61="","",IF(ISNUMBER(SEARCH("CEO",C61))+ISNUMBER(SEARCH("Founder",C61))+ISNUMBER(SEARCH("Owner",C61))+ISNUMBER(SEARCH("Dueño",C61))+ISNUMBER(SEARCH("Director General",C61))+ISNUMBER(SEARCH("Presidente",C61))+ISNUMBER(SEARCH("President",C61))>0,'Configuración'!$B$31,IF(ISNUMBER(SEARCH("CMO",C61))+ISNUMBER(SEARCH("Chief Marketing",C61))+ISNUMBER(SEARCH("VP Marketing",C61))+ISNUMBER(SEARCH("Director de Marketing",C61))+ISNUMBER(SEARCH("Director Marketing",C61))+ISNUMBER(SEARCH("Head of Marketing",C61))+ISNUMBER(SEARCH("Head Marketing",C61))>0,'Configuración'!$B$32,IF(ISNUMBER(SEARCH("Marketing Manager",C61))+ISNUMBER(SEARCH("Gerente de Marketing",C61))+ISNUMBER(SEARCH("Growth Manager",C61))+ISNUMBER(SEARCH("Demand Gen",C61))+ISNUMBER(SEARCH("Marketing Lead",C61))>0,'Configuración'!$B$33,IF(ISNUMBER(SEARCH("COO",C61))+ISNUMBER(SEARCH("CFO",C61))+ISNUMBER(SEARCH("CTO",C61))+ISNUMBER(SEARCH("Chief Operating",C61))+ISNUMBER(SEARCH("Chief Financial",C61))+ISNUMBER(SEARCH("Gerente General",C61))+ISNUMBER(SEARCH("General Manager",C61))>0,'Configuración'!$B$34,'Configuración'!$B$35))))) -> 4 | V61: =IF(B61="","",IF(K61="Sí",'Configuración'!$B$5,0)+IF(L61="Semanal",'Configuración'!$B$6,IF(L61="Mensual",'Configuración'!$B$7,0))+IF(M61="Sí",'Configuración'!$B$8,0)+IF(N61="Sí",'Configuración'!$B$9,0)+IF(O61="Sí",'Configuración'!$B$10,0)+IF(P61="Sí",'Configuración'!$B$11,0)+IF(Q61="Sí",'Configuración'!$B$12,0)+S61+T61+U61) -> 48 | W61: =IF(B61="","",IF(V61>='Configuración'!$B$19,"A",IF(V61>='Configuración'!$B$20,"B",IF(V61>='Configuración'!$B$21,"C","Descarte")))) -> B
A62: =IF(B62="","",ROW()-2) -> 60 | B62: Andres | C62: Head of Growth | D62: Isitec | E62: atorres@isi.com.co | F62: http://www.linkedin.com/in/andrestorres455 | G62: http://www.linkedin.com/company/isitecgroup | H62: https://isitec.co | I62: information technology & services | J62: 49 | K62: No | L62: Inactivo | M62: No | N62: No | O62: No | Q62: No | S62: =IF(B62="","",IF(ISNUMBER(J62),IF(J62<=10,'Configuración'!$B$23,IF(J62<=50,'Configuración'!$B$24,IF(J62<=200,'Configuración'!$B$25,0))),0)) -> 4 | T62: =IF(B62="","",IF(ISNUMBER(SEARCH("information technology",I62))+ISNUMBER(SEARCH("software",I62))+ISNUMBER(SEARCH("internet",I62))+ISNUMBER(SEARCH("computer",I62))+ISNUMBER(SEARCH("saas",I62))+ISNUMBER(SEARCH("fintech",I62))+ISNUMBER(SEARCH("information services",I62))+ISNUMBER(SEARCH("telecommunications",I62))>0,'Configuración'!$B$27,'Configuración'!$B$28)) -> 12 | U62: =IF(B62="","",IF(ISNUMBER(SEARCH("CEO",C62))+ISNUMBER(SEARCH("Founder",C62))+ISNUMBER(SEARCH("Owner",C62))+ISNUMBER(SEARCH("Dueño",C62))+ISNUMBER(SEARCH("Director General",C62))+ISNUMBER(SEARCH("Presidente",C62))+ISNUMBER(SEARCH("President",C62))>0,'Configuración'!$B$31,IF(ISNUMBER(SEARCH("CMO",C62))+ISNUMBER(SEARCH("Chief Marketing",C62))+ISNUMBER(SEARCH("VP Marketing",C62))+ISNUMBER(SEARCH("Director de Marketing",C62))+ISNUMBER(SEARCH("Director Marketing",C62))+ISNUMBER(SEARCH("Head of Marketing",C62))+ISNUMBER(SEARCH("Head Marketing",C62))>0,'Configuración'!$B$32,IF(ISNUMBER(SEARCH("Marketing Manager",C62))+ISNUMBER(SEARCH("Gerente de Marketing",C62))+ISNUMBER(SEARCH("Growth Manager",C62))+ISNUMBER(SEARCH("Demand Gen",C62))+ISNUMBER(SEARCH("Marketing Lead",C62))>0,'Configuración'!$B$33,IF(ISNUMBER(SEARCH("COO",C62))+ISNUMBER(SEARCH("CFO",C62))+ISNUMBER(SEARCH("CTO",C62))+ISNUMBER(SEARCH("Chief Operating",C62))+ISNUMBER(SEARCH("Chief Financial",C62))+ISNUMBER(SEARCH("Gerente General",C62))+ISNUMBER(SEARCH("General Manager",C62))>0,'Configuración'!$B$34,'Configuración'!$B$35))))) -> 0 | V62: =IF(B62="","",IF(K62="Sí",'Configuración'!$B$5,0)+IF(L62="Semanal",'Configuración'!$B$6,IF(L62="Mensual",'Configuración'!$B$7,0))+IF(M62="Sí",'Configuración'!$B$8,0)+IF(N62="Sí",'Configuración'!$B$9,0)+IF(O62="Sí",'Configuración'!$B$10,0)+IF(P62="Sí",'Configuración'!$B$11,0)+IF(Q62="Sí",'Configuración'!$B$12,0)+S62+T62+U62) -> 16 | W62: =IF(B62="","",IF(V62>='Configuración'!$B$19,"A",IF(V62>='Configuración'!$B$20,"B",IF(V62>='Configuración'!$B$21,"C","Descarte")))) -> Descarte
A63: =IF(B63="","",ROW()-2) -> 61 | B63: Mrudula | C63: Chief Operating Officer | D63: Innovex International SAS | E63: mrudula@innovexinternational.com | F63: http://www.linkedin.com/in/mrudula-wattamwar-798bb211 | G63: http://www.linkedin.com/company/innovex-international-sas | H63: https://innovexinternational.com | I63: pharmaceuticals | J63: 17 | K63: No | L63: Semanal | M63: No | N63: No | O63: No | Q63: No | S63: =IF(B63="","",IF(ISNUMBER(J63),IF(J63<=10,'Configuración'!$B$23,IF(J63<=50,'Configuración'!$B$24,IF(J63<=200,'Configuración'!$B$25,0))),0)) -> 4 | T63: =IF(B63="","",IF(ISNUMBER(SEARCH("information technology",I63))+ISNUMBER(SEARCH("software",I63))+ISNUMBER(SEARCH("internet",I63))+ISNUMBER(SEARCH("computer",I63))+ISNUMBER(SEARCH("saas",I63))+ISNUMBER(SEARCH("fintech",I63))+ISNUMBER(SEARCH("information services",I63))+ISNUMBER(SEARCH("telecommunications",I63))>0,'Configuración'!$B$27,'Configuración'!$B$28)) -> 4 | U63: =IF(B63="","",IF(ISNUMBER(SEARCH("CEO",C63))+ISNUMBER(SEARCH("Founder",C63))+ISNUMBER(SEARCH("Owner",C63))+ISNUMBER(SEARCH("Dueño",C63))+ISNUMBER(SEARCH("Director General",C63))+ISNUMBER(SEARCH("Presidente",C63))+ISNUMBER(SEARCH("President",C63))>0,'Configuración'!$B$31,IF(ISNUMBER(SEARCH("CMO",C63))+ISNUMBER(SEARCH("Chief Marketing",C63))+ISNUMBER(SEARCH("VP Marketing",C63))+ISNUMBER(SEARCH("Director de Marketing",C63))+ISNUMBER(SEARCH("Director Marketing",C63))+ISNUMBER(SEARCH("Head of Marketing",C63))+ISNUMBER(SEARCH("Head Marketing",C63))>0,'Configuración'!$B$32,IF(ISNUMBER(SEARCH("Marketing Manager",C63))+ISNUMBER(SEARCH("Gerente de Marketing",C63))+ISNUMBER(SEARCH("Growth Manager",C63))+ISNUMBER(SEARCH("Demand Gen",C63))+ISNUMBER(SEARCH("Marketing Lead",C63))>0,'Configuración'!$B$33,IF(ISNUMBER(SEARCH("COO",C63))+ISNUMBER(SEARCH("CFO",C63))+ISNUMBER(SEARCH("CTO",C63))+ISNUMBER(SEARCH("Chief Operating",C63))+ISNUMBER(SEARCH("Chief Financial",C63))+ISNUMBER(SEARCH("Gerente General",C63))+ISNUMBER(SEARCH("General Manager",C63))>0,'Configuración'!$B$34,'Configuración'!$B$35))))) -> 4 | V63: =IF(B63="","",IF(K63="Sí",'Configuración'!$B$5,0)+IF(L63="Semanal",'Configuración'!$B$6,IF(L63="Mensual",'Configuración'!$B$7,0))+IF(M63="Sí",'Configuración'!$B$8,0)+IF(N63="Sí",'Configuración'!$B$9,0)+IF(O63="Sí",'Configuración'!$B$10,0)+IF(P63="Sí",'Configuración'!$B$11,0)+IF(Q63="Sí",'Configuración'!$B$12,0)+S63+T63+U63) -> 24 | W63: =IF(B63="","",IF(V63>='Configuración'!$B$19,"A",IF(V63>='Configuración'!$B$20,"B",IF(V63>='Configuración'!$B$21,"C","Descarte")))) -> C
A64: =IF(B64="","",ROW()-2) -> 62 | B64: Maria | C64: Co Founder - Desarrollo Creativo | D64: FAUNO Beauty | E64: marialopez@fauno.com.co | F64: http://www.linkedin.com/in/maria-isabel-l%c3%b3pez-puerta-63750776 | G64: http://www.linkedin.com/company/beauty-brands-sas | H64: https://fauno.com.co | I64: health, wellness & fitness | J64: 6 | K64: No | L64: Inactivo | M64: Sí | N64: No | O64: No | Q64: No | S64: =IF(B64="","",IF(ISNUMBER(J64),IF(J64<=10,'Configuración'!$B$23,IF(J64<=50,'Configuración'!$B$24,IF(J64<=200,'Configuración'!$B$25,0))),0)) -> 12 | T64: =IF(B64="","",IF(ISNUMBER(SEARCH("information technology",I64))+ISNUMBER(SEARCH("software",I64))+ISNUMBER(SEARCH("internet",I64))+ISNUMBER(SEARCH("computer",I64))+ISNUMBER(SEARCH("saas",I64))+ISNUMBER(SEARCH("fintech",I64))+ISNUMBER(SEARCH("information services",I64))+ISNUMBER(SEARCH("telecommunications",I64))>0,'Configuración'!$B$27,'Configuración'!$B$28)) -> 4 | U64: =IF(B64="","",IF(ISNUMBER(SEARCH("CEO",C64))+ISNUMBER(SEARCH("Founder",C64))+ISNUMBER(SEARCH("Owner",C64))+ISNUMBER(SEARCH("Dueño",C64))+ISNUMBER(SEARCH("Director General",C64))+ISNUMBER(SEARCH("Presidente",C64))+ISNUMBER(SEARCH("President",C64))>0,'Configuración'!$B$31,IF(ISNUMBER(SEARCH("CMO",C64))+ISNUMBER(SEARCH("Chief Marketing",C64))+ISNUMBER(SEARCH("VP Marketing",C64))+ISNUMBER(SEARCH("Director de Marketing",C64))+ISNUMBER(SEARCH("Director Marketing",C64))+ISNUMBER(SEARCH("Head of Marketing",C64))+ISNUMBER(SEARCH("Head Marketing",C64))>0,'Configuración'!$B$32,IF(ISNUMBER(SEARCH("Marketing Manager",C64))+ISNUMBER(SEARCH("Gerente de Marketing",C64))+ISNUMBER(SEARCH("Growth Manager",C64))+ISNUMBER(SEARCH("Demand Gen",C64))+ISNUMBER(SEARCH("Marketing Lead",C64))>0,'Configuración'!$B$33,IF(ISNUMBER(SEARCH("COO",C64))+ISNUMBER(SEARCH("CFO",C64))+ISNUMBER(SEARCH("CTO",C64))+ISNUMBER(SEARCH("Chief Operating",C64))+ISNUMBER(SEARCH("Chief Financial",C64))+ISNUMBER(SEARCH("Gerente General",C64))+ISNUMBER(SEARCH("General Manager",C64))>0,'Configuración'!$B$34,'Configuración'!$B$35))))) -> 12 | V64: =IF(B64="","",IF(K64="Sí",'Configuración'!$B$5,0)+IF(L64="Semanal",'Configuración'!$B$6,IF(L64="Mensual",'Configuración'!$B$7,0))+IF(M64="Sí",'Configuración'!$B$8,0)+IF(N64="Sí",'Configuración'!$B$9,0)+IF(O64="Sí",'Configuración'!$B$10,0)+IF(P64="Sí",'Configuración'!$B$11,0)+IF(Q64="Sí",'Configuración'!$B$12,0)+S64+T64+U64) -> 40 | W64: =IF(B64="","",IF(V64>='Configuración'!$B$19,"A",IF(V64>='Configuración'!$B$20,"B",IF(V64>='Configuración'!$B$21,"C","Descarte")))) -> B
A65: =IF(B65="","",ROW()-2) -> 63 | B65: Juan Pablo | C65: Chief Executive Officer | D65: Greenwood Energy | E65: juan.crane@greenwood.energy | F65: http://www.linkedin.com/in/juan-pablo-crane-665191 | G65: http://www.linkedin.com/company/greenwoodenergy | H65: https://greenwood.energy | I65: environmental services | J65: 43 | K65: No | L65: Semanal | M65: No | N65: No | O65: No | Q65: No | S65: =IF(B65="","",IF(ISNUMBER(J65),IF(J65<=10,'Configuración'!$B$23,IF(J65<=50,'Configuración'!$B$24,IF(J65<=200,'Configuración'!$B$25,0))),0)) -> 4 | T65: =IF(B65="","",IF(ISNUMBER(SEARCH("information technology",I65))+ISNUMBER(SEARCH("software",I65))+ISNUMBER(SEARCH("internet",I65))+ISNUMBER(SEARCH("computer",I65))+ISNUMBER(SEARCH("saas",I65))+ISNUMBER(SEARCH("fintech",I65))+ISNUMBER(SEARCH("information services",I65))+ISNUMBER(SEARCH("telecommunications",I65))>0,'Configuración'!$B$27,'Configuración'!$B$28)) -> 4 | U65: =IF(B65="","",IF(ISNUMBER(SEARCH("CEO",C65))+ISNUMBER(SEARCH("Founder",C65))+ISNUMBER(SEARCH("Owner",C65))+ISNUMBER(SEARCH("Dueño",C65))+ISNUMBER(SEARCH("Director General",C65))+ISNUMBER(SEARCH("Presidente",C65))+ISNUMBER(SEARCH("President",C65))>0,'Configuración'!$B$31,IF(ISNUMBER(SEARCH("CMO",C65))+ISNUMBER(SEARCH("Chief Marketing",C65))+ISNUMBER(SEARCH("VP Marketing",C65))+ISNUMBER(SEARCH("Director de Marketing",C65))+ISNUMBER(SEARCH("Director Marketing",C65))+ISNUMBER(SEARCH("Head of Marketing",C65))+ISNUMBER(SEARCH("Head Marketing",C65))>0,'Configuración'!$B$32,IF(ISNUMBER(SEARCH("Marketing Manager",C65))+ISNUMBER(SEARCH("Gerente de Marketing",C65))+ISNUMBER(SEARCH("Growth Manager",C65))+ISNUMBER(SEARCH("Demand Gen",C65))+ISNUMBER(SEARCH("Marketing Lead",C65))>0,'Configuración'!$B$33,IF(ISNUMBER(SEARCH("COO",C65))+ISNUMBER(SEARCH("CFO",C65))+ISNUMBER(SEARCH("CTO",C65))+ISNUMBER(SEARCH("Chief Operating",C65))+ISNUMBER(SEARCH("Chief Financial",C65))+ISNUMBER(SEARCH("Gerente General",C65))+ISNUMBER(SEARCH("General Manager",C65))>0,'Configuración'!$B$34,'Configuración'!$B$35))))) -> 0 | V65: =IF(B65="","",IF(K65="Sí",'Configuración'!$B$5,0)+IF(L65="Semanal",'Configuración'!$B$6,IF(L65="Mensual",'Configuración'!$B$7,0))+IF(M65="Sí",'Configuración'!$B$8,0)+IF(N65="Sí",'Configuración'!$B$9,0)+IF(O65="Sí",'Configuración'!$B$10,0)+IF(P65="Sí",'Configuración'!$B$11,0)+IF(Q65="Sí",'Configuración'!$B$12,0)+S65+T65+U65) -> 20 | W65: =IF(B65="","",IF(V65>='Configuración'!$B$19,"A",IF(V65>='Configuración'!$B$20,"B",IF(V65>='Configuración'!$B$21,"C","Descarte")))) -> Descarte
A66: =IF(B66="","",ROW()-2) -> 64 | B66: Ingrid | C66: CEO | D66: Deloria Research | E66: ingrid@deloria.com.co | F66: http://www.linkedin.com/in/ingrid-l%c3%b3pez-b56926242 | G66: http://www.linkedin.com/company/deloria-research | H66: https://deloria.com.co | I66: research | J66: 3 | K66: No | L66: Inactivo | M66: No | N66: No | O66: No | Q66: No | S66: =IF(B66="","",IF(ISNUMBER(J66),IF(J66<=10,'Configuración'!$B$23,IF(J66<=50,'Configuración'!$B$24,IF(J66<=200,'Configuración'!$B$25,0))),0)) -> 12 | T66: =IF(B66="","",IF(ISNUMBER(SEARCH("information technology",I66))+ISNUMBER(SEARCH("software",I66))+ISNUMBER(SEARCH("internet",I66))+ISNUMBER(SEARCH("computer",I66))+ISNUMBER(SEARCH("saas",I66))+ISNUMBER(SEARCH("fintech",I66))+ISNUMBER(SEARCH("information services",I66))+ISNUMBER(SEARCH("telecommunications",I66))>0,'Configuración'!$B$27,'Configuración'!$B$28)) -> 4 | U66: =IF(B66="","",IF(ISNUMBER(SEARCH("CEO",C66))+ISNUMBER(SEARCH("Founder",C66))+ISNUMBER(SEARCH("Owner",C66))+ISNUMBER(SEARCH("Dueño",C66))+ISNUMBER(SEARCH("Director General",C66))+ISNUMBER(SEARCH("Presidente",C66))+ISNUMBER(SEARCH("President",C66))>0,'Configuración'!$B$31,IF(ISNUMBER(SEARCH("CMO",C66))+ISNUMBER(SEARCH("Chief Marketing",C66))+ISNUMBER(SEARCH("VP Marketing",C66))+ISNUMBER(SEARCH("Director de Marketing",C66))+ISNUMBER(SEARCH("Director Marketing",C66))+ISNUMBER(SEARCH("Head of Marketing",C66))+ISNUMBER(SEARCH("Head Marketing",C66))>0,'Configuración'!$B$32,IF(ISNUMBER(SEARCH("Marketing Manager",C66))+ISNUMBER(SEARCH("Gerente de Marketing",C66))+ISNUMBER(SEARCH("Growth Manager",C66))+ISNUMBER(SEARCH("Demand Gen",C66))+ISNUMBER(SEARCH("Marketing Lead",C66))>0,'Configuración'!$B$33,IF(ISNUMBER(SEARCH("COO",C66))+ISNUMBER(SEARCH("CFO",C66))+ISNUMBER(SEARCH("CTO",C66))+ISNUMBER(SEARCH("Chief Operating",C66))+ISNUMBER(SEARCH("Chief Financial",C66))+ISNUMBER(SEARCH("Gerente General",C66))+ISNUMBER(SEARCH("General Manager",C66))>0,'Configuración'!$B$34,'Configuración'!$B$35))))) -> 12 | V66: =IF(B66="","",IF(K66="Sí",'Configuración'!$B$5,0)+IF(L66="Semanal",'Configuración'!$B$6,IF(L66="Mensual",'Configuración'!$B$7,0))+IF(M66="Sí",'Configuración'!$B$8,0)+IF(N66="Sí",'Configuración'!$B$9,0)+IF(O66="Sí",'Configuración'!$B$10,0)+IF(P66="Sí",'Configuración'!$B$11,0)+IF(Q66="Sí",'Configuración'!$B$12,0)+S66+T66+U66) -> 28 | W66: =IF(B66="","",IF(V66>='Configuración'!$B$19,"A",IF(V66>='Configuración'!$B$20,"B",IF(V66>='Configuración'!$B$21,"C","Descarte")))) -> C
A67: =IF(B67="","",ROW()-2) -> 65 | B67: Yily | C67: CEO de FioraSoft | D67: FioraSoft-SAS | E67: yaparicio@fiorasoft.com | F67: http://www.linkedin.com/in/yily-aparicio-fiorasoft | G67: http://www.linkedin.com/company/fiorasoft | H67: https://fiorasoft.co | I67: information technology & services | J67: 7 | K67: No | L67: Semanal | M67: Sí | N67: No | O67: No | Q67: No | R67: Posible Tier 1 | S67: =IF(B67="","",IF(ISNUMBER(J67),IF(J67<=10,'Configuración'!$B$23,IF(J67<=50,'Configuración'!$B$24,IF(J67<=200,'Configuración'!$B$25,0))),0)) -> 12 | T67: =IF(B67="","",IF(ISNUMBER(SEARCH("information technology",I67))+ISNUMBER(SEARCH("software",I67))+ISNUMBER(SEARCH("internet",I67))+ISNUMBER(SEARCH("computer",I67))+ISNUMBER(SEARCH("saas",I67))+ISNUMBER(SEARCH("fintech",I67))+ISNUMBER(SEARCH("information services",I67))+ISNUMBER(SEARCH("telecommunications",I67))>0,'Configuración'!$B$27,'Configuración'!$B$28)) -> 12 | U67: =IF(B67="","",IF(ISNUMBER(SEARCH("CEO",C67))+ISNUMBER(SEARCH("Founder",C67))+ISNUMBER(SEARCH("Owner",C67))+ISNUMBER(SEARCH("Dueño",C67))+ISNUMBER(SEARCH("Director General",C67))+ISNUMBER(SEARCH("Presidente",C67))+ISNUMBER(SEARCH("President",C67))>0,'Configuración'!$B$31,IF(ISNUMBER(SEARCH("CMO",C67))+ISNUMBER(SEARCH("Chief Marketing",C67))+ISNUMBER(SEARCH("VP Marketing",C67))+ISNUMBER(SEARCH("Director de Marketing",C67))+ISNUMBER(SEARCH("Director Marketing",C67))+ISNUMBER(SEARCH("Head of Marketing",C67))+ISNUMBER(SEARCH("Head Marketing",C67))>0,'Configuración'!$B$32,IF(ISNUMBER(SEARCH("Marketing Manager",C67))+ISNUMBER(SEARCH("Gerente de Marketing",C67))+ISNUMBER(SEARCH("Growth Manager",C67))+ISNUMBER(SEARCH("Demand Gen",C67))+ISNUMBER(SEARCH("Marketing Lead",C67))>0,'Configuración'!$B$33,IF(ISNUMBER(SEARCH("COO",C67))+ISNUMBER(SEARCH("CFO",C67))+ISNUMBER(SEARCH("CTO",C67))+ISNUMBER(SEARCH("Chief Operating",C67))+ISNUMBER(SEARCH("Chief Financial",C67))+ISNUMBER(SEARCH("Gerente General",C67))+ISNUMBER(SEARCH("General Manager",C67))>0,'Configuración'!$B$34,'Configuración'!$B$35))))) -> 12 | V67: =IF(B67="","",IF(K67="Sí",'Configuración'!$B$5,0)+IF(L67="Semanal",'Configuración'!$B$6,IF(L67="Mensual",'Configuración'!$B$7,0))+IF(M67="Sí",'Configuración'!$B$8,0)+IF(N67="Sí",'Configuración'!$B$9,0)+IF(O67="Sí",'Configuración'!$B$10,0)+IF(P67="Sí",'Configuración'!$B$11,0)+IF(Q67="Sí",'Configuración'!$B$12,0)+S67+T67+U67) -> 60 | W67: =IF(B67="","",IF(V67>='Configuración'!$B$19,"A",IF(V67>='Configuración'!$B$20,"B",IF(V67>='Configuración'!$B$21,"C","Descarte")))) -> A
A68: =IF(B68="","",ROW()-2) -> 66 | B68: David | C68: Co-Founder & Managing Partner | D68: Tripact Advisory | E68: david@tripactadvisory.com | F68: http://www.linkedin.com/in/david-dewez- | G68: http://www.linkedin.com/company/tripactadvisory | H68: https://tripactadvisory.com | I68: capital markets | J68: 3 | K68: No | L68: Semanal | M68: Sí | N68: No | O68: No | Q68: No | S68: =IF(B68="","",IF(ISNUMBER(J68),IF(J68<=10,'Configuración'!$B$23,IF(J68<=50,'Configuración'!$B$24,IF(J68<=200,'Configuración'!$B$25,0))),0)) -> 12 | T68: =IF(B68="","",IF(ISNUMBER(SEARCH("information technology",I68))+ISNUMBER(SEARCH("software",I68))+ISNUMBER(SEARCH("internet",I68))+ISNUMBER(SEARCH("computer",I68))+ISNUMBER(SEARCH("saas",I68))+ISNUMBER(SEARCH("fintech",I68))+ISNUMBER(SEARCH("information services",I68))+ISNUMBER(SEARCH("telecommunications",I68))>0,'Configuración'!$B$27,'Configuración'!$B$28)) -> 4 | U68: =IF(B68="","",IF(ISNUMBER(SEARCH("CEO",C68))+ISNUMBER(SEARCH("Founder",C68))+ISNUMBER(SEARCH("Owner",C68))+ISNUMBER(SEARCH("Dueño",C68))+ISNUMBER(SEARCH("Director General",C68))+ISNUMBER(SEARCH("Presidente",C68))+ISNUMBER(SEARCH("President",C68))>0,'Configuración'!$B$31,IF(ISNUMBER(SEARCH("CMO",C68))+ISNUMBER(SEARCH("Chief Marketing",C68))+ISNUMBER(SEARCH("VP Marketing",C68))+ISNUMBER(SEARCH("Director de Marketing",C68))+ISNUMBER(SEARCH("Director Marketing",C68))+ISNUMBER(SEARCH("Head of Marketing",C68))+ISNUMBER(SEARCH("Head Marketing",C68))>0,'Configuración'!$B$32,IF(ISNUMBER(SEARCH("Marketing Manager",C68))+ISNUMBER(SEARCH("Gerente de Marketing",C68))+ISNUMBER(SEARCH("Growth Manager",C68))+ISNUMBER(SEARCH("Demand Gen",C68))+ISNUMBER(SEARCH("Marketing Lead",C68))>0,'Configuración'!$B$33,IF(ISNUMBER(SEARCH("COO",C68))+ISNUMBER(SEARCH("CFO",C68))+ISNUMBER(SEARCH("CTO",C68))+ISNUMBER(SEARCH("Chief Operating",C68))+ISNUMBER(SEARCH("Chief Financial",C68))+ISNUMBER(SEARCH("Gerente General",C68))+ISNUMBER(SEARCH("General Manager",C68))>0,'Configuración'!$B$34,'Configuración'!$B$35))))) -> 12 | V68: =IF(B68="","",IF(K68="Sí",'Configuración'!$B$5,0)+IF(L68="Semanal",'Configuración'!$B$6,IF(L68="Mensual",'Configuración'!$B$7,0))+IF(M68="Sí",'Configuración'!$B$8,0)+IF(N68="Sí",'Configuración'!$B$9,0)+IF(O68="Sí",'Configuración'!$B$10,0)+IF(P68="Sí",'Configuración'!$B$11,0)+IF(Q68="Sí",'Configuración'!$B$12,0)+S68+T68+U68) -> 52 | W68: =IF(B68="","",IF(V68>='Configuración'!$B$19,"A",IF(V68>='Configuración'!$B$20,"B",IF(V68>='Configuración'!$B$21,"C","Descarte")))) -> B
A69: =IF(B69="","",ROW()-2) -> 67 | B69: Javier | C69: CEO | Asociado | D69: Finance Group | E69: javiercardenas@financegroup.com.co | F69: http://www.linkedin.com/in/javiercardenasl | G69: http://www.linkedin.com/company/financegroupcol | H69: https://financegroup.com.co | I69: management consulting | J69: 8 | K69: No | L69: Inactivo | M69: Sí | N69: No | O69: No | Q69: No | S69: =IF(B69="","",IF(ISNUMBER(J69),IF(J69<=10,'Configuración'!$B$23,IF(J69<=50,'Configuración'!$B$24,IF(J69<=200,'Configuración'!$B$25,0))),0)) -> 12 | T69: =IF(B69="","",IF(ISNUMBER(SEARCH("information technology",I69))+ISNUMBER(SEARCH("software",I69))+ISNUMBER(SEARCH("internet",I69))+ISNUMBER(SEARCH("computer",I69))+ISNUMBER(SEARCH("saas",I69))+ISNUMBER(SEARCH("fintech",I69))+ISNUMBER(SEARCH("information services",I69))+ISNUMBER(SEARCH("telecommunications",I69))>0,'Configuración'!$B$27,'Configuración'!$B$28)) -> 4 | U69: =IF(B69="","",IF(ISNUMBER(SEARCH("CEO",C69))+ISNUMBER(SEARCH("Founder",C69))+ISNUMBER(SEARCH("Owner",C69))+ISNUMBER(SEARCH("Dueño",C69))+ISNUMBER(SEARCH("Director General",C69))+ISNUMBER(SEARCH("Presidente",C69))+ISNUMBER(SEARCH("President",C69))>0,'Configuración'!$B$31,IF(ISNUMBER(SEARCH("CMO",C69))+ISNUMBER(SEARCH("Chief Marketing",C69))+ISNUMBER(SEARCH("VP Marketing",C69))+ISNUMBER(SEARCH("Director de Marketing",C69))+ISNUMBER(SEARCH("Director Marketing",C69))+ISNUMBER(SEARCH("Head of Marketing",C69))+ISNUMBER(SEARCH("Head Marketing",C69))>0,'Configuración'!$B$32,IF(ISNUMBER(SEARCH("Marketing Manager",C69))+ISNUMBER(SEARCH("Gerente de Marketing",C69))+ISNUMBER(SEARCH("Growth Manager",C69))+ISNUMBER(SEARCH("Demand Gen",C69))+ISNUMBER(SEARCH("Marketing Lead",C69))>0,'Configuración'!$B$33,IF(ISNUMBER(SEARCH("COO",C69))+ISNUMBER(SEARCH("CFO",C69))+ISNUMBER(SEARCH("CTO",C69))+ISNUMBER(SEARCH("Chief Operating",C69))+ISNUMBER(SEARCH("Chief Financial",C69))+ISNUMBER(SEARCH("Gerente General",C69))+ISNUMBER(SEARCH("General Manager",C69))>0,'Configuración'!$B$34,'Configuración'!$B$35))))) -> 12 | V69: =IF(B69="","",IF(K69="Sí",'Configuración'!$B$5,0)+IF(L69="Semanal",'Configuración'!$B$6,IF(L69="Mensual",'Configuración'!$B$7,0))+IF(M69="Sí",'Configuración'!$B$8,0)+IF(N69="Sí",'Configuración'!$B$9,0)+IF(O69="Sí",'Configuración'!$B$10,0)+IF(P69="Sí",'Configuración'!$B$11,0)+IF(Q69="Sí",'Configuración'!$B$12,0)+S69+T69+U69) -> 40 | W69: =IF(B69="","",IF(V69>='Configuración'!$B$19,"A",IF(V69>='Configuración'!$B$20,"B",IF(V69>='Configuración'!$B$21,"C","Descarte")))) -> B
A70: =IF(B70="","",ROW()-2) -> 68 | B70: Lorenz | C70: Co-Founder & CPO | D70: Cotierra | E70: lorenz.buser@cotierra.com | F70: http://www.linkedin.com/in/lorenz-buser-22031bb9 | G70: http://www.linkedin.com/company/cotierra-ag | H70: https://cotierra.com | I70: environmental services | J70: 16 | K70: No | L70: Inactivo | M70: Sí | N70: No | O70: No | Q70: No | S70: =IF(B70="","",IF(ISNUMBER(J70),IF(J70<=10,'Configuración'!$B$23,IF(J70<=50,'Configuración'!$B$24,IF(J70<=200,'Configuración'!$B$25,0))),0)) -> 4 | T70: =IF(B70="","",IF(ISNUMBER(SEARCH("information technology",I70))+ISNUMBER(SEARCH("software",I70))+ISNUMBER(SEARCH("internet",I70))+ISNUMBER(SEARCH("computer",I70))+ISNUMBER(SEARCH("saas",I70))+ISNUMBER(SEARCH("fintech",I70))+ISNUMBER(SEARCH("information services",I70))+ISNUMBER(SEARCH("telecommunications",I70))>0,'Configuración'!$B$27,'Configuración'!$B$28)) -> 4 | U70: =IF(B70="","",IF(ISNUMBER(SEARCH("CEO",C70))+ISNUMBER(SEARCH("Founder",C70))+ISNUMBER(SEARCH("Owner",C70))+ISNUMBER(SEARCH("Dueño",C70))+ISNUMBER(SEARCH("Director General",C70))+ISNUMBER(SEARCH("Presidente",C70))+ISNUMBER(SEARCH("President",C70))>0,'Configuración'!$B$31,IF(ISNUMBER(SEARCH("CMO",C70))+ISNUMBER(SEARCH("Chief Marketing",C70))+ISNUMBER(SEARCH("VP Marketing",C70))+ISNUMBER(SEARCH("Director de Marketing",C70))+ISNUMBER(SEARCH("Director Marketing",C70))+ISNUMBER(SEARCH("Head of Marketing",C70))+ISNUMBER(SEARCH("Head Marketing",C70))>0,'Configuración'!$B$32,IF(ISNUMBER(SEARCH("Marketing Manager",C70))+ISNUMBER(SEARCH("Gerente de Marketing",C70))+ISNUMBER(SEARCH("Growth Manager",C70))+ISNUMBER(SEARCH("Demand Gen",C70))+ISNUMBER(SEARCH("Marketing Lead",C70))>0,'Configuración'!$B$33,IF(ISNUMBER(SEARCH("COO",C70))+ISNUMBER(SEARCH("CFO",C70))+ISNUMBER(SEARCH("CTO",C70))+ISNUMBER(SEARCH("Chief Operating",C70))+ISNUMBER(SEARCH("Chief Financial",C70))+ISNUMBER(SEARCH("Gerente General",C70))+ISNUMBER(SEARCH("General Manager",C70))>0,'Configuración'!$B$34,'Configuración'!$B$35))))) -> 12 | V70: =IF(B70="","",IF(K70="Sí",'Configuración'!$B$5,0)+IF(L70="Semanal",'Configuración'!$B$6,IF(L70="Mensual",'Configuración'!$B$7,0))+IF(M70="Sí",'Configuración'!$B$8,0)+IF(N70="Sí",'Configuración'!$B$9,0)+IF(O70="Sí",'Configuración'!$B$10,0)+IF(P70="Sí",'Configuración'!$B$11,0)+IF(Q70="Sí",'Configuración'!$B$12,0)+S70+T70+U70) -> 32 | W70: =IF(B70="","",IF(V70>='Configuración'!$B$19,"A",IF(V70>='Configuración'!$B$20,"B",IF(V70>='Configuración'!$B$21,"C","Descarte")))) -> C
A71: =IF(B71="","",ROW()-2) -> 69 | B71: Manuel | C71: CEO | D71: ArkNova S.A.S | E71: manuel.guzman@arknova.co | F71: http://www.linkedin.com/in/manguzm | G71: http://www.linkedin.com/company/arknovasas | H71: https://arknova.co | I71: information technology & services | J71: 7 | K71: No | L71: Inactivo | M71: No | N71: No | O71: No | Q71: No | R71: Posible Tier 1 | S71: =IF(B71="","",IF(ISNUMBER(J71),IF(J71<=10,'Configuración'!$B$23,IF(J71<=50,'Configuración'!$B$24,IF(J71<=200,'Configuración'!$B$25,0))),0)) -> 12 | T71: =IF(B71="","",IF(ISNUMBER(SEARCH("information technology",I71))+ISNUMBER(SEARCH("software",I71))+ISNUMBER(SEARCH("internet",I71))+ISNUMBER(SEARCH("computer",I71))+ISNUMBER(SEARCH("saas",I71))+ISNUMBER(SEARCH("fintech",I71))+ISNUMBER(SEARCH("information services",I71))+ISNUMBER(SEARCH("telecommunications",I71))>0,'Configuración'!$B$27,'Configuración'!$B$28)) -> 12 | U71: =IF(B71="","",IF(ISNUMBER(SEARCH("CEO",C71))+ISNUMBER(SEARCH("Founder",C71))+ISNUMBER(SEARCH("Owner",C71))+ISNUMBER(SEARCH("Dueño",C71))+ISNUMBER(SEARCH("Director General",C71))+ISNUMBER(SEARCH("Presidente",C71))+ISNUMBER(SEARCH("President",C71))>0,'Configuración'!$B$31,IF(ISNUMBER(SEARCH("CMO",C71))+ISNUMBER(SEARCH("Chief Marketing",C71))+ISNUMBER(SEARCH("VP Marketing",C71))+ISNUMBER(SEARCH("Director de Marketing",C71))+ISNUMBER(SEARCH("Director Marketing",C71))+ISNUMBER(SEARCH("Head of Marketing",C71))+ISNUMBER(SEARCH("Head Marketing",C71))>0,'Configuración'!$B$32,IF(ISNUMBER(SEARCH("Marketing Manager",C71))+ISNUMBER(SEARCH("Gerente de Marketing",C71))+ISNUMBER(SEARCH("Growth Manager",C71))+ISNUMBER(SEARCH("Demand Gen",C71))+ISNUMBER(SEARCH("Marketing Lead",C71))>0,'Configuración'!$B$33,IF(ISNUMBER(SEARCH("COO",C71))+ISNUMBER(SEARCH("CFO",C71))+ISNUMBER(SEARCH("CTO",C71))+ISNUMBER(SEARCH("Chief Operating",C71))+ISNUMBER(SEARCH("Chief Financial",C71))+ISNUMBER(SEARCH("Gerente General",C71))+ISNUMBER(SEARCH("General Manager",C71))>0,'Configuración'!$B$34,'Configuración'!$B$35))))) -> 12 | V71: =IF(B71="","",IF(K71="Sí",'Configuración'!$B$5,0)+IF(L71="Semanal",'Configuración'!$B$6,IF(L71="Mensual",'Configuración'!$B$7,0))+IF(M71="Sí",'Configuración'!$B$8,0)+IF(N71="Sí",'Configuración'!$B$9,0)+IF(O71="Sí",'Configuración'!$B$10,0)+IF(P71="Sí",'Configuración'!$B$11,0)+IF(Q71="Sí",'Configuración'!$B$12,0)+S71+T71+U71) -> 36 | W71: =IF(B71="","",IF(V71>='Configuración'!$B$19,"A",IF(V71>='Configuración'!$B$20,"B",IF(V71>='Configuración'!$B$21,"C","Descarte")))) -> C
A72: =IF(B72="","",ROW()-2) -> 70 | B72: Estefania | C72: Cofounder and CEO | D72: AURORA | E72: estefania@auroraglobal.com.co | F72: http://www.linkedin.com/in/estefania-grajales | G72: http://www.linkedin.com/company/aurora-comunidad | H72: https://auroraglobal.com.co | I72: professional training & coaching | J72: 4 | K72: No | L72: Semanal | M72: Sí | N72: No | O72: No | Q72: No | S72: =IF(B72="","",IF(ISNUMBER(J72),IF(J72<=10,'Configuración'!$B$23,IF(J72<=50,'Configuración'!$B$24,IF(J72<=200,'Configuración'!$B$25,0))),0)) -> 12 | T72: =IF(B72="","",IF(ISNUMBER(SEARCH("information technology",I72))+ISNUMBER(SEARCH("software",I72))+ISNUMBER(SEARCH("internet",I72))+ISNUMBER(SEARCH("computer",I72))+ISNUMBER(SEARCH("saas",I72))+ISNUMBER(SEARCH("fintech",I72))+ISNUMBER(SEARCH("information services",I72))+ISNUMBER(SEARCH("telecommunications",I72))>0,'Configuración'!$B$27,'Configuración'!$B$28)) -> 4 | U72: =IF(B72="","",IF(ISNUMBER(SEARCH("CEO",C72))+ISNUMBER(SEARCH("Founder",C72))+ISNUMBER(SEARCH("Owner",C72))+ISNUMBER(SEARCH("Dueño",C72))+ISNUMBER(SEARCH("Director General",C72))+ISNUMBER(SEARCH("Presidente",C72))+ISNUMBER(SEARCH("President",C72))>0,'Configuración'!$B$31,IF(ISNUMBER(SEARCH("CMO",C72))+ISNUMBER(SEARCH("Chief Marketing",C72))+ISNUMBER(SEARCH("VP Marketing",C72))+ISNUMBER(SEARCH("Director de Marketing",C72))+ISNUMBER(SEARCH("Director Marketing",C72))+ISNUMBER(SEARCH("Head of Marketing",C72))+ISNUMBER(SEARCH("Head Marketing",C72))>0,'Configuración'!$B$32,IF(ISNUMBER(SEARCH("Marketing Manager",C72))+ISNUMBER(SEARCH("Gerente de Marketing",C72))+ISNUMBER(SEARCH("Growth Manager",C72))+ISNUMBER(SEARCH("Demand Gen",C72))+ISNUMBER(SEARCH("Marketing Lead",C72))>0,'Configuración'!$B$33,IF(ISNUMBER(SEARCH("COO",C72))+ISNUMBER(SEARCH("CFO",C72))+ISNUMBER(SEARCH("CTO",C72))+ISNUMBER(SEARCH("Chief Operating",C72))+ISNUMBER(SEARCH("Chief Financial",C72))+ISNUMBER(SEARCH("Gerente General",C72))+ISNUMBER(SEARCH("General Manager",C72))>0,'Configuración'!$B$34,'Configuración'!$B$35))))) -> 12 | V72: =IF(B72="","",IF(K72="Sí",'Configuración'!$B$5,0)+IF(L72="Semanal",'Configuración'!$B$6,IF(L72="Mensual",'Configuración'!$B$7,0))+IF(M72="Sí",'Configuración'!$B$8,0)+IF(N72="Sí",'Configuración'!$B$9,0)+IF(O72="Sí",'Configuración'!$B$10,0)+IF(P72="Sí",'Configuración'!$B$11,0)+IF(Q72="Sí",'Configuración'!$B$12,0)+S72+T72+U72) -> 52 | W72: =IF(B72="","",IF(V72>='Configuración'!$B$19,"A",IF(V72>='Configuración'!$B$20,"B",IF(V72>='Configuración'!$B$21,"C","Descarte")))) -> B
A73: =IF(B73="","",ROW()-2) -> 71 | B73: Juan Pablo | C73: Founder - CEO | D73: JP Tactical Trading | E73: jvieira@ttrading.co | F73: http://www.linkedin.com/in/juan-pablo-vieira-ttrading | G73: http://www.linkedin.com/company/jptacticaltrading | H73: https://ttrading.co | I73: investment management | J73: 8 | K73: No | L73: Semanal | M73: Sí | N73: Sí | O73: No | Q73: No | S73: =IF(B73="","",IF(ISNUMBER(J73),IF(J73<=10,'Configuración'!$B$23,IF(J73<=50,'Configuración'!$B$24,IF(J73<=200,'Configuración'!$B$25,0))),0)) -> 12 | T73: =IF(B73="","",IF(ISNUMBER(SEARCH("information technology",I73))+ISNUMBER(SEARCH("software",I73))+ISNUMBER(SEARCH("internet",I73))+ISNUMBER(SEARCH("computer",I73))+ISNUMBER(SEARCH("saas",I73))+ISNUMBER(SEARCH("fintech",I73))+ISNUMBER(SEARCH("information services",I73))+ISNUMBER(SEARCH("telecommunications",I73))>0,'Configuración'!$B$27,'Configuración'!$B$28)) -> 4 | U73: =IF(B73="","",IF(ISNUMBER(SEARCH("CEO",C73))+ISNUMBER(SEARCH("Founder",C73))+ISNUMBER(SEARCH("Owner",C73))+ISNUMBER(SEARCH("Dueño",C73))+ISNUMBER(SEARCH("Director General",C73))+ISNUMBER(SEARCH("Presidente",C73))+ISNUMBER(SEARCH("President",C73))>0,'Configuración'!$B$31,IF(ISNUMBER(SEARCH("CMO",C73))+ISNUMBER(SEARCH("Chief Marketing",C73))+ISNUMBER(SEARCH("VP Marketing",C73))+ISNUMBER(SEARCH("Director de Marketing",C73))+ISNUMBER(SEARCH("Director Marketing",C73))+ISNUMBER(SEARCH("Head of Marketing",C73))+ISNUMBER(SEARCH("Head Marketing",C73))>0,'Configuración'!$B$32,IF(ISNUMBER(SEARCH("Marketing Manager",C73))+ISNUMBER(SEARCH("Gerente de Marketing",C73))+ISNUMBER(SEARCH("Growth Manager",C73))+ISNUMBER(SEARCH("Demand Gen",C73))+ISNUMBER(SEARCH("Marketing Lead",C73))>0,'Configuración'!$B$33,IF(ISNUMBER(SEARCH("COO",C73))+ISNUMBER(SEARCH("CFO",C73))+ISNUMBER(SEARCH("CTO",C73))+ISNUMBER(SEARCH("Chief Operating",C73))+ISNUMBER(SEARCH("Chief Financial",C73))+ISNUMBER(SEARCH("Gerente General",C73))+ISNUMBER(SEARCH("General Manager",C73))>0,'Configuración'!$B$34,'Configuración'!$B$35))))) -> 12 | V73: =IF(B73="","",IF(K73="Sí",'Configuración'!$B$5,0)+IF(L73="Semanal",'Configuración'!$B$6,IF(L73="Mensual",'Configuración'!$B$7,0))+IF(M73="Sí",'Configuración'!$B$8,0)+IF(N73="Sí",'Configuración'!$B$9,0)+IF(O73="Sí",'Configuración'!$B$10,0)+IF(P73="Sí",'Configuración'!$B$11,0)+IF(Q73="Sí",'Configuración'!$B$12,0)+S73+T73+U73) -> 56 | W73: =IF(B73="","",IF(V73>='Configuración'!$B$19,"A",IF(V73>='Configuración'!$B$20,"B",IF(V73>='Configuración'!$B$21,"C","Descarte")))) -> B
A74: =IF(B74="","",ROW()-2) -> 72 | B74: Juan | C74: Co-Founder & CEO | D74: Cocotero | E74: juan@cocotero.com.co | F74: http://www.linkedin.com/in/juan-carlos-martinez-sabbagh-42990464 | G74: http://www.linkedin.com/company/cocoteroapp | H74: https://cocotero.com.co | I74: information technology & services | J74: 2 | K74: No | L74: Inactivo | M74: Sí | N74: No | O74: No | Q74: No | R74: Posible Tier 1 | S74: =IF(B74="","",IF(ISNUMBER(J74),IF(J74<=10,'Configuración'!$B$23,IF(J74<=50,'Configuración'!$B$24,IF(J74<=200,'Configuración'!$B$25,0))),0)) -> 12 | T74: =IF(B74="","",IF(ISNUMBER(SEARCH("information technology",I74))+ISNUMBER(SEARCH("software",I74))+ISNUMBER(SEARCH("internet",I74))+ISNUMBER(SEARCH("computer",I74))+ISNUMBER(SEARCH("saas",I74))+ISNUMBER(SEARCH("fintech",I74))+ISNUMBER(SEARCH("information services",I74))+ISNUMBER(SEARCH("telecommunications",I74))>0,'Configuración'!$B$27,'Configuración'!$B$28)) -> 12 | U74: =IF(B74="","",IF(ISNUMBER(SEARCH("CEO",C74))+ISNUMBER(SEARCH("Founder",C74))+ISNUMBER(SEARCH("Owner",C74))+ISNUMBER(SEARCH("Dueño",C74))+ISNUMBER(SEARCH("Director General",C74))+ISNUMBER(SEARCH("Presidente",C74))+ISNUMBER(SEARCH("President",C74))>0,'Configuración'!$B$31,IF(ISNUMBER(SEARCH("CMO",C74))+ISNUMBER(SEARCH("Chief Marketing",C74))+ISNUMBER(SEARCH("VP Marketing",C74))+ISNUMBER(SEARCH("Director de Marketing",C74))+ISNUMBER(SEARCH("Director Marketing",C74))+ISNUMBER(SEARCH("Head of Marketing",C74))+ISNUMBER(SEARCH("Head Marketing",C74))>0,'Configuración'!$B$32,IF(ISNUMBER(SEARCH("Marketing Manager",C74))+ISNUMBER(SEARCH("Gerente de Marketing",C74))+ISNUMBER(SEARCH("Growth Manager",C74))+ISNUMBER(SEARCH("Demand Gen",C74))+ISNUMBER(SEARCH("Marketing Lead",C74))>0,'Configuración'!$B$33,IF(ISNUMBER(SEARCH("COO",C74))+ISNUMBER(SEARCH("CFO",C74))+ISNUMBER(SEARCH("CTO",C74))+ISNUMBER(SEARCH("Chief Operating",C74))+ISNUMBER(SEARCH("Chief Financial",C74))+ISNUMBER(SEARCH("Gerente General",C74))+ISNUMBER(SEARCH("General Manager",C74))>0,'Configuración'!$B$34,'Configuración'!$B$35))))) -> 12 | V74: =IF(B74="","",IF(K74="Sí",'Configuración'!$B$5,0)+IF(L74="Semanal",'Configuración'!$B$6,IF(L74="Mensual",'Configuración'!$B$7,0))+IF(M74="Sí",'Configuración'!$B$8,0)+IF(N74="Sí",'Configuración'!$B$9,0)+IF(O74="Sí",'Configuración'!$B$10,0)+IF(P74="Sí",'Configuración'!$B$11,0)+IF(Q74="Sí",'Configuración'!$B$12,0)+S74+T74+U74) -> 48 | W74: =IF(B74="","",IF(V74>='Configuración'!$B$19,"A",IF(V74>='Configuración'!$B$20,"B",IF(V74>='Configuración'!$B$21,"C","Descarte")))) -> B
A75: =IF(B75="","",ROW()-2) -> 73 | B75: Jonathan | C75: Founder & CTO | D75: Walix | E75: jonathan.waldo@walix.co | F75: http://www.linkedin.com/in/jonathan-waldo | G75: http://www.linkedin.com/company/walix | H75: https://walix.co | I75: telecommunications | J75: 7 | K75: No | L75: Inactivo | M75: No | N75: No | O75: No | Q75: No | S75: =IF(B75="","",IF(ISNUMBER(J75),IF(J75<=10,'Configuración'!$B$23,IF(J75<=50,'Configuración'!$B$24,IF(J75<=200,'Configuración'!$B$25,0))),0)) -> 12 | T75: =IF(B75="","",IF(ISNUMBER(SEARCH("information technology",I75))+ISNUMBER(SEARCH("software",I75))+ISNUMBER(SEARCH("internet",I75))+ISNUMBER(SEARCH("computer",I75))+ISNUMBER(SEARCH("saas",I75))+ISNUMBER(SEARCH("fintech",I75))+ISNUMBER(SEARCH("information services",I75))+ISNUMBER(SEARCH("telecommunications",I75))>0,'Configuración'!$B$27,'Configuración'!$B$28)) -> 12 | U75: =IF(B75="","",IF(ISNUMBER(SEARCH("CEO",C75))+ISNUMBER(SEARCH("Founder",C75))+ISNUMBER(SEARCH("Owner",C75))+ISNUMBER(SEARCH("Dueño",C75))+ISNUMBER(SEARCH("Director General",C75))+ISNUMBER(SEARCH("Presidente",C75))+ISNUMBER(SEARCH("President",C75))>0,'Configuración'!$B$31,IF(ISNUMBER(SEARCH("CMO",C75))+ISNUMBER(SEARCH("Chief Marketing",C75))+ISNUMBER(SEARCH("VP Marketing",C75))+ISNUMBER(SEARCH("Director de Marketing",C75))+ISNUMBER(SEARCH("Director Marketing",C75))+ISNUMBER(SEARCH("Head of Marketing",C75))+ISNUMBER(SEARCH("Head Marketing",C75))>0,'Configuración'!$B$32,IF(ISNUMBER(SEARCH("Marketing Manager",C75))+ISNUMBER(SEARCH("Gerente de Marketing",C75))+ISNUMBER(SEARCH("Growth Manager",C75))+ISNUMBER(SEARCH("Demand Gen",C75))+ISNUMBER(SEARCH("Marketing Lead",C75))>0,'Configuración'!$B$33,IF(ISNUMBER(SEARCH("COO",C75))+ISNUMBER(SEARCH("CFO",C75))+ISNUMBER(SEARCH("CTO",C75))+ISNUMBER(SEARCH("Chief Operating",C75))+ISNUMBER(SEARCH("Chief Financial",C75))+ISNUMBER(SEARCH("Gerente General",C75))+ISNUMBER(SEARCH("General Manager",C75))>0,'Configuración'!$B$34,'Configuración'!$B$35))))) -> 12 | V75: =IF(B75="","",IF(K75="Sí",'Configuración'!$B$5,0)+IF(L75="Semanal",'Configuración'!$B$6,IF(L75="Mensual",'Configuración'!$B$7,0))+IF(M75="Sí",'Configuración'!$B$8,0)+IF(N75="Sí",'Configuración'!$B$9,0)+IF(O75="Sí",'Configuración'!$B$10,0)+IF(P75="Sí",'Configuración'!$B$11,0)+IF(Q75="Sí",'Configuración'!$B$12,0)+S75+T75+U75) -> 36 | W75: =IF(B75="","",IF(V75>='Configuración'!$B$19,"A",IF(V75>='Configuración'!$B$20,"B",IF(V75>='Configuración'!$B$21,"C","Descarte")))) -> C
A76: =IF(B76="","",ROW()-2) -> 74 | B76: Alejandro | C76: Founder | D76: PaLaTierra | E76: alejandro.gutierrez@palatierra.com | F76: http://www.linkedin.com/in/alejandro-gutierrez-diaz | G76: http://www.linkedin.com/company/palatierra | H76: https://palatierra.com | I76: farming | J76: 4 | K76: No | L76: Inactivo | M76: Sí | N76: No | O76: No | Q76: No | S76: =IF(B76="","",IF(ISNUMBER(J76),IF(J76<=10,'Configuración'!$B$23,IF(J76<=50,'Configuración'!$B$24,IF(J76<=200,'Configuración'!$B$25,0))),0)) -> 12 | T76: =IF(B76="","",IF(ISNUMBER(SEARCH("information technology",I76))+ISNUMBER(SEARCH("software",I76))+ISNUMBER(SEARCH("internet",I76))+ISNUMBER(SEARCH("computer",I76))+ISNUMBER(SEARCH("saas",I76))+ISNUMBER(SEARCH("fintech",I76))+ISNUMBER(SEARCH("information services",I76))+ISNUMBER(SEARCH("telecommunications",I76))>0,'Configuración'!$B$27,'Configuración'!$B$28)) -> 4 | U76: =IF(B76="","",IF(ISNUMBER(SEARCH("CEO",C76))+ISNUMBER(SEARCH("Founder",C76))+ISNUMBER(SEARCH("Owner",C76))+ISNUMBER(SEARCH("Dueño",C76))+ISNUMBER(SEARCH("Director General",C76))+ISNUMBER(SEARCH("Presidente",C76))+ISNUMBER(SEARCH("President",C76))>0,'Configuración'!$B$31,IF(ISNUMBER(SEARCH("CMO",C76))+ISNUMBER(SEARCH("Chief Marketing",C76))+ISNUMBER(SEARCH("VP Marketing",C76))+ISNUMBER(SEARCH("Director de Marketing",C76))+ISNUMBER(SEARCH("Director Marketing",C76))+ISNUMBER(SEARCH("Head of Marketing",C76))+ISNUMBER(SEARCH("Head Marketing",C76))>0,'Configuración'!$B$32,IF(ISNUMBER(SEARCH("Marketing Manager",C76))+ISNUMBER(SEARCH("Gerente de Marketing",C76))+ISNUMBER(SEARCH("Growth Manager",C76))+ISNUMBER(SEARCH("Demand Gen",C76))+ISNUMBER(SEARCH("Marketing Lead",C76))>0,'Configuración'!$B$33,IF(ISNUMBER(SEARCH("COO",C76))+ISNUMBER(SEARCH("CFO",C76))+ISNUMBER(SEARCH("CTO",C76))+ISNUMBER(SEARCH("Chief Operating",C76))+ISNUMBER(SEARCH("Chief Financial",C76))+ISNUMBER(SEARCH("Gerente General",C76))+ISNUMBER(SEARCH("General Manager",C76))>0,'Configuración'!$B$34,'Configuración'!$B$35))))) -> 12 | V76: =IF(B76="","",IF(K76="Sí",'Configuración'!$B$5,0)+IF(L76="Semanal",'Configuración'!$B$6,IF(L76="Mensual",'Configuración'!$B$7,0))+IF(M76="Sí",'Configuración'!$B$8,0)+IF(N76="Sí",'Configuración'!$B$9,0)+IF(O76="Sí",'Configuración'!$B$10,0)+IF(P76="Sí",'Configuración'!$B$11,0)+IF(Q76="Sí",'Configuración'!$B$12,0)+S76+T76+U76) -> 40 | W76: =IF(B76="","",IF(V76>='Configuración'!$B$19,"A",IF(V76>='Configuración'!$B$20,"B",IF(V76>='Configuración'!$B$21,"C","Descarte")))) -> B
A77: =IF(B77="","",ROW()-2) -> 75 | B77: Diego | C77: CEO | D77: ⦵ omnierp.app | E77: diego.avalos@incore.club | F77: http://www.linkedin.com/in/diego-avalos | G77: http://www.linkedin.com/company/controltotal | H77: https://omnierp.app | I77: information technology & services | J77: 2 | K77: No | L77: Inactivo | M77: No | N77: Sí | O77: No | Q77: Sí | R77: Posible Tier 1 | S77: =IF(B77="","",IF(ISNUMBER(J77),IF(J77<=10,'Configuración'!$B$23,IF(J77<=50,'Configuración'!$B$24,IF(J77<=200,'Configuración'!$B$25,0))),0)) -> 12 | T77: =IF(B77="","",IF(ISNUMBER(SEARCH("information technology",I77))+ISNUMBER(SEARCH("software",I77))+ISNUMBER(SEARCH("internet",I77))+ISNUMBER(SEARCH("computer",I77))+ISNUMBER(SEARCH("saas",I77))+ISNUMBER(SEARCH("fintech",I77))+ISNUMBER(SEARCH("information services",I77))+ISNUMBER(SEARCH("telecommunications",I77))>0,'Configuración'!$B$27,'Configuración'!$B$28)) -> 12 | U77: =IF(B77="","",IF(ISNUMBER(SEARCH("CEO",C77))+ISNUMBER(SEARCH("Founder",C77))+ISNUMBER(SEARCH("Owner",C77))+ISNUMBER(SEARCH("Dueño",C77))+ISNUMBER(SEARCH("Director General",C77))+ISNUMBER(SEARCH("Presidente",C77))+ISNUMBER(SEARCH("President",C77))>0,'Configuración'!$B$31,IF(ISNUMBER(SEARCH("CMO",C77))+ISNUMBER(SEARCH("Chief Marketing",C77))+ISNUMBER(SEARCH("VP Marketing",C77))+ISNUMBER(SEARCH("Director de Marketing",C77))+ISNUMBER(SEARCH("Director Marketing",C77))+ISNUMBER(SEARCH("Head of Marketing",C77))+ISNUMBER(SEARCH("Head Marketing",C77))>0,'Configuración'!$B$32,IF(ISNUMBER(SEARCH("Marketing Manager",C77))+ISNUMBER(SEARCH("Gerente de Marketing",C77))+ISNUMBER(SEARCH("Growth Manager",C77))+ISNUMBER(SEARCH("Demand Gen",C77))+ISNUMBER(SEARCH("Marketing Lead",C77))>0,'Configuración'!$B$33,IF(ISNUMBER(SEARCH("COO",C77))+ISNUMBER(SEARCH("CFO",C77))+ISNUMBER(SEARCH("CTO",C77))+ISNUMBER(SEARCH("Chief Operating",C77))+ISNUMBER(SEARCH("Chief Financial",C77))+ISNUMBER(SEARCH("Gerente General",C77))+ISNUMBER(SEARCH("General Manager",C77))>0,'Configuración'!$B$34,'Configuración'!$B$35))))) -> 12 | V77: =IF(B77="","",IF(K77="Sí",'Configuración'!$B$5,0)+IF(L77="Semanal",'Configuración'!$B$6,IF(L77="Mensual",'Configuración'!$B$7,0))+IF(M77="Sí",'Configuración'!$B$8,0)+IF(N77="Sí",'Configuración'!$B$9,0)+IF(O77="Sí",'Configuración'!$B$10,0)+IF(P77="Sí",'Configuración'!$B$11,0)+IF(Q77="Sí",'Configuración'!$B$12,0)+S77+T77+U77) -> 48 | W77: =IF(B77="","",IF(V77>='Configuración'!$B$19,"A",IF(V77>='Configuración'!$B$20,"B",IF(V77>='Configuración'!$B$21,"C","Descarte")))) -> B
A78: =IF(B78="","",ROW()-2) -> 76 | B78: Daniel | C78: Founder & CEO | D78: Creditop | E78: daniel@creditop.com | F78: http://www.linkedin.com/in/daniel-garz%c3%b3n-1a570a70 | G78: http://www.linkedin.com/company/creditopcompany | H78: https://creditop.com | I78: banking | J78: 45 | K78: No | L78: Mensual | M78: Sí | N78: No | O78: No | Q78: No | S78: =IF(B78="","",IF(ISNUMBER(J78),IF(J78<=10,'Configuración'!$B$23,IF(J78<=50,'Configuración'!$B$24,IF(J78<=200,'Configuración'!$B$25,0))),0)) -> 4 | T78: =IF(B78="","",IF(ISNUMBER(SEARCH("information technology",I78))+ISNUMBER(SEARCH("software",I78))+ISNUMBER(SEARCH("internet",I78))+ISNUMBER(SEARCH("computer",I78))+ISNUMBER(SEARCH("saas",I78))+ISNUMBER(SEARCH("fintech",I78))+ISNUMBER(SEARCH("information services",I78))+ISNUMBER(SEARCH("telecommunications",I78))>0,'Configuración'!$B$27,'Configuración'!$B$28)) -> 4 | U78: =IF(B78="","",IF(ISNUMBER(SEARCH("CEO",C78))+ISNUMBER(SEARCH("Founder",C78))+ISNUMBER(SEARCH("Owner",C78))+ISNUMBER(SEARCH("Dueño",C78))+ISNUMBER(SEARCH("Director General",C78))+ISNUMBER(SEARCH("Presidente",C78))+ISNUMBER(SEARCH("President",C78))>0,'Configuración'!$B$31,IF(ISNUMBER(SEARCH("CMO",C78))+ISNUMBER(SEARCH("Chief Marketing",C78))+ISNUMBER(SEARCH("VP Marketing",C78))+ISNUMBER(SEARCH("Director de Marketing",C78))+ISNUMBER(SEARCH("Director Marketing",C78))+ISNUMBER(SEARCH("Head of Marketing",C78))+ISNUMBER(SEARCH("Head Marketing",C78))>0,'Configuración'!$B$32,IF(ISNUMBER(SEARCH("Marketing Manager",C78))+ISNUMBER(SEARCH("Gerente de Marketing",C78))+ISNUMBER(SEARCH("Growth Manager",C78))+ISNUMBER(SEARCH("Demand Gen",C78))+ISNUMBER(SEARCH("Marketing Lead",C78))>0,'Configuración'!$B$33,IF(ISNUMBER(SEARCH("COO",C78))+ISNUMBER(SEARCH("CFO",C78))+ISNUMBER(SEARCH("CTO",C78))+ISNUMBER(SEARCH("Chief Operating",C78))+ISNUMBER(SEARCH("Chief Financial",C78))+ISNUMBER(SEARCH("Gerente General",C78))+ISNUMBER(SEARCH("General Manager",C78))>0,'Configuración'!$B$34,'Configuración'!$B$35))))) -> 12 | V78: =IF(B78="","",IF(K78="Sí",'Configuración'!$B$5,0)+IF(L78="Semanal",'Configuración'!$B$6,IF(L78="Mensual",'Configuración'!$B$7,0))+IF(M78="Sí",'Configuración'!$B$8,0)+IF(N78="Sí",'Configuración'!$B$9,0)+IF(O78="Sí",'Configuración'!$B$10,0)+IF(P78="Sí",'Configuración'!$B$11,0)+IF(Q78="Sí",'Configuración'!$B$12,0)+S78+T78+U78) -> 36 | W78: =IF(B78="","",IF(V78>='Configuración'!$B$19,"A",IF(V78>='Configuración'!$B$20,"B",IF(V78>='Configuración'!$B$21,"C","Descarte")))) -> C
A79: =IF(B79="","",ROW()-2) -> 77 | B79: Gustavo | C79: Gerente General / Founder & CEO | D79: Ajustecol SAS Avalúos Comerciales | E79: gerencia@ajustecol.com | F79: http://www.linkedin.com/in/gustavo-bedoya-nordmann-90065547 | G79: http://www.linkedin.com/company/ajustecol-sas | H79: https://ajustecol.com | I79: management consulting | J79: 6 | K79: No | L79: Mensual | M79: Sí | N79: No | O79: No | Q79: No | S79: =IF(B79="","",IF(ISNUMBER(J79),IF(J79<=10,'Configuración'!$B$23,IF(J79<=50,'Configuración'!$B$24,IF(J79<=200,'Configuración'!$B$25,0))),0)) -> 12 | T79: =IF(B79="","",IF(ISNUMBER(SEARCH("information technology",I79))+ISNUMBER(SEARCH("software",I79))+ISNUMBER(SEARCH("internet",I79))+ISNUMBER(SEARCH("computer",I79))+ISNUMBER(SEARCH("saas",I79))+ISNUMBER(SEARCH("fintech",I79))+ISNUMBER(SEARCH("information services",I79))+ISNUMBER(SEARCH("telecommunications",I79))>0,'Configuración'!$B$27,'Configuración'!$B$28)) -> 4 | U79: =IF(B79="","",IF(ISNUMBER(SEARCH("CEO",C79))+ISNUMBER(SEARCH("Founder",C79))+ISNUMBER(SEARCH("Owner",C79))+ISNUMBER(SEARCH("Dueño",C79))+ISNUMBER(SEARCH("Director General",C79))+ISNUMBER(SEARCH("Presidente",C79))+ISNUMBER(SEARCH("President",C79))>0,'Configuración'!$B$31,IF(ISNUMBER(SEARCH("CMO",C79))+ISNUMBER(SEARCH("Chief Marketing",C79))+ISNUMBER(SEARCH("VP Marketing",C79))+ISNUMBER(SEARCH("Director de Marketing",C79))+ISNUMBER(SEARCH("Director Marketing",C79))+ISNUMBER(SEARCH("Head of Marketing",C79))+ISNUMBER(SEARCH("Head Marketing",C79))>0,'Configuración'!$B$32,IF(ISNUMBER(SEARCH("Marketing Manager",C79))+ISNUMBER(SEARCH("Gerente de Marketing",C79))+ISNUMBER(SEARCH("Growth Manager",C79))+ISNUMBER(SEARCH("Demand Gen",C79))+ISNUMBER(SEARCH("Marketing Lead",C79))>0,'Configuración'!$B$33,IF(ISNUMBER(SEARCH("COO",C79))+ISNUMBER(SEARCH("CFO",C79))+ISNUMBER(SEARCH("CTO",C79))+ISNUMBER(SEARCH("Chief Operating",C79))+ISNUMBER(SEARCH("Chief Financial",C79))+ISNUMBER(SEARCH("Gerente General",C79))+ISNUMBER(SEARCH("General Manager",C79))>0,'Configuración'!$B$34,'Configuración'!$B$35))))) -> 12 | V79: =IF(B79="","",IF(K79="Sí",'Configuración'!$B$5,0)+IF(L79="Semanal",'Configuración'!$B$6,IF(L79="Mensual",'Configuración'!$B$7,0))+IF(M79="Sí",'Configuración'!$B$8,0)+IF(N79="Sí",'Configuración'!$B$9,0)+IF(O79="Sí",'Configuración'!$B$10,0)+IF(P79="Sí",'Configuración'!$B$11,0)+IF(Q79="Sí",'Configuración'!$B$12,0)+S79+T79+U79) -> 44 | W79: =IF(B79="","",IF(V79>='Configuración'!$B$19,"A",IF(V79>='Configuración'!$B$20,"B",IF(V79>='Configuración'!$B$21,"C","Descarte")))) -> B
A80: =IF(B80="","",ROW()-2) -> 78 | B80: Adriana | C80: Founder | D80: Ecolegalia | E80: adrianavergara@ecolegalia.com | F80: http://www.linkedin.com/in/adriana-carolina-vergara-avila-809352a1 | G80: http://www.linkedin.com/company/ecolegalia | H80: https://ecolegalia.com | I80: environmental services | J80: 2 | K80: No | L80: Inactivo | M80: Sí | N80: No | O80: No | Q80: No | S80: =IF(B80="","",IF(ISNUMBER(J80),IF(J80<=10,'Configuración'!$B$23,IF(J80<=50,'Configuración'!$B$24,IF(J80<=200,'Configuración'!$B$25,0))),0)) -> 12 | T80: =IF(B80="","",IF(ISNUMBER(SEARCH("information technology",I80))+ISNUMBER(SEARCH("software",I80))+ISNUMBER(SEARCH("internet",I80))+ISNUMBER(SEARCH("computer",I80))+ISNUMBER(SEARCH("saas",I80))+ISNUMBER(SEARCH("fintech",I80))+ISNUMBER(SEARCH("information services",I80))+ISNUMBER(SEARCH("telecommunications",I80))>0,'Configuración'!$B$27,'Configuración'!$B$28)) -> 4 | U80: =IF(B80="","",IF(ISNUMBER(SEARCH("CEO",C80))+ISNUMBER(SEARCH("Founder",C80))+ISNUMBER(SEARCH("Owner",C80))+ISNUMBER(SEARCH("Dueño",C80))+ISNUMBER(SEARCH("Director General",C80))+ISNUMBER(SEARCH("Presidente",C80))+ISNUMBER(SEARCH("President",C80))>0,'Configuración'!$B$31,IF(ISNUMBER(SEARCH("CMO",C80))+ISNUMBER(SEARCH("Chief Marketing",C80))+ISNUMBER(SEARCH("VP Marketing",C80))+ISNUMBER(SEARCH("Director de Marketing",C80))+ISNUMBER(SEARCH("Director Marketing",C80))+ISNUMBER(SEARCH("Head of Marketing",C80))+ISNUMBER(SEARCH("Head Marketing",C80))>0,'Configuración'!$B$32,IF(ISNUMBER(SEARCH("Marketing Manager",C80))+ISNUMBER(SEARCH("Gerente de Marketing",C80))+ISNUMBER(SEARCH("Growth Manager",C80))+ISNUMBER(SEARCH("Demand Gen",C80))+ISNUMBER(SEARCH("Marketing Lead",C80))>0,'Configuración'!$B$33,IF(ISNUMBER(SEARCH("COO",C80))+ISNUMBER(SEARCH("CFO",C80))+ISNUMBER(SEARCH("CTO",C80))+ISNUMBER(SEARCH("Chief Operating",C80))+ISNUMBER(SEARCH("Chief Financial",C80))+ISNUMBER(SEARCH("Gerente General",C80))+ISNUMBER(SEARCH("General Manager",C80))>0,'Configuración'!$B$34,'Configuración'!$B$35))))) -> 12 | V80: =IF(B80="","",IF(K80="Sí",'Configuración'!$B$5,0)+IF(L80="Semanal",'Configuración'!$B$6,IF(L80="Mensual",'Configuración'!$B$7,0))+IF(M80="Sí",'Configuración'!$B$8,0)+IF(N80="Sí",'Configuración'!$B$9,0)+IF(O80="Sí",'Configuración'!$B$10,0)+IF(P80="Sí",'Configuración'!$B$11,0)+IF(Q80="Sí",'Configuración'!$B$12,0)+S80+T80+U80) -> 40 | W80: =IF(B80="","",IF(V80>='Configuración'!$B$19,"A",IF(V80>='Configuración'!$B$20,"B",IF(V80>='Configuración'!$B$21,"C","Descarte")))) -> B
